Workbook

Sheet 0% Grant, BVGEC recoup via Mixt
A2: Capacity Factor | B2: 0.17 | D2: Norfolk | E2: 0.33
A3: System Output | B3: 65000 | D3: BVGEC | E3: 0.33
A4: Hours per Year | B4: 8766 | D4: Community | E4: =1-E2-E3 -> 0.34
A5: System Size | B5: =$B$3/$B$4/$B$2 -> 43.617721
A6: Install Cost | B6: 2.5
A7: Capex | B7: =B5*B6*1000 -> 109044.3
A8: Degradation | B8: 0.005
A9: Inflation | B9: 0.03
A10: Admin Rate | B10: =$E$11 -> 0.0055 | D10: Combined OPEX Rate | E10: 0.0165
A11: Insurance Rate | B11: =$E$11 -> 0.0055 | D11: Individual | E11: =E10/3 -> 0.0055
A12: Maintenance Rate | B12: =$E$11 -> 0.0055
A13: CCA Rate | B13: 0.3
A14: Half Year Rule | B14: 0.5
A15: Grant Rate | B15: 0 | L15: Current Bill | M15: ='Bill Comparison'!F28 -> 322479.95
A16: Grant Amount | B16: =B7*B15 -> 0 | L16: New Bill | M16: ='Bill Comparison'!J28 -> 49771.697 | N16: Benefit Dist | O16: Annuity
A17: Net Capex | B17: =B7-B16 -> 109044.3 | L17: Available Savings | M17: ='Bill Comparison'!L28 -> 272708.26 | R17: Bill Saving | S17: =1-(I56+M16)/M15 -> -0.10394169
A18: Debt Rate | B18: 0.04 | L18: Norfolk Bill Savings | M18: =M17-I56 -> -33519.112 | N18: =M18/M19 -> -0.2948195
A19: Debt Term | B19: 10 | L19: Total Benefit | M19: =M18+T56+G56 -> 113693.67 | R19: Effective Savings | S19: =1-(M16+I56-M21)/M15 -> 0.012403253
L20: Norfolk Residual | M20: =M19*0.33-M18 -> 71038.024
L21: Norfolk Total | M21: =M18+M20 -> 37518.912 | N21: =M21/M19 -> 0.33 | O21: =M21/25 -> 1500.7565
A22: Repayment Start | B22: 3 | L22: BVGEC Residual | M22: =M19*0.45-G56 -> -14436.485
L23: BVGEC Total | M23: =M22+G56 -> 51162.153 | N23: =M23/M19 -> 0.45 | O23: =M23/25 -> 2046.4861
A24: Repayment Principal | B24: =B17/B19 -> 10904.43 | L24: Community | M24: =M19-M21-M23 -> 25012.608 | N24: =M24/M19 -> 0.22 | O24: =M24/25 -> 1000.5043
A25: Tax Rate | B25: 0.23 | N25: =N21+N23+N24 -> 1
A26: ITC Rate | B26: 0.3
A27: ITC Amount | B27: =B26*B17 -> 32713.291 | L27: Utilization | M27: =M19/M17 -> 0.41690587
A28: ITC year | B28: 1
H29: Effective PPA | I29: 0.2
A30: Year | B30: Effective Output | C30: Escalation Factor | D30: Admin Cost | E30: Insurance Cost | F30: Maintenance Cost | G30: OPEX | H30: Capital Cost Allowance | I30: Maxmimum Revenue | J30: Debt Principal | K30: Debt Interest | L30: ITC Credit | M30: Pre Tax Operating Cashflow | N30: Taxable Income Before Carry Forward Loss | O30: Carry Forward Losses | P30: Taxable Income After Carry Forward Loss | Q30: Tax | R30: After Tax Income | S30: Principal Repayent | T30: Cashflow To Equity
A31: 0 | B31: =POWER(1-$B$8,A31)*$B$3 -> 65000 | C31: =POWER(1+$B$9,A31) -> 1 | D31: =$B$7*C31*$B$10 -> 599.74366 | E31: =$B$7*$C31*$B$11 -> 599.74366 | F31: =$B$7*$C31*$B$12 -> 599.74366 | G31: =SUM(D31:F31) -> 1799.231 | H31: =IF(A31=0,$B$17*$B$14*$B$13,H30*$B$13) -> 16356.645 | I31: =$I$29*B31 -> 13000 | J31: =MAX(IF(A31>=$B$22,J30-$B$24,$B$17),0) -> 109044.3 | K31: =IF(A31>=$B$20,J31*$B$18,0) -> 4361.7721 | L31: =IF(A31=$B$28,$B$27,0) -> 0 | M31: =I31-G31-K31+L31 -> 6838.9969 | N31: =M31-H31 -> -9517.6484 | O31: =IF(N31<0,N31,0) -> -9517.6484 | P31: =N31-O31 -> 0 | Q31: =$B$25*P31 -> 0 | R31: =M31-Q31 -> 6838.9969 | S31: =IFERROR(__xludf.DUMMYFUNCTION("IF(ISBETWEEN(A31,$B$22,$B$22+$B$19-1),$B$24,0)"),0.0) -> 0 | T31: =R31-S31 -> 6838.9969 | U31: =T31 -> 6838.9969
A32: 1 | B32: =POWER(1-$B$8,A32)*$B$3 -> 64675 | C32: =POWER(1+$B$9,A32) -> 1.03 | D32: =$B$7*C32*$B$10 -> 617.73597 | E32: =$B$7*$C32*$B$11 -> 617.73597 | F32: =$B$7*$C32*$B$12 -> 617.73597 | G32: =SUM(D32:F32) -> 1853.2079 | H32: =IF(A32=0,$B$17*$B$14*$B$13,H31*$B$13) -> 4906.9936 | I32: =$I$29*B32 -> 12935 | J32: =MAX(IF(A32>=$B$22,J31-$B$24,$B$17),0) -> 109044.3 | K32: =IF(A32>=$B$20,J32*$B$18,0) -> 4361.7721 | L32: =IF(A32=$B$28,$B$27,0) -> 32713.291 | M32: =I32-G32-K32+L32 -> 39433.311 | N32: =M32-H32 -> 34526.317 | O32: =IF(N32<0,N32,0) -> 0 | P32: =IF(N32>0,N32+O31,0) -> 25008.669 | Q32: =$B$25*P32 -> 5751.9938 | R32: =M32-Q32 -> 33681.317 | S32: =IFERROR(__xludf.DUMMYFUNCTION("IF(ISBETWEEN(A32,$B$22,$B$22+$B$19-1),$B$24,0)"),0.0) -> 0 | T32: =R32-S32 -> 33681.317 | U32: =T32+U31 -> 40520.314
A33: 2 | B33: =POWER(1-$B$8,A33)*$B$3 -> 64351.625 | C33: =POWER(1+$B$9,A33) -> 1.0609 | D33: =$B$7*C33*$B$10 -> 636.26805 | E33: =$B$7*$C33*$B$11 -> 636.26805 | F33: =$B$7*$C33*$B$12 -> 636.26805 | G33: =SUM(D33:F33) -> 1908.8042 | H33: =IF(A33=0,$B$17*$B$14*$B$13,H32*$B$13) -> 1472.0981 | I33: =$I$29*B33 -> 12870.325 | J33: =MAX(IF(A33>=$B$22,J32-$B$24,$B$17),0) -> 109044.3 | K33: =IF(A33>=$B$20,J33*$B$18,0) -> 4361.7721 | L33: =IF(A33=$B$28,$B$27,0) -> 0 | M33: =I33-G33-K33+L33 -> 6599.7488 | N33: =M33-H33 -> 5127.6507 | O33: =IF(N33<0,N33,0) -> 0 | P33: =IF(N33>0,N33+O32,0) -> 5127.6507 | Q33: =$B$25*P33 -> 1179.3597 | R33: =M33-Q33 -> 5420.3891 | S33: =IFERROR(__xludf.DUMMYFUNCTION("IF(ISBETWEEN(A33,$B$22,$B$22+$B$19-1),$B$24,0)"),0.0) -> 0 | T33: =R33-S33 -> 5420.3891 | U33: =T33+U32 -> 45940.703
A34: 3 | B34: =POWER(1-$B$8,A34)*$B$3 -> 64029.867 | C34: =POWER(1+$B$9,A34) -> 1.092727 | D34: =$B$7*C34*$B$10 -> 655.35609 | E34: =$B$7*$C34*$B$11 -> 655.35609 | F34: =$B$7*$C34*$B$12 -> 655.35609 | G34: =SUM(D34:F34) -> 1966.0683 | H34: =IF(A34=0,$B$17*$B$14*$B$13,H33*$B$13) -> 441.62942 | I34: =$I$29*B34 -> 12805.973 | J34: =MAX(IF(A34>=$B$22,J33-$B$24,$B$17),0) -> 98139.872 | K34: =IF(A34>=$B$20,J34*$B$18,0) -> 3925.5949 | L34: =IF(A34=$B$28,$B$27,0) -> 0 | M34: =I34-G34-K34+L34 -> 6914.3102 | N34: =M34-H34 -> 6472.6808 | O34: =IF(N34<0,N34,0) -> 0 | P34: =IF(N34>0,N34+O33,0) -> 6472.6808 | Q34: =$B$25*P34 -> 1488.7166 | R34: =M34-Q34 -> 5425.5936 | S34: =IFERROR(__xludf.DUMMYFUNCTION("IF(ISBETWEEN(A34,$B$22,$B$22+$B$19-1),$B$24,0)"),10904.430218357022) -> 10904.43 | T34: =R34-S34 -> -5478.8366 | U34: =T34+U33 -> 40461.866
A35: 4 | B35: =POWER(1-$B$8,A35)*$B$3 -> 63709.718 | C35: =POWER(1+$B$9,A35) -> 1.1255088 | D35: =$B$7*C35*$B$10 -> 675.01678 | E35: =$B$7*$C35*$B$11 -> 675.01678 | F35: =$B$7*$C35*$B$12 -> 675.01678 | G35: =SUM(D35:F35) -> 2025.0503 | H35: =IF(A35=0,$B$17*$B$14*$B$13,H34*$B$13) -> 132.48883 | I35: =$I$29*B35 -> 12741.944 | J35: =MAX(IF(A35>=$B$22,J34-$B$24,$B$17),0) -> 87235.442 | K35: =IF(A35>=$B$20,J35*$B$18,0) -> 3489.4177 | L35: =IF(A35=$B$28,$B$27,0) -> 0 | M35: =I35-G35-K35+L35 -> 7227.4755 | N35: =M35-H35 -> 7094.9867 | O35: =IF(N35<0,N35,0) -> 0 | P35: =IF(N35>0,N35+O34,0) -> 7094.9867 | Q35: =$B$25*P35 -> 1631.8469 | R35: =M35-Q35 -> 5595.6286 | S35: =IFERROR(__xludf.DUMMYFUNCTION("IF(ISBETWEEN(A35,$B$22,$B$22+$B$19-1),$B$24,0)"),10904.430218357022) -> 10904.43 | T35: =R35-S35 -> -5308.8016 | U35: =T35+U34 -> 35153.065
A36: 5 | B36: =POWER(1-$B$8,A36)*$B$3 -> 63391.169 | C36: =POWER(1+$B$9,A36) -> 1.1592741 | D36: =$B$7*C36*$B$10 -> 695.26728 | E36: =$B$7*$C36*$B$11 -> 695.26728 | F36: =$B$7*$C36*$B$12 -> 695.26728 | G36: =SUM(D36:F36) -> 2085.8018 | H36: =IF(A36=0,$B$17*$B$14*$B$13,H35*$B$13) -> 39.746648 | I36: =$I$29*B36 -> 12678.234 | J36: =MAX(IF(A36>=$B$22,J35-$B$24,$B$17),0) -> 76331.012 | K36: =IF(A36>=$B$20,J36*$B$18,0) -> 3053.2405 | L36: =IF(A36=$B$28,$B$27,0) -> 0 | M36: =I36-G36-K36+L36 -> 7539.1915 | N36: =M36-H36 -> 7499.4448 | O36: =IF(N36<0,N36,0) -> 0 | P36: =IF(N36>0,N36+O35,0) -> 7499.4448 | Q36: =$B$25*P36 -> 1724.8723 | R36: =M36-Q36 -> 5814.3192 | S36: =IFERROR(__xludf.DUMMYFUNCTION("IF(ISBETWEEN(A36,$B$22,$B$22+$B$19-1),$B$24,0)"),10904.430218357022) -> 10904.43 | T36: =R36-S36 -> -5090.111 | U36: =T36+U35 -> 30062.954
A37: 6 | B37: =POWER(1-$B$8,A37)*$B$3 -> 63074.213 | C37: =POWER(1+$B$9,A37) -> 1.1940523 | D37: =$B$7*C37*$B$10 -> 716.1253 | E37: =$B$7*$C37*$B$11 -> 716.1253 | F37: =$B$7*$C37*$B$12 -> 716.1253 | G37: =SUM(D37:F37) -> 2148.3759 | H37: =IF(A37=0,$B$17*$B$14*$B$13,H36*$B$13) -> 11.923994 | I37: =$I$29*B37 -> 12614.843 | J37: =MAX(IF(A37>=$B$22,J36-$B$24,$B$17),0) -> 65426.581 | K37: =IF(A37>=$B$20,J37*$B$18,0) -> 2617.0633 | L37: =IF(A37=$B$28,$B$27,0) -> 0 | M37: =I37-G37-K37+L37 -> 7849.4035 | N37: =M37-H37 -> 7837.4795 | O37: =IF(N37<0,N37,0) -> 0 | P37: =IF(N37>0,N37+O36,0) -> 7837.4795 | Q37: =$B$25*P37 -> 1802.6203 | R37: =M37-Q37 -> 6046.7832 | S37: =IFERROR(__xludf.DUMMYFUNCTION("IF(ISBETWEEN(A37,$B$22,$B$22+$B$19-1),$B$24,0)"),10904.430218357022) -> 10904.43 | T37: =R37-S37 -> -4857.647 | U37: =T37+U36 -> 25205.307
A38: 7 | B38: =POWER(1-$B$8,A38)*$B$3 -> 62758.842 | C38: =POWER(1+$B$9,A38) -> 1.2298739 | D38: =$B$7*C38*$B$10 -> 737.60906 | E38: =$B$7*$C38*$B$11 -> 737.60906 | F38: =$B$7*$C38*$B$12 -> 737.60906 | G38: =SUM(D38:F38) -> 2212.8272 | H38: =IF(A38=0,$B$17*$B$14*$B$13,H37*$B$13) -> 3.5771983 | I38: =$I$29*B38 -> 12551.768 | J38: =MAX(IF(A38>=$B$22,J37-$B$24,$B$17),0) -> 54522.151 | K38: =IF(A38>=$B$20,J38*$B$18,0) -> 2180.886 | L38: =IF(A38=$B$28,$B$27,0) -> 0 | M38: =I38-G38-K38+L38 -> 8158.0552 | N38: =M38-H38 -> 8154.478 | O38: =IF(N38<0,N38,0) -> 0 | P38: =IF(N38>0,N38+O37,0) -> 8154.478 | Q38: =$B$25*P38 -> 1875.5299 | R38: =M38-Q38 -> 6282.5253 | S38: =IFERROR(__xludf.DUMMYFUNCTION("IF(ISBETWEEN(A38,$B$22,$B$22+$B$19-1),$B$24,0)"),10904.430218357022) -> 10904.43 | T38: =R38-S38 -> -4621.905 | U38: =T38+U37 -> 20583.402
A39: 8 | B39: =POWER(1-$B$8,A39)*$B$3 -> 62445.048 | C39: =POWER(1+$B$9,A39) -> 1.2667701 | D39: =$B$7*C39*$B$10 -> 759.73733 | E39: =$B$7*$C39*$B$11 -> 759.73733 | F39: =$B$7*$C39*$B$12 -> 759.73733 | G39: =SUM(D39:F39) -> 2279.212 | H39: =IF(A39=0,$B$17*$B$14*$B$13,H38*$B$13) -> 1.0731595 | I39: =$I$29*B39 -> 12489.01 | J39: =MAX(IF(A39>=$B$22,J38-$B$24,$B$17),0) -> 43617.721 | K39: =IF(A39>=$B$20,J39*$B$18,0) -> 1744.7088 | L39: =IF(A39=$B$28,$B$27,0) -> 0 | M39: =I39-G39-K39+L39 -> 8465.0887 | N39: =M39-H39 -> 8464.0156 | O39: =IF(N39<0,N39,0) -> 0 | P39: =IF(N39>0,N39+O38,0) -> 8464.0156 | Q39: =$B$25*P39 -> 1946.7236 | R39: =M39-Q39 -> 6518.3652 | S39: =IFERROR(__xludf.DUMMYFUNCTION("IF(ISBETWEEN(A39,$B$22,$B$22+$B$19-1),$B$24,0)"),10904.430218357022) -> 10904.43 | T39: =R39-S39 -> -4386.0651 | U39: =T39+U38 -> 16197.337
A40: 9 | B40: =POWER(1-$B$8,A40)*$B$3 -> 62132.823 | C40: =POWER(1+$B$9,A40) -> 1.3047732 | D40: =$B$7*C40*$B$10 -> 782.52945 | E40: =$B$7*$C40*$B$11 -> 782.52945 | F40: =$B$7*$C40*$B$12 -> 782.52945 | G40: =SUM(D40:F40) -> 2347.5883 | H40: =IF(A40=0,$B$17*$B$14*$B$13,H39*$B$13) -> 0.32194785 | I40: =$I$29*B40 -> 12426.565 | J40: =MAX(IF(A40>=$B$22,J39-$B$24,$B$17),0) -> 32713.291 | K40: =IF(A40>=$B$20,J40*$B$18,0) -> 1308.5316 | L40: =IF(A40=$B$28,$B$27,0) -> 0 | M40: =I40-G40-K40+L40 -> 8770.4446 | N40: =M40-H40 -> 8770.1226 | O40: =IF(N40<0,N40,0) -> 0 | P40: =IF(N40>0,N40+O39,0) -> 8770.1226 | Q40: =$B$25*P40 -> 2017.1282 | R40: =M40-Q40 -> 6753.3164 | S40: =IFERROR(__xludf.DUMMYFUNCTION("IF(ISBETWEEN(A40,$B$22,$B$22+$B$19-1),$B$24,0)"),10904.430218357022) -> 10904.43 | T40: =R40-S40 -> -4151.1139 | U40: =T40+U39 -> 12046.223
A41: 10 | B41: =POWER(1-$B$8,A41)*$B$3 -> 61822.158 | C41: =POWER(1+$B$9,A41) -> 1.3439164 | D41: =$B$7*C41*$B$10 -> 806.00533 | E41: =$B$7*$C41*$B$11 -> 806.00533 | F41: =$B$7*$C41*$B$12 -> 806.00533 | G41: =SUM(D41:F41) -> 2418.016 | H41: =IF(A41=0,$B$17*$B$14*$B$13,H40*$B$13) -> 0.096584355 | I41: =$I$29*B41 -> 12364.432 | J41: =MAX(IF(A41>=$B$22,J40-$B$24,$B$17),0) -> 21808.86 | K41: =IF(A41>=$B$20,J41*$B$18,0) -> 872.35442 | L41: =IF(A41=$B$28,$B$27,0) -> 0 | M41: =I41-G41-K41+L41 -> 9074.0613 | N41: =M41-H41 -> 9073.9647 | O41: =IF(N41<0,N41,0) -> 0 | P41: =IF(N41>0,N41+O40,0) -> 9073.9647 | Q41: =$B$25*P41 -> 2087.0119 | R41: =M41-Q41 -> 6987.0494 | S41: =IFERROR(__xludf.DUMMYFUNCTION("IF(ISBETWEEN(A41,$B$22,$B$22+$B$19-1),$B$24,0)"),10904.430218357022) -> 10904.43 | T41: =R41-S41 -> -3917.3808 | U41: =T41+U40 -> 8128.8419
A42: 11 | B42: =POWER(1-$B$8,A42)*$B$3 -> 61513.048 | C42: =POWER(1+$B$9,A42) -> 1.3842339 | D42: =$B$7*C42*$B$10 -> 830.18549 | E42: =$B$7*$C42*$B$11 -> 830.18549 | F42: =$B$7*$C42*$B$12 -> 830.18549 | G42: =SUM(D42:F42) -> 2490.5565 | H42: =IF(A42=0,$B$17*$B$14*$B$13,H41*$B$13) -> 0.028975306 | I42: =$I$29*B42 -> 12302.61 | J42: =MAX(IF(A42>=$B$22,J41-$B$24,$B$17),0) -> 10904.43 | K42: =IF(A42>=$B$20,J42*$B$18,0) -> 436.17721 | L42: =IF(A42=$B$28,$B$27,0) -> 0 | M42: =I42-G42-K42+L42 -> 9375.8759 | N42: =M42-H42 -> 9375.8469 | O42: =IF(N42<0,N42,0) -> 0 | P42: =IF(N42>0,N42+O41,0) -> 9375.8469 | Q42: =$B$25*P42 -> 2156.4448 | R42: =M42-Q42 -> 7219.4311 | S42: =IFERROR(__xludf.DUMMYFUNCTION("IF(ISBETWEEN(A42,$B$22,$B$22+$B$19-1),$B$24,0)"),10904.430218357022) -> 10904.43 | T42: =R42-S42 -> -3684.9991 | U42: =T42+U41 -> 4443.8428
A43: 12 | B43: =POWER(1-$B$8,A43)*$B$3 -> 61205.482 | C43: =POWER(1+$B$9,A43) -> 1.4257609 | D43: =$B$7*C43*$B$10 -> 855.09106 | E43: =$B$7*$C43*$B$11 -> 855.09106 | F43: =$B$7*$C43*$B$12 -> 855.09106 | G43: =SUM(D43:F43) -> 2565.2732 | H43: =IF(A43=0,$B$17*$B$14*$B$13,H42*$B$13) -> 0.008692592 | I43: =$I$29*B43 -> 12241.096 | J43: =MAX(IF(A43>=$B$22,J42-$B$24,$B$17),0) -> 0 | K43: =IF(A43>=$B$20,J43*$B$18,0) -> 0 | L43: =IF(A43=$B$28,$B$27,0) -> 0 | M43: =I43-G43-K43+L43 -> 9675.8233 | N43: =M43-H43 -> 9675.8146 | O43: =IF(N43<0,N43,0) -> 0 | P43: =IF(N43>0,N43+O42,0) -> 9675.8146 | Q43: =$B$25*P43 -> 2225.4374 | R43: =M43-Q43 -> 7450.386 | S43: =IFERROR(__xludf.DUMMYFUNCTION("IF(ISBETWEEN(A43,$B$22,$B$22+$B$19-1),$B$24,0)"),10904.430218357022) -> 10904.43 | T43: =R43-S43 -> -3454.0443 | U43: =T43+U42 -> 989.7985
A44: 13 | B44: =POWER(1-$B$8,A44)*$B$3 -> 60899.455 | C44: =POWER(1+$B$9,A44) -> 1.4685337 | D44: =$B$7*C44*$B$10 -> 880.74379 | E44: =$B$7*$C44*$B$11 -> 880.74379 | F44: =$B$7*$C44*$B$12 -> 880.74379 | G44: =SUM(D44:F44) -> 2642.2314 | H44: =IF(A44=0,$B$17*$B$14*$B$13,H43*$B$13) -> 0.0026077776 | I44: =$I$29*B44 -> 12179.891 | J44: =MAX(IF(A44>=$B$22,J43-$B$24,$B$17),0) -> 0 | K44: =IF(A44>=$B$20,J44*$B$18,0) -> 0 | L44: =IF(A44=$B$28,$B$27,0) -> 0 | M44: =I44-G44-K44+L44 -> 9537.6596 | N44: =M44-H44 -> 9537.657 | O44: =IF(N44<0,N44,0) -> 0 | P44: =IF(N44>0,N44+O43,0) -> 9537.657 | Q44: =$B$25*P44 -> 2193.6611 | R44: =M44-Q44 -> 7343.9985 | S44: =IFERROR(__xludf.DUMMYFUNCTION("IF(ISBETWEEN(A44,$B$22,$B$22+$B$19-1),$B$24,0)"),0.0) -> 0 | T44: =R44-S44 -> 7343.9985 | U44: =T44+U43 -> 8333.797
A45: 14 | B45: =POWER(1-$B$8,A45)*$B$3 -> 60594.958 | C45: =POWER(1+$B$9,A45) -> 1.5125897 | D45: =$B$7*C45*$B$10 -> 907.1661 | E45: =$B$7*$C45*$B$11 -> 907.1661 | F45: =$B$7*$C45*$B$12 -> 907.1661 | G45: =SUM(D45:F45) -> 2721.4983 | H45: =IF(A45=0,$B$17*$B$14*$B$13,H44*$B$13) -> 0.00078233328 | I45: =$I$29*B45 -> 12118.992 | J45: =MAX(IF(A45>=$B$22,J44-$B$24,$B$17),0) -> 0 | K45: =IF(A45>=$B$20,J45*$B$18,0) -> 0 | L45: =IF(A45=$B$28,$B$27,0) -> 0 | M45: =I45-G45-K45+L45 -> 9397.4932 | N45: =M45-H45 -> 9397.4925 | O45: =IF(N45<0,N45,0) -> 0 | P45: =IF(N45>0,N45+O44,0) -> 9397.4925 | Q45: =$B$25*P45 -> 2161.4233 | R45: =M45-Q45 -> 7236.07 | S45: =IFERROR(__xludf.DUMMYFUNCTION("IF(ISBETWEEN(A45,$B$22,$B$22+$B$19-1),$B$24,0)"),0.0) -> 0 | T45: =R45-S45 -> 7236.07 | U45: =T45+U44 -> 15569.867
A46: 15 | B46: =POWER(1-$B$8,A46)*$B$3 -> 60291.983 | C46: =POWER(1+$B$9,A46) -> 1.5579674 | D46: =$B$7*C46*$B$10 -> 934.38108 | E46: =$B$7*$C46*$B$11 -> 934.38108 | F46: =$B$7*$C46*$B$12 -> 934.38108 | G46: =SUM(D46:F46) -> 2803.1433 | H46: =IF(A46=0,$B$17*$B$14*$B$13,H45*$B$13) -> 0.00023469998 | I46: =$I$29*B46 -> 12058.397 | J46: =MAX(IF(A46>=$B$22,J45-$B$24,$B$17),0) -> 0 | K46: =IF(A46>=$B$20,J46*$B$18,0) -> 0 | L46: =IF(A46=$B$28,$B$27,0) -> 0 | M46: =I46-G46-K46+L46 -> 9255.2533 | N46: =M46-H46 -> 9255.2531 | O46: =IF(N46<0,N46,0) -> 0 | P46: =IF(N46>0,N46+O45,0) -> 9255.2531 | Q46: =$B$25*P46 -> 2128.7082 | R46: =M46-Q46 -> 7126.5451 | S46: =IFERROR(__xludf.DUMMYFUNCTION("IF(ISBETWEEN(A46,$B$22,$B$22+$B$19-1),$B$24,0)"),0.0) -> 0 | T46: =R46-S46 -> 7126.5451 | U46: =T46+U45 -> 22696.412
A47: 16 | B47: =POWER(1-$B$8,A47)*$B$3 -> 59990.523 | C47: =POWER(1+$B$9,A47) -> 1.6047064 | D47: =$B$7*C47*$B$10 -> 962.41252 | E47: =$B$7*$C47*$B$11 -> 962.41252 | F47: =$B$7*$C47*$B$12 -> 962.41252 | G47: =SUM(D47:F47) -> 2887.2375 | H47: =IF(A47=0,$B$17*$B$14*$B$13,H46*$B$13) -> 7.0409995e-05 | I47: =$I$29*B47 -> 11998.105 | J47: =MAX(IF(A47>=$B$22,J46-$B$24,$B$17),0) -> 0 | K47: =IF(A47>=$B$20,J47*$B$18,0) -> 0 | L47: =IF(A47=$B$28,$B$27,0) -> 0 | M47: =I47-G47-K47+L47 -> 9110.8671 | N47: =M47-H47 -> 9110.867 | O47: =IF(N47<0,N47,0) -> 0 | P47: =IF(N47>0,N47+O46,0) -> 9110.867 | Q47: =$B$25*P47 -> 2095.4994 | R47: =M47-Q47 -> 7015.3677 | S47: =IFERROR(__xludf.DUMMYFUNCTION("IF(ISBETWEEN(A47,$B$22,$B$22+$B$19-1),$B$24,0)"),0.0) -> 0 | T47: =R47-S47 -> 7015.3677 | U47: =T47+U46 -> 29711.78
A48: 17 | B48: =POWER(1-$B$8,A48)*$B$3 -> 59690.57 | C48: =POWER(1+$B$9,A48) -> 1.6528476 | D48: =$B$7*C48*$B$10 -> 991.28489 | E48: =$B$7*$C48*$B$11 -> 991.28489 | F48: =$B$7*$C48*$B$12 -> 991.28489 | G48: =SUM(D48:F48) -> 2973.8547 | H48: =IF(A48=0,$B$17*$B$14*$B$13,H47*$B$13) -> 2.1122998e-05 | I48: =$I$29*B48 -> 11938.114 | J48: =MAX(IF(A48>=$B$22,J47-$B$24,$B$17),0) -> 0 | K48: =IF(A48>=$B$20,J48*$B$18,0) -> 0 | L48: =IF(A48=$B$28,$B$27,0) -> 0 | M48: =I48-G48-K48+L48 -> 8964.2594 | N48: =M48-H48 -> 8964.2594 | O48: =IF(N48<0,N48,0) -> 0 | P48: =IF(N48>0,N48+O47,0) -> 8964.2594 | Q48: =$B$25*P48 -> 2061.7797 | R48: =M48-Q48 -> 6902.4798 | S48: =IFERROR(__xludf.DUMMYFUNCTION("IF(ISBETWEEN(A48,$B$22,$B$22+$B$19-1),$B$24,0)"),0.0) -> 0 | T48: =R48-S48 -> 6902.4798 | U48: =T48+U47 -> 36614.26
A49: 18 | B49: =POWER(1-$B$8,A49)*$B$3 -> 59392.118 | C49: =POWER(1+$B$9,A49) -> 1.7024331 | D49: =$B$7*C49*$B$10 -> 1021.0234 | E49: =$B$7*$C49*$B$11 -> 1021.0234 | F49: =$B$7*$C49*$B$12 -> 1021.0234 | G49: =SUM(D49:F49) -> 3063.0703 | H49: =IF(A49=0,$B$17*$B$14*$B$13,H48*$B$13) -> 6.3368995e-06 | I49: =$I$29*B49 -> 11878.424 | J49: =MAX(IF(A49>=$B$22,J48-$B$24,$B$17),0) -> 0 | K49: =IF(A49>=$B$20,J49*$B$18,0) -> 0 | L49: =IF(A49=$B$28,$B$27,0) -> 0 | M49: =I49-G49-K49+L49 -> 8815.3532 | N49: =M49-H49 -> 8815.3532 | O49: =IF(N49<0,N49,0) -> 0 | P49: =IF(N49>0,N49+O48,0) -> 8815.3532 | Q49: =$B$25*P49 -> 2027.5312 | R49: =M49-Q49 -> 6787.822 | S49: =IFERROR(__xludf.DUMMYFUNCTION("IF(ISBETWEEN(A49,$B$22,$B$22+$B$19-1),$B$24,0)"),0.0) -> 0 | T49: =R49-S49 -> 6787.822 | U49: =T49+U48 -> 43402.082
A50: 19 | B50: =POWER(1-$B$8,A50)*$B$3 -> 59095.157 | C50: =POWER(1+$B$9,A50) -> 1.7535061 | D50: =$B$7*C50*$B$10 -> 1051.6541 | E50: =$B$7*$C50*$B$11 -> 1051.6541 | F50: =$B$7*$C50*$B$12 -> 1051.6541 | G50: =SUM(D50:F50) -> 3154.9624 | H50: =IF(A50=0,$B$17*$B$14*$B$13,H49*$B$13) -> 1.9010699e-06 | I50: =$I$29*B50 -> 11819.031 | J50: =MAX(IF(A50>=$B$22,J49-$B$24,$B$17),0) -> 0 | K50: =IF(A50>=$B$20,J50*$B$18,0) -> 0 | L50: =IF(A50=$B$28,$B$27,0) -> 0 | M50: =I50-G50-K50+L50 -> 8664.069 | N50: =M50-H50 -> 8664.069 | O50: =IF(N50<0,N50,0) -> 0 | P50: =IF(N50>0,N50+O49,0) -> 8664.069 | Q50: =$B$25*P50 -> 1992.7359 | R50: =M50-Q50 -> 6671.3331 | S50: =IFERROR(__xludf.DUMMYFUNCTION("IF(ISBETWEEN(A50,$B$22,$B$22+$B$19-1),$B$24,0)"),0.0) -> 0 | T50: =R50-S50 -> 6671.3331 | U50: =T50+U49 -> 50073.415
A51: 20 | B51: =POWER(1-$B$8,A51)*$B$3 -> 58799.681 | C51: =POWER(1+$B$9,A51) -> 1.8061112 | D51: =$B$7*C51*$B$10 -> 1083.2038 | E51: =$B$7*$C51*$B$11 -> 1083.2038 | F51: =$B$7*$C51*$B$12 -> 1083.2038 | G51: =SUM(D51:F51) -> 3249.6113 | H51: =IF(A51=0,$B$17*$B$14*$B$13,H50*$B$13) -> 5.7032096e-07 | I51: =$I$29*B51 -> 11759.936 | J51: =MAX(IF(A51>=$B$22,J50-$B$24,$B$17),0) -> 0 | K51: =IF(A51>=$B$20,J51*$B$18,0) -> 0 | L51: =IF(A51=$B$28,$B$27,0) -> 0 | M51: =I51-G51-K51+L51 -> 8510.3249 | N51: =M51-H51 -> 8510.3249 | O51: =IF(N51<0,N51,0) -> 0 | P51: =IF(N51>0,N51+O50,0) -> 8510.3249 | Q51: =$B$25*P51 -> 1957.3747 | R51: =M51-Q51 -> 6552.9502 | S51: =IFERROR(__xludf.DUMMYFUNCTION("IF(ISBETWEEN(A51,$B$22,$B$22+$B$19-1),$B$24,0)"),0.0) -> 0 | T51: =R51-S51 -> 6552.9502 | U51: =T51+U50 -> 56626.365
A52: 21 | B52: =POWER(1-$B$8,A52)*$B$3 -> 58505.683 | C52: =POWER(1+$B$9,A52) -> 1.8602946 | D52: =$B$7*C52*$B$10 -> 1115.6999 | E52: =$B$7*$C52*$B$11 -> 1115.6999 | F52: =$B$7*$C52*$B$12 -> 1115.6999 | G52: =SUM(D52:F52) -> 3347.0996 | H52: =IF(A52=0,$B$17*$B$14*$B$13,H51*$B$13) -> 1.7109629e-07 | I52: =$I$29*B52 -> 11701.137 | J52: =MAX(IF(A52>=$B$22,J51-$B$24,$B$17),0) -> 0 | K52: =IF(A52>=$B$20,J52*$B$18,0) -> 0 | L52: =IF(A52=$B$28,$B$27,0) -> 0 | M52: =I52-G52-K52+L52 -> 8354.0369 | N52: =M52-H52 -> 8354.0369 | O52: =IF(N52<0,N52,0) -> 0 | P52: =IF(N52>0,N52+O51,0) -> 8354.0369 | Q52: =$B$25*P52 -> 1921.4285 | R52: =M52-Q52 -> 6432.6084 | S52: =IFERROR(__xludf.DUMMYFUNCTION("IF(ISBETWEEN(A52,$B$22,$B$22+$B$19-1),$B$24,0)"),0.0) -> 0 | T52: =R52-S52 -> 6432.6084 | U52: =T52+U51 -> 63058.973
A53: 22 | B53: =POWER(1-$B$8,A53)*$B$3 -> 58213.154 | C53: =POWER(1+$B$9,A53) -> 1.9161034 | D53: =$B$7*C53*$B$10 -> 1149.1709 | E53: =$B$7*$C53*$B$11 -> 1149.1709 | F53: =$B$7*$C53*$B$12 -> 1149.1709 | G53: =SUM(D53:F53) -> 3447.5126 | H53: =IF(A53=0,$B$17*$B$14*$B$13,H52*$B$13) -> 5.1328886e-08 | I53: =$I$29*B53 -> 11642.631 | J53: =MAX(IF(A53>=$B$22,J52-$B$24,$B$17),0) -> 0 | K53: =IF(A53>=$B$20,J53*$B$18,0) -> 0 | L53: =IF(A53=$B$28,$B$27,0) -> 0 | M53: =I53-G53-K53+L53 -> 8195.1183 | N53: =M53-H53 -> 8195.1183 | O53: =IF(N53<0,N53,0) -> 0 | P53: =IF(N53>0,N53+O52,0) -> 8195.1183 | Q53: =$B$25*P53 -> 1884.8772 | R53: =M53-Q53 -> 6310.2411 | S53: =IFERROR(__xludf.DUMMYFUNCTION("IF(ISBETWEEN(A53,$B$22,$B$22+$B$19-1),$B$24,0)"),0.0) -> 0 | T53: =R53-S53 -> 6310.2411 | U53: =T53+U52 -> 69369.214
A54: 23 | B54: =POWER(1-$B$8,A54)*$B$3 -> 57922.089 | C54: =POWER(1+$B$9,A54) -> 1.9735865 | D54: =$B$7*C54*$B$10 -> 1183.646 | E54: =$B$7*$C54*$B$11 -> 1183.646 | F54: =$B$7*$C54*$B$12 -> 1183.646 | G54: =SUM(D54:F54) -> 3550.938 | H54: =IF(A54=0,$B$17*$B$14*$B$13,H53*$B$13) -> 1.5398666e-08 | I54: =$I$29*B54 -> 11584.418 | J54: =MAX(IF(A54>=$B$22,J53-$B$24,$B$17),0) -> 0 | K54: =IF(A54>=$B$20,J54*$B$18,0) -> 0 | L54: =IF(A54=$B$28,$B$27,0) -> 0 | M54: =I54-G54-K54+L54 -> 8033.4797 | N54: =M54-H54 -> 8033.4797 | O54: =IF(N54<0,N54,0) -> 0 | P54: =IF(N54>0,N54+O53,0) -> 8033.4797 | Q54: =$B$25*P54 -> 1847.7003 | R54: =M54-Q54 -> 6185.7794 | S54: =IFERROR(__xludf.DUMMYFUNCTION("IF(ISBETWEEN(A54,$B$22,$B$22+$B$19-1),$B$24,0)"),0.0) -> 0 | T54: =R54-S54 -> 6185.7794 | U54: =T54+U53 -> 75554.994
A55: 24 | B55: =POWER(1-$B$8,A55)*$B$3 -> 57632.478 | C55: =POWER(1+$B$9,A55) -> 2.0327941 | D55: =$B$7*C55*$B$10 -> 1219.1554 | E55: =$B$7*$C55*$B$11 -> 1219.1554 | F55: =$B$7*$C55*$B$12 -> 1219.1554 | G55: =SUM(D55:F55) -> 3657.4661 | H55: =IF(A55=0,$B$17*$B$14*$B$13,H54*$B$13) -> 4.6195998e-09 | I55: =$I$29*B55 -> 11526.496 | J55: =MAX(IF(A55>=$B$22,J54-$B$24,$B$17),0) -> 0 | K55: =IF(A55>=$B$20,J55*$B$18,0) -> 0 | L55: =IF(A55=$B$28,$B$27,0) -> 0 | M55: =I55-G55-K55+L55 -> 7869.0295 | N55: =M55-H55 -> 7869.0295 | O55: =IF(N55<0,N55,0) -> 0 | P55: =IF(N55>0,N55+O54,0) -> 7869.0295 | Q55: =$B$25*P55 -> 1809.8768 | R55: =M55-Q55 -> 6059.1527 | S55: =IFERROR(__xludf.DUMMYFUNCTION("IF(ISBETWEEN(A55,$B$22,$B$22+$B$19-1),$B$24,0)"),0.0) -> 0 | T55: =R55-S55 -> 6059.1527 | U55: =T55+U54 -> 81614.146
B56: =SUM(B31:B55) -> 1531136.8 | D56: =SUM(D31:D55) -> 21866.213 | E56: =SUM(E31:E55) -> 21866.213 | F56: =SUM(F31:F55) -> 21866.213 | G56: =SUM(G31:G55) -> 65598.638 | H56: =SUM(H31:H55) -> 23366.636 | I56: =SUM(I31:I55) -> 306227.37 | K56: =SUM(K31:K55) -> 32713.291 | L56: =SUM(L31:L55) -> 32713.291 | M56: =SUM(M31:M55) -> 240628.73 | Q56: =SUM(Q31:Q55) -> 49970.282 | R56: =SUM(R31:R55) -> 190658.45 | S56: =SUM(S31:S55) -> 109044.3 | T56: =SUM(T31:T55) -> 81614.146

Sheet 0% Grant, BVGEC recoup via Prof
A2: Capacity Factor | B2: 0.17 | D2: Norfolk | E2: 0.33
A3: System Output | B3: 65000 | D3: BVGEC | E3: 0.33
A4: Hours per Year | B4: 8766 | D4: Community | E4: =1-E2-E3 -> 0.34
A5: System Size | B5: =$B$3/$B$4/$B$2 -> 43.617721
A6: Install Cost | B6: 2.5
A7: Capex | B7: =B5*B6*1000 -> 109044.3
A8: Degradation | B8: 0.005
A9: Inflation | B9: 0.03
A10: Admin Rate | B10: =$E$11 -> 0 | D10: Combined OPEX Rate | E10: 0
A11: Insurance Rate | B11: =$E$11 -> 0 | D11: Individual | E11: =E10/3 -> 0
A12: Maintenance Rate | B12: =$E$11 -> 0
A13: CCA Rate | B13: 0.3
A14: Half Year Rule | B14: 0.5
A15: Grant Rate | B15: 0 | L15: Current Bill | M15: ='Bill Comparison'!F28 -> 322479.95
A16: Grant Amount | B16: =B7*B15 -> 0 | L16: New Bill | M16: ='Bill Comparison'!J28 -> 49771.697 | N16: Benefit Dist | O16: Annuity
A17: Net Capex | B17: =B7-B16 -> 109044.3 | L17: Available Savings | M17: ='Bill Comparison'!L28 -> 272708.26 | R17: Bill Saving | S17: =1-(I56+M16)/M15 -> 0.062238529
A18: Debt Rate | B18: 0.04 | L18: Norfolk Bill Savings | M18: =M17-I56 -> 20070.678 | N18: =M18/M19 -> 0.18092835
A19: Debt Term | B19: 10 | L19: Total Benefit | M19: =M18+T56+G56 -> 110931.64 | R19: Effective Savings | S19: =1-(M16+I56-M21)/M15 -> 0.17575703
L20: Norfolk Residual | M20: =M19*0.33-M18 -> 16536.763
L21: Norfolk Total | M21: =M18+M20 -> 36607.44 | N21: =M21/M19 -> 0.33 | O21: =M21/25 -> 1464.2976
A22: Repayment Start | B22: 3 | L22: BVGEC Residual | M22: =M19*0.45-G56 -> 49919.237
L23: BVGEC Total | M23: =M22+G56 -> 49919.237 | N23: =M23/M19 -> 0.45 | O23: =M23/25 -> 1996.7695
A24: Repayment Principal | B24: =B17/B19 -> 10904.43 | L24: Community | M24: =M19-M21-M23 -> 24404.96 | N24: =M24/M19 -> 0.22 | O24: =M24/25 -> 976.19841
A25: Tax Rate | B25: 0.23 | N25: =N21+N23+N24 -> 1
A26: ITC Rate | B26: 0.3
A27: ITC Amount | B27: =B26*B17 -> 32713.291 | L27: Utilization | M27: =M19/M17 -> 0.4067777
A28: ITC year | B28: 1
H29: Effective PPA | I29: 0.165
A30: Year | B30: Effective Output | C30: Escalation Factor | D30: Admin Cost | E30: Insurance Cost | F30: Maintenance Cost | G30: OPEX | H30: Capital Cost Allowance | I30: Maxmimum Revenue | J30: Debt Principal | K30: Debt Interest | L30: ITC Credit | M30: Pre Tax Operating Cashflow | N30: Taxable Income Before Carry Forward Loss | O30: Carry Forward Losses | P30: Taxable Income After Carry Forward Loss | Q30: Tax | R30: After Tax Income | S30: Principal Repayent | T30: Cashflow To Equity
A31: 0 | B31: =POWER(1-$B$8,A31)*$B$3 -> 65000 | C31: =POWER(1+$B$9,A31) -> 1 | D31: =$B$7*C31*$B$10 -> 0 | E31: =$B$7*$C31*$B$11 -> 0 | F31: =$B$7*$C31*$B$12 -> 0 | G31: =SUM(D31:F31) -> 0 | H31: =IF(A31=0,$B$17*$B$14*$B$13,H30*$B$13) -> 16356.645 | I31: =$I$29*B31 -> 10725 | J31: =MAX(IF(A31>=$B$22,J30-$B$24,$B$17),0) -> 109044.3 | K31: =IF(A31>=$B$20,J31*$B$18,0) -> 4361.7721 | L31: =IF(A31=$B$28,$B$27,0) -> 0 | M31: =I31-G31-K31+L31 -> 6363.2279 | N31: =M31-H31 -> -9993.4174 | O31: =IF(N31<0,N31,0) -> -9993.4174 | P31: =N31-O31 -> 0 | Q31: =$B$25*P31 -> 0 | R31: =M31-Q31 -> 6363.2279 | S31: =IFERROR(__xludf.DUMMYFUNCTION("IF(ISBETWEEN(A31,$B$22,$B$22+$B$19-1),$B$24,0)"),0.0) -> 0 | T31: =R31-S31 -> 6363.2279 | U31: =T31 -> 6363.2279
A32: 1 | B32: =POWER(1-$B$8,A32)*$B$3 -> 64675 | C32: =POWER(1+$B$9,A32) -> 1.03 | D32: =$B$7*C32*$B$10 -> 0 | E32: =$B$7*$C32*$B$11 -> 0 | F32: =$B$7*$C32*$B$12 -> 0 | G32: =SUM(D32:F32) -> 0 | H32: =IF(A32=0,$B$17*$B$14*$B$13,H31*$B$13) -> 4906.9936 | I32: =$I$29*B32 -> 10671.375 | J32: =MAX(IF(A32>=$B$22,J31-$B$24,$B$17),0) -> 109044.3 | K32: =IF(A32>=$B$20,J32*$B$18,0) -> 4361.7721 | L32: =IF(A32=$B$28,$B$27,0) -> 32713.291 | M32: =I32-G32-K32+L32 -> 39022.894 | N32: =M32-H32 -> 34115.9 | O32: =IF(N32<0,N32,0) -> 0 | P32: =IF(N32>0,N32+O31,0) -> 24122.483 | Q32: =$B$25*P32 -> 5548.171 | R32: =M32-Q32 -> 33474.723 | S32: =IFERROR(__xludf.DUMMYFUNCTION("IF(ISBETWEEN(A32,$B$22,$B$22+$B$19-1),$B$24,0)"),0.0) -> 0 | T32: =R32-S32 -> 33474.723 | U32: =T32+U31 -> 39837.95
A33: 2 | B33: =POWER(1-$B$8,A33)*$B$3 -> 64351.625 | C33: =POWER(1+$B$9,A33) -> 1.0609 | D33: =$B$7*C33*$B$10 -> 0 | E33: =$B$7*$C33*$B$11 -> 0 | F33: =$B$7*$C33*$B$12 -> 0 | G33: =SUM(D33:F33) -> 0 | H33: =IF(A33=0,$B$17*$B$14*$B$13,H32*$B$13) -> 1472.0981 | I33: =$I$29*B33 -> 10618.018 | J33: =MAX(IF(A33>=$B$22,J32-$B$24,$B$17),0) -> 109044.3 | K33: =IF(A33>=$B$20,J33*$B$18,0) -> 4361.7721 | L33: =IF(A33=$B$28,$B$27,0) -> 0 | M33: =I33-G33-K33+L33 -> 6256.246 | N33: =M33-H33 -> 4784.148 | O33: =IF(N33<0,N33,0) -> 0 | P33: =IF(N33>0,N33+O32,0) -> 4784.148 | Q33: =$B$25*P33 -> 1100.354 | R33: =M33-Q33 -> 5155.892 | S33: =IFERROR(__xludf.DUMMYFUNCTION("IF(ISBETWEEN(A33,$B$22,$B$22+$B$19-1),$B$24,0)"),0.0) -> 0 | T33: =R33-S33 -> 5155.892 | U33: =T33+U32 -> 44993.842
A34: 3 | B34: =POWER(1-$B$8,A34)*$B$3 -> 64029.867 | C34: =POWER(1+$B$9,A34) -> 1.092727 | D34: =$B$7*C34*$B$10 -> 0 | E34: =$B$7*$C34*$B$11 -> 0 | F34: =$B$7*$C34*$B$12 -> 0 | G34: =SUM(D34:F34) -> 0 | H34: =IF(A34=0,$B$17*$B$14*$B$13,H33*$B$13) -> 441.62942 | I34: =$I$29*B34 -> 10564.928 | J34: =MAX(IF(A34>=$B$22,J33-$B$24,$B$17),0) -> 98139.872 | K34: =IF(A34>=$B$20,J34*$B$18,0) -> 3925.5949 | L34: =IF(A34=$B$28,$B$27,0) -> 0 | M34: =I34-G34-K34+L34 -> 6639.3332 | N34: =M34-H34 -> 6197.7037 | O34: =IF(N34<0,N34,0) -> 0 | P34: =IF(N34>0,N34+O33,0) -> 6197.7037 | Q34: =$B$25*P34 -> 1425.4719 | R34: =M34-Q34 -> 5213.8613 | S34: =IFERROR(__xludf.DUMMYFUNCTION("IF(ISBETWEEN(A34,$B$22,$B$22+$B$19-1),$B$24,0)"),10904.430218357022) -> 10904.43 | T34: =R34-S34 -> -5690.5689 | U34: =T34+U33 -> 39303.274
A35: 4 | B35: =POWER(1-$B$8,A35)*$B$3 -> 63709.718 | C35: =POWER(1+$B$9,A35) -> 1.1255088 | D35: =$B$7*C35*$B$10 -> 0 | E35: =$B$7*$C35*$B$11 -> 0 | F35: =$B$7*$C35*$B$12 -> 0 | G35: =SUM(D35:F35) -> 0 | H35: =IF(A35=0,$B$17*$B$14*$B$13,H34*$B$13) -> 132.48883 | I35: =$I$29*B35 -> 10512.103 | J35: =MAX(IF(A35>=$B$22,J34-$B$24,$B$17),0) -> 87235.442 | K35: =IF(A35>=$B$20,J35*$B$18,0) -> 3489.4177 | L35: =IF(A35=$B$28,$B$27,0) -> 0 | M35: =I35-G35-K35+L35 -> 7022.6857 | N35: =M35-H35 -> 6890.1969 | O35: =IF(N35<0,N35,0) -> 0 | P35: =IF(N35>0,N35+O34,0) -> 6890.1969 | Q35: =$B$25*P35 -> 1584.7453 | R35: =M35-Q35 -> 5437.9404 | S35: =IFERROR(__xludf.DUMMYFUNCTION("IF(ISBETWEEN(A35,$B$22,$B$22+$B$19-1),$B$24,0)"),10904.430218357022) -> 10904.43 | T35: =R35-S35 -> -5466.4898 | U35: =T35+U34 -> 33836.784
A36: 5 | B36: =POWER(1-$B$8,A36)*$B$3 -> 63391.169 | C36: =POWER(1+$B$9,A36) -> 1.1592741 | D36: =$B$7*C36*$B$10 -> 0 | E36: =$B$7*$C36*$B$11 -> 0 | F36: =$B$7*$C36*$B$12 -> 0 | G36: =SUM(D36:F36) -> 0 | H36: =IF(A36=0,$B$17*$B$14*$B$13,H35*$B$13) -> 39.746648 | I36: =$I$29*B36 -> 10459.543 | J36: =MAX(IF(A36>=$B$22,J35-$B$24,$B$17),0) -> 76331.012 | K36: =IF(A36>=$B$20,J36*$B$18,0) -> 3053.2405 | L36: =IF(A36=$B$28,$B$27,0) -> 0 | M36: =I36-G36-K36+L36 -> 7406.3024 | N36: =M36-H36 -> 7366.5558 | O36: =IF(N36<0,N36,0) -> 0 | P36: =IF(N36>0,N36+O35,0) -> 7366.5558 | Q36: =$B$25*P36 -> 1694.3078 | R36: =M36-Q36 -> 5711.9946 | S36: =IFERROR(__xludf.DUMMYFUNCTION("IF(ISBETWEEN(A36,$B$22,$B$22+$B$19-1),$B$24,0)"),10904.430218357022) -> 10904.43 | T36: =R36-S36 -> -5192.4356 | U36: =T36+U35 -> 28644.348
A37: 6 | B37: =POWER(1-$B$8,A37)*$B$3 -> 63074.213 | C37: =POWER(1+$B$9,A37) -> 1.1940523 | D37: =$B$7*C37*$B$10 -> 0 | E37: =$B$7*$C37*$B$11 -> 0 | F37: =$B$7*$C37*$B$12 -> 0 | G37: =SUM(D37:F37) -> 0 | H37: =IF(A37=0,$B$17*$B$14*$B$13,H36*$B$13) -> 11.923994 | I37: =$I$29*B37 -> 10407.245 | J37: =MAX(IF(A37>=$B$22,J36-$B$24,$B$17),0) -> 65426.581 | K37: =IF(A37>=$B$20,J37*$B$18,0) -> 2617.0633 | L37: =IF(A37=$B$28,$B$27,0) -> 0 | M37: =I37-G37-K37+L37 -> 7790.1819 | N37: =M37-H37 -> 7778.2579 | O37: =IF(N37<0,N37,0) -> 0 | P37: =IF(N37>0,N37+O36,0) -> 7778.2579 | Q37: =$B$25*P37 -> 1788.9993 | R37: =M37-Q37 -> 6001.1826 | S37: =IFERROR(__xludf.DUMMYFUNCTION("IF(ISBETWEEN(A37,$B$22,$B$22+$B$19-1),$B$24,0)"),10904.430218357022) -> 10904.43 | T37: =R37-S37 -> -4903.2476 | U37: =T37+U36 -> 23741.101
A38: 7 | B38: =POWER(1-$B$8,A38)*$B$3 -> 62758.842 | C38: =POWER(1+$B$9,A38) -> 1.2298739 | D38: =$B$7*C38*$B$10 -> 0 | E38: =$B$7*$C38*$B$11 -> 0 | F38: =$B$7*$C38*$B$12 -> 0 | G38: =SUM(D38:F38) -> 0 | H38: =IF(A38=0,$B$17*$B$14*$B$13,H37*$B$13) -> 3.5771983 | I38: =$I$29*B38 -> 10355.209 | J38: =MAX(IF(A38>=$B$22,J37-$B$24,$B$17),0) -> 54522.151 | K38: =IF(A38>=$B$20,J38*$B$18,0) -> 2180.886 | L38: =IF(A38=$B$28,$B$27,0) -> 0 | M38: =I38-G38-K38+L38 -> 8174.3229 | N38: =M38-H38 -> 8170.7457 | O38: =IF(N38<0,N38,0) -> 0 | P38: =IF(N38>0,N38+O37,0) -> 8170.7457 | Q38: =$B$25*P38 -> 1879.2715 | R38: =M38-Q38 -> 6295.0514 | S38: =IFERROR(__xludf.DUMMYFUNCTION("IF(ISBETWEEN(A38,$B$22,$B$22+$B$19-1),$B$24,0)"),10904.430218357022) -> 10904.43 | T38: =R38-S38 -> -4609.3788 | U38: =T38+U37 -> 19131.722
A39: 8 | B39: =POWER(1-$B$8,A39)*$B$3 -> 62445.048 | C39: =POWER(1+$B$9,A39) -> 1.2667701 | D39: =$B$7*C39*$B$10 -> 0 | E39: =$B$7*$C39*$B$11 -> 0 | F39: =$B$7*$C39*$B$12 -> 0 | G39: =SUM(D39:F39) -> 0 | H39: =IF(A39=0,$B$17*$B$14*$B$13,H38*$B$13) -> 1.0731595 | I39: =$I$29*B39 -> 10303.433 | J39: =MAX(IF(A39>=$B$22,J38-$B$24,$B$17),0) -> 43617.721 | K39: =IF(A39>=$B$20,J39*$B$18,0) -> 1744.7088 | L39: =IF(A39=$B$28,$B$27,0) -> 0 | M39: =I39-G39-K39+L39 -> 8558.7241 | N39: =M39-H39 -> 8557.6509 | O39: =IF(N39<0,N39,0) -> 0 | P39: =IF(N39>0,N39+O38,0) -> 8557.6509 | Q39: =$B$25*P39 -> 1968.2597 | R39: =M39-Q39 -> 6590.4644 | S39: =IFERROR(__xludf.DUMMYFUNCTION("IF(ISBETWEEN(A39,$B$22,$B$22+$B$19-1),$B$24,0)"),10904.430218357022) -> 10904.43 | T39: =R39-S39 -> -4313.9659 | U39: =T39+U38 -> 14817.756
A40: 9 | B40: =POWER(1-$B$8,A40)*$B$3 -> 62132.823 | C40: =POWER(1+$B$9,A40) -> 1.3047732 | D40: =$B$7*C40*$B$10 -> 0 | E40: =$B$7*$C40*$B$11 -> 0 | F40: =$B$7*$C40*$B$12 -> 0 | G40: =SUM(D40:F40) -> 0 | H40: =IF(A40=0,$B$17*$B$14*$B$13,H39*$B$13) -> 0.32194785 | I40: =$I$29*B40 -> 10251.916 | J40: =MAX(IF(A40>=$B$22,J39-$B$24,$B$17),0) -> 32713.291 | K40: =IF(A40>=$B$20,J40*$B$18,0) -> 1308.5316 | L40: =IF(A40=$B$28,$B$27,0) -> 0 | M40: =I40-G40-K40+L40 -> 8943.3841 | N40: =M40-H40 -> 8943.0622 | O40: =IF(N40<0,N40,0) -> 0 | P40: =IF(N40>0,N40+O39,0) -> 8943.0622 | Q40: =$B$25*P40 -> 2056.9043 | R40: =M40-Q40 -> 6886.4798 | S40: =IFERROR(__xludf.DUMMYFUNCTION("IF(ISBETWEEN(A40,$B$22,$B$22+$B$19-1),$B$24,0)"),10904.430218357022) -> 10904.43 | T40: =R40-S40 -> -4017.9504 | U40: =T40+U39 -> 10799.805
A41: 10 | B41: =POWER(1-$B$8,A41)*$B$3 -> 61822.158 | C41: =POWER(1+$B$9,A41) -> 1.3439164 | D41: =$B$7*C41*$B$10 -> 0 | E41: =$B$7*$C41*$B$11 -> 0 | F41: =$B$7*$C41*$B$12 -> 0 | G41: =SUM(D41:F41) -> 0 | H41: =IF(A41=0,$B$17*$B$14*$B$13,H40*$B$13) -> 0.096584355 | I41: =$I$29*B41 -> 10200.656 | J41: =MAX(IF(A41>=$B$22,J40-$B$24,$B$17),0) -> 21808.86 | K41: =IF(A41>=$B$20,J41*$B$18,0) -> 872.35442 | L41: =IF(A41=$B$28,$B$27,0) -> 0 | M41: =I41-G41-K41+L41 -> 9328.3017 | N41: =M41-H41 -> 9328.2051 | O41: =IF(N41<0,N41,0) -> 0 | P41: =IF(N41>0,N41+O40,0) -> 9328.2051 | Q41: =$B$25*P41 -> 2145.4872 | R41: =M41-Q41 -> 7182.8145 | S41: =IFERROR(__xludf.DUMMYFUNCTION("IF(ISBETWEEN(A41,$B$22,$B$22+$B$19-1),$B$24,0)"),10904.430218357022) -> 10904.43 | T41: =R41-S41 -> -3721.6157 | U41: =T41+U40 -> 7078.1898
A42: 11 | B42: =POWER(1-$B$8,A42)*$B$3 -> 61513.048 | C42: =POWER(1+$B$9,A42) -> 1.3842339 | D42: =$B$7*C42*$B$10 -> 0 | E42: =$B$7*$C42*$B$11 -> 0 | F42: =$B$7*$C42*$B$12 -> 0 | G42: =SUM(D42:F42) -> 0 | H42: =IF(A42=0,$B$17*$B$14*$B$13,H41*$B$13) -> 0.028975306 | I42: =$I$29*B42 -> 10149.653 | J42: =MAX(IF(A42>=$B$22,J41-$B$24,$B$17),0) -> 10904.43 | K42: =IF(A42>=$B$20,J42*$B$18,0) -> 436.17721 | L42: =IF(A42=$B$28,$B$27,0) -> 0 | M42: =I42-G42-K42+L42 -> 9713.4757 | N42: =M42-H42 -> 9713.4467 | O42: =IF(N42<0,N42,0) -> 0 | P42: =IF(N42>0,N42+O41,0) -> 9713.4467 | Q42: =$B$25*P42 -> 2234.0927 | R42: =M42-Q42 -> 7479.3829 | S42: =IFERROR(__xludf.DUMMYFUNCTION("IF(ISBETWEEN(A42,$B$22,$B$22+$B$19-1),$B$24,0)"),10904.430218357022) -> 10904.43 | T42: =R42-S42 -> -3425.0473 | U42: =T42+U41 -> 3653.1425
A43: 12 | B43: =POWER(1-$B$8,A43)*$B$3 -> 61205.482 | C43: =POWER(1+$B$9,A43) -> 1.4257609 | D43: =$B$7*C43*$B$10 -> 0 | E43: =$B$7*$C43*$B$11 -> 0 | F43: =$B$7*$C43*$B$12 -> 0 | G43: =SUM(D43:F43) -> 0 | H43: =IF(A43=0,$B$17*$B$14*$B$13,H42*$B$13) -> 0.008692592 | I43: =$I$29*B43 -> 10098.905 | J43: =MAX(IF(A43>=$B$22,J42-$B$24,$B$17),0) -> 0 | K43: =IF(A43>=$B$20,J43*$B$18,0) -> 0 | L43: =IF(A43=$B$28,$B$27,0) -> 0 | M43: =I43-G43-K43+L43 -> 10098.905 | N43: =M43-H43 -> 10098.896 | O43: =IF(N43<0,N43,0) -> 0 | P43: =IF(N43>0,N43+O42,0) -> 10098.896 | Q43: =$B$25*P43 -> 2322.7461 | R43: =M43-Q43 -> 7776.1585 | S43: =IFERROR(__xludf.DUMMYFUNCTION("IF(ISBETWEEN(A43,$B$22,$B$22+$B$19-1),$B$24,0)"),10904.430218357022) -> 10904.43 | T43: =R43-S43 -> -3128.2717 | U43: =T43+U42 -> 524.87079
A44: 13 | B44: =POWER(1-$B$8,A44)*$B$3 -> 60899.455 | C44: =POWER(1+$B$9,A44) -> 1.4685337 | D44: =$B$7*C44*$B$10 -> 0 | E44: =$B$7*$C44*$B$11 -> 0 | F44: =$B$7*$C44*$B$12 -> 0 | G44: =SUM(D44:F44) -> 0 | H44: =IF(A44=0,$B$17*$B$14*$B$13,H43*$B$13) -> 0.0026077776 | I44: =$I$29*B44 -> 10048.41 | J44: =MAX(IF(A44>=$B$22,J43-$B$24,$B$17),0) -> 0 | K44: =IF(A44>=$B$20,J44*$B$18,0) -> 0 | L44: =IF(A44=$B$28,$B$27,0) -> 0 | M44: =I44-G44-K44+L44 -> 10048.41 | N44: =M44-H44 -> 10048.407 | O44: =IF(N44<0,N44,0) -> 0 | P44: =IF(N44>0,N44+O43,0) -> 10048.407 | Q44: =$B$25*P44 -> 2311.1337 | R44: =M44-Q44 -> 7737.2764 | S44: =IFERROR(__xludf.DUMMYFUNCTION("IF(ISBETWEEN(A44,$B$22,$B$22+$B$19-1),$B$24,0)"),0.0) -> 0 | T44: =R44-S44 -> 7737.2764 | U44: =T44+U43 -> 8262.1471
A45: 14 | B45: =POWER(1-$B$8,A45)*$B$3 -> 60594.958 | C45: =POWER(1+$B$9,A45) -> 1.5125897 | D45: =$B$7*C45*$B$10 -> 0 | E45: =$B$7*$C45*$B$11 -> 0 | F45: =$B$7*$C45*$B$12 -> 0 | G45: =SUM(D45:F45) -> 0 | H45: =IF(A45=0,$B$17*$B$14*$B$13,H44*$B$13) -> 0.00078233328 | I45: =$I$29*B45 -> 9998.168 | J45: =MAX(IF(A45>=$B$22,J44-$B$24,$B$17),0) -> 0 | K45: =IF(A45>=$B$20,J45*$B$18,0) -> 0 | L45: =IF(A45=$B$28,$B$27,0) -> 0 | M45: =I45-G45-K45+L45 -> 9998.168 | N45: =M45-H45 -> 9998.1672 | O45: =IF(N45<0,N45,0) -> 0 | P45: =IF(N45>0,N45+O44,0) -> 9998.1672 | Q45: =$B$25*P45 -> 2299.5785 | R45: =M45-Q45 -> 7698.5896 | S45: =IFERROR(__xludf.DUMMYFUNCTION("IF(ISBETWEEN(A45,$B$22,$B$22+$B$19-1),$B$24,0)"),0.0) -> 0 | T45: =R45-S45 -> 7698.5896 | U45: =T45+U44 -> 15960.737
A46: 15 | B46: =POWER(1-$B$8,A46)*$B$3 -> 60291.983 | C46: =POWER(1+$B$9,A46) -> 1.5579674 | D46: =$B$7*C46*$B$10 -> 0 | E46: =$B$7*$C46*$B$11 -> 0 | F46: =$B$7*$C46*$B$12 -> 0 | G46: =SUM(D46:F46) -> 0 | H46: =IF(A46=0,$B$17*$B$14*$B$13,H45*$B$13) -> 0.00023469998 | I46: =$I$29*B46 -> 9948.1772 | J46: =MAX(IF(A46>=$B$22,J45-$B$24,$B$17),0) -> 0 | K46: =IF(A46>=$B$20,J46*$B$18,0) -> 0 | L46: =IF(A46=$B$28,$B$27,0) -> 0 | M46: =I46-G46-K46+L46 -> 9948.1772 | N46: =M46-H46 -> 9948.177 | O46: =IF(N46<0,N46,0) -> 0 | P46: =IF(N46>0,N46+O45,0) -> 9948.177 | Q46: =$B$25*P46 -> 2288.0807 | R46: =M46-Q46 -> 7660.0965 | S46: =IFERROR(__xludf.DUMMYFUNCTION("IF(ISBETWEEN(A46,$B$22,$B$22+$B$19-1),$B$24,0)"),0.0) -> 0 | T46: =R46-S46 -> 7660.0965 | U46: =T46+U45 -> 23620.833
A47: 16 | B47: =POWER(1-$B$8,A47)*$B$3 -> 59990.523 | C47: =POWER(1+$B$9,A47) -> 1.6047064 | D47: =$B$7*C47*$B$10 -> 0 | E47: =$B$7*$C47*$B$11 -> 0 | F47: =$B$7*$C47*$B$12 -> 0 | G47: =SUM(D47:F47) -> 0 | H47: =IF(A47=0,$B$17*$B$14*$B$13,H46*$B$13) -> 7.0409995e-05 | I47: =$I$29*B47 -> 9898.4363 | J47: =MAX(IF(A47>=$B$22,J46-$B$24,$B$17),0) -> 0 | K47: =IF(A47>=$B$20,J47*$B$18,0) -> 0 | L47: =IF(A47=$B$28,$B$27,0) -> 0 | M47: =I47-G47-K47+L47 -> 9898.4363 | N47: =M47-H47 -> 9898.4362 | O47: =IF(N47<0,N47,0) -> 0 | P47: =IF(N47>0,N47+O46,0) -> 9898.4362 | Q47: =$B$25*P47 -> 2276.6403 | R47: =M47-Q47 -> 7621.796 | S47: =IFERROR(__xludf.DUMMYFUNCTION("IF(ISBETWEEN(A47,$B$22,$B$22+$B$19-1),$B$24,0)"),0.0) -> 0 | T47: =R47-S47 -> 7621.796 | U47: =T47+U46 -> 31242.629
A48: 17 | B48: =POWER(1-$B$8,A48)*$B$3 -> 59690.57 | C48: =POWER(1+$B$9,A48) -> 1.6528476 | D48: =$B$7*C48*$B$10 -> 0 | E48: =$B$7*$C48*$B$11 -> 0 | F48: =$B$7*$C48*$B$12 -> 0 | G48: =SUM(D48:F48) -> 0 | H48: =IF(A48=0,$B$17*$B$14*$B$13,H47*$B$13) -> 2.1122998e-05 | I48: =$I$29*B48 -> 9848.9441 | J48: =MAX(IF(A48>=$B$22,J47-$B$24,$B$17),0) -> 0 | K48: =IF(A48>=$B$20,J48*$B$18,0) -> 0 | L48: =IF(A48=$B$28,$B$27,0) -> 0 | M48: =I48-G48-K48+L48 -> 9848.9441 | N48: =M48-H48 -> 9848.9441 | O48: =IF(N48<0,N48,0) -> 0 | P48: =IF(N48>0,N48+O47,0) -> 9848.9441 | Q48: =$B$25*P48 -> 2265.2571 | R48: =M48-Q48 -> 7583.687 | S48: =IFERROR(__xludf.DUMMYFUNCTION("IF(ISBETWEEN(A48,$B$22,$B$22+$B$19-1),$B$24,0)"),0.0) -> 0 | T48: =R48-S48 -> 7583.687 | U48: =T48+U47 -> 38826.316
A49: 18 | B49: =POWER(1-$B$8,A49)*$B$3 -> 59392.118 | C49: =POWER(1+$B$9,A49) -> 1.7024331 | D49: =$B$7*C49*$B$10 -> 0 | E49: =$B$7*$C49*$B$11 -> 0 | F49: =$B$7*$C49*$B$12 -> 0 | G49: =SUM(D49:F49) -> 0 | H49: =IF(A49=0,$B$17*$B$14*$B$13,H48*$B$13) -> 6.3368995e-06 | I49: =$I$29*B49 -> 9799.6994 | J49: =MAX(IF(A49>=$B$22,J48-$B$24,$B$17),0) -> 0 | K49: =IF(A49>=$B$20,J49*$B$18,0) -> 0 | L49: =IF(A49=$B$28,$B$27,0) -> 0 | M49: =I49-G49-K49+L49 -> 9799.6994 | N49: =M49-H49 -> 9799.6994 | O49: =IF(N49<0,N49,0) -> 0 | P49: =IF(N49>0,N49+O48,0) -> 9799.6994 | Q49: =$B$25*P49 -> 2253.9309 | R49: =M49-Q49 -> 7545.7685 | S49: =IFERROR(__xludf.DUMMYFUNCTION("IF(ISBETWEEN(A49,$B$22,$B$22+$B$19-1),$B$24,0)"),0.0) -> 0 | T49: =R49-S49 -> 7545.7685 | U49: =T49+U48 -> 46372.085
A50: 19 | B50: =POWER(1-$B$8,A50)*$B$3 -> 59095.157 | C50: =POWER(1+$B$9,A50) -> 1.7535061 | D50: =$B$7*C50*$B$10 -> 0 | E50: =$B$7*$C50*$B$11 -> 0 | F50: =$B$7*$C50*$B$12 -> 0 | G50: =SUM(D50:F50) -> 0 | H50: =IF(A50=0,$B$17*$B$14*$B$13,H49*$B$13) -> 1.9010699e-06 | I50: =$I$29*B50 -> 9750.7009 | J50: =MAX(IF(A50>=$B$22,J49-$B$24,$B$17),0) -> 0 | K50: =IF(A50>=$B$20,J50*$B$18,0) -> 0 | L50: =IF(A50=$B$28,$B$27,0) -> 0 | M50: =I50-G50-K50+L50 -> 9750.7009 | N50: =M50-H50 -> 9750.7009 | O50: =IF(N50<0,N50,0) -> 0 | P50: =IF(N50>0,N50+O49,0) -> 9750.7009 | Q50: =$B$25*P50 -> 2242.6612 | R50: =M50-Q50 -> 7508.0397 | S50: =IFERROR(__xludf.DUMMYFUNCTION("IF(ISBETWEEN(A50,$B$22,$B$22+$B$19-1),$B$24,0)"),0.0) -> 0 | T50: =R50-S50 -> 7508.0397 | U50: =T50+U49 -> 53880.124
A51: 20 | B51: =POWER(1-$B$8,A51)*$B$3 -> 58799.681 | C51: =POWER(1+$B$9,A51) -> 1.8061112 | D51: =$B$7*C51*$B$10 -> 0 | E51: =$B$7*$C51*$B$11 -> 0 | F51: =$B$7*$C51*$B$12 -> 0 | G51: =SUM(D51:F51) -> 0 | H51: =IF(A51=0,$B$17*$B$14*$B$13,H50*$B$13) -> 5.7032096e-07 | I51: =$I$29*B51 -> 9701.9474 | J51: =MAX(IF(A51>=$B$22,J50-$B$24,$B$17),0) -> 0 | K51: =IF(A51>=$B$20,J51*$B$18,0) -> 0 | L51: =IF(A51=$B$28,$B$27,0) -> 0 | M51: =I51-G51-K51+L51 -> 9701.9474 | N51: =M51-H51 -> 9701.9474 | O51: =IF(N51<0,N51,0) -> 0 | P51: =IF(N51>0,N51+O50,0) -> 9701.9474 | Q51: =$B$25*P51 -> 2231.4479 | R51: =M51-Q51 -> 7470.4995 | S51: =IFERROR(__xludf.DUMMYFUNCTION("IF(ISBETWEEN(A51,$B$22,$B$22+$B$19-1),$B$24,0)"),0.0) -> 0 | T51: =R51-S51 -> 7470.4995 | U51: =T51+U50 -> 61350.624
A52: 21 | B52: =POWER(1-$B$8,A52)*$B$3 -> 58505.683 | C52: =POWER(1+$B$9,A52) -> 1.8602946 | D52: =$B$7*C52*$B$10 -> 0 | E52: =$B$7*$C52*$B$11 -> 0 | F52: =$B$7*$C52*$B$12 -> 0 | G52: =SUM(D52:F52) -> 0 | H52: =IF(A52=0,$B$17*$B$14*$B$13,H51*$B$13) -> 1.7109629e-07 | I52: =$I$29*B52 -> 9653.4377 | J52: =MAX(IF(A52>=$B$22,J51-$B$24,$B$17),0) -> 0 | K52: =IF(A52>=$B$20,J52*$B$18,0) -> 0 | L52: =IF(A52=$B$28,$B$27,0) -> 0 | M52: =I52-G52-K52+L52 -> 9653.4377 | N52: =M52-H52 -> 9653.4377 | O52: =IF(N52<0,N52,0) -> 0 | P52: =IF(N52>0,N52+O51,0) -> 9653.4377 | Q52: =$B$25*P52 -> 2220.2907 | R52: =M52-Q52 -> 7433.147 | S52: =IFERROR(__xludf.DUMMYFUNCTION("IF(ISBETWEEN(A52,$B$22,$B$22+$B$19-1),$B$24,0)"),0.0) -> 0 | T52: =R52-S52 -> 7433.147 | U52: =T52+U51 -> 68783.771
A53: 22 | B53: =POWER(1-$B$8,A53)*$B$3 -> 58213.154 | C53: =POWER(1+$B$9,A53) -> 1.9161034 | D53: =$B$7*C53*$B$10 -> 0 | E53: =$B$7*$C53*$B$11 -> 0 | F53: =$B$7*$C53*$B$12 -> 0 | G53: =SUM(D53:F53) -> 0 | H53: =IF(A53=0,$B$17*$B$14*$B$13,H52*$B$13) -> 5.1328886e-08 | I53: =$I$29*B53 -> 9605.1705 | J53: =MAX(IF(A53>=$B$22,J52-$B$24,$B$17),0) -> 0 | K53: =IF(A53>=$B$20,J53*$B$18,0) -> 0 | L53: =IF(A53=$B$28,$B$27,0) -> 0 | M53: =I53-G53-K53+L53 -> 9605.1705 | N53: =M53-H53 -> 9605.1705 | O53: =IF(N53<0,N53,0) -> 0 | P53: =IF(N53>0,N53+O52,0) -> 9605.1705 | Q53: =$B$25*P53 -> 2209.1892 | R53: =M53-Q53 -> 7395.9813 | S53: =IFERROR(__xludf.DUMMYFUNCTION("IF(ISBETWEEN(A53,$B$22,$B$22+$B$19-1),$B$24,0)"),0.0) -> 0 | T53: =R53-S53 -> 7395.9813 | U53: =T53+U52 -> 76179.752
A54: 23 | B54: =POWER(1-$B$8,A54)*$B$3 -> 57922.089 | C54: =POWER(1+$B$9,A54) -> 1.9735865 | D54: =$B$7*C54*$B$10 -> 0 | E54: =$B$7*$C54*$B$11 -> 0 | F54: =$B$7*$C54*$B$12 -> 0 | G54: =SUM(D54:F54) -> 0 | H54: =IF(A54=0,$B$17*$B$14*$B$13,H53*$B$13) -> 1.5398666e-08 | I54: =$I$29*B54 -> 9557.1446 | J54: =MAX(IF(A54>=$B$22,J53-$B$24,$B$17),0) -> 0 | K54: =IF(A54>=$B$20,J54*$B$18,0) -> 0 | L54: =IF(A54=$B$28,$B$27,0) -> 0 | M54: =I54-G54-K54+L54 -> 9557.1446 | N54: =M54-H54 -> 9557.1446 | O54: =IF(N54<0,N54,0) -> 0 | P54: =IF(N54>0,N54+O53,0) -> 9557.1446 | Q54: =$B$25*P54 -> 2198.1433 | R54: =M54-Q54 -> 7359.0014 | S54: =IFERROR(__xludf.DUMMYFUNCTION("IF(ISBETWEEN(A54,$B$22,$B$22+$B$19-1),$B$24,0)"),0.0) -> 0 | T54: =R54-S54 -> 7359.0014 | U54: =T54+U53 -> 83538.754
A55: 24 | B55: =POWER(1-$B$8,A55)*$B$3 -> 57632.478 | C55: =POWER(1+$B$9,A55) -> 2.0327941 | D55: =$B$7*C55*$B$10 -> 0 | E55: =$B$7*$C55*$B$11 -> 0 | F55: =$B$7*$C55*$B$12 -> 0 | G55: =SUM(D55:F55) -> 0 | H55: =IF(A55=0,$B$17*$B$14*$B$13,H54*$B$13) -> 4.6195998e-09 | I55: =$I$29*B55 -> 9509.3589 | J55: =MAX(IF(A55>=$B$22,J54-$B$24,$B$17),0) -> 0 | K55: =IF(A55>=$B$20,J55*$B$18,0) -> 0 | L55: =IF(A55=$B$28,$B$27,0) -> 0 | M55: =I55-G55-K55+L55 -> 9509.3589 | N55: =M55-H55 -> 9509.3589 | O55: =IF(N55<0,N55,0) -> 0 | P55: =IF(N55>0,N55+O54,0) -> 9509.3589 | Q55: =$B$25*P55 -> 2187.1525 | R55: =M55-Q55 -> 7322.2064 | S55: =IFERROR(__xludf.DUMMYFUNCTION("IF(ISBETWEEN(A55,$B$22,$B$22+$B$19-1),$B$24,0)"),0.0) -> 0 | T55: =R55-S55 -> 7322.2064 | U55: =T55+U54 -> 90860.96
B56: =SUM(B31:B55) -> 1531136.8 | D56: =SUM(D31:D55) -> 0 | E56: =SUM(E31:E55) -> 0 | F56: =SUM(F31:F55) -> 0 | G56: =SUM(G31:G55) -> 0 | H56: =SUM(H31:H55) -> 23366.636 | I56: =SUM(I31:I55) -> 252637.58 | K56: =SUM(K31:K55) -> 32713.291 | L56: =SUM(L31:L55) -> 32713.291 | M56: =SUM(M31:M55) -> 252637.58 | Q56: =SUM(Q31:Q55) -> 52732.317 | R56: =SUM(R31:R55) -> 199905.26 | S56: =SUM(S31:S55) -> 109044.3 | T56: =SUM(T31:T55) -> 90860.96

Sheet 50% Grant, BVGEC recoup via pro
A2: Capacity Factor | B2: 0.17 | D2: Norfolk | E2: 0.33
A3: System Output | B3: 65000 | D3: BVGEC | E3: 0.33
A4: Hours per Year | B4: 8766 | D4: Community | E4: =1-E2-E3 -> 0.34
A5: System Size | B5: =$B$3/$B$4/$B$2 -> 43.617721
A6: Install Cost | B6: 2.5
A7: Capex | B7: =B5*B6*1000 -> 109044.3
A8: Degradation | B8: 0.005
A9: Inflation | B9: 0.03
A10: Admin Rate | B10: =$E$11 -> 0 | D10: Combined OPEX Rate | E10: 0
A11: Insurance Rate | B11: =$E$11 -> 0 | D11: Individual | E11: =E10/3 -> 0
A12: Maintenance Rate | B12: =$E$11 -> 0
A13: CCA Rate | B13: 0.3
A14: Half Year Rule | B14: 0.5
A15: Grant Rate | B15: 0.5 | L15: Current Bill | M15: ='Bill Comparison'!F28 -> 322479.95
A16: Grant Amount | B16: =B7*B15 -> 54522.151 | L16: New Bill | M16: ='Bill Comparison'!J28 -> 49771.697 | N16: Benefit Dist | O16: Annuity
A17: Net Capex | B17: =B7-B16 -> 54522.151 | L17: Available Savings | M17: ='Bill Comparison'!L28 -> 272708.26 | R17: Bill Saving | S17: =1-(I56+M16)/M15 -> 0.44207903
A18: Debt Rate | B18: 0.04 | L18: Norfolk Bill Savings | M18: =M17-I56 -> 142561.63 | N18: =M18/M19 -> 0.74663227
A19: Debt Term | B19: 10 | L19: Total Benefit | M19: =M18+T56+G56 -> 190939.54 | R19: Effective Savings | S19: =1-(M16+I56-M21)/M15 -> 0.63747117
L20: Norfolk Residual | M20: =M19*0.33-M18 -> -79551.576
L21: Norfolk Total | M21: =M18+M20 -> 63010.049 | N21: =M21/M19 -> 0.33 | O21: =M21/25 -> 2520.402
A22: Repayment Start | B22: 3 | L22: BVGEC Residual | M22: =M19*0.45-G56 -> 85922.795
L23: BVGEC Total | M23: =M22+G56 -> 85922.795 | N23: =M23/M19 -> 0.45 | O23: =M23/25 -> 3436.9118
A24: Repayment Principal | B24: =B17/B19 -> 5452.2151 | L24: Community | M24: =M19-M21-M23 -> 42006.7 | N24: =M24/M19 -> 0.22 | O24: =M24/25 -> 1680.268
A25: Tax Rate | B25: 0.23 | N25: =N21+N23+N24 -> 1
A26: ITC Rate | B26: 0.3
A27: ITC Amount | B27: =B26*B17 -> 16356.645 | L27: Utilization | M27: =M19/M17 -> 0.70016048
A28: ITC year | B28: 1
H29: Effective PPA | I29: 0.085
A30: Year | B30: Effective Output | C30: Escalation Factor | D30: Admin Cost | E30: Insurance Cost | F30: Maintenance Cost | G30: OPEX | H30: Capital Cost Allowance | I30: Revenue | J30: Debt Principal | K30: Debt Interest | L30: ITC Credit | M30: Pre Tax Operating Cashflow | N30: Taxable Income Before Carry Forward Loss | O30: Carry Forward Losses | P30: Taxable Income After Carry Forward Loss | Q30: Tax | R30: After Tax Income | S30: Principal Repayent | T30: Cashflow To Equity
A31: 0 | B31: =POWER(1-$B$8,A31)*$B$3 -> 65000 | C31: =POWER(1+$B$9,A31) -> 1 | D31: =$B$7*C31*$B$10 -> 0 | E31: =$B$7*$C31*$B$11 -> 0 | F31: =$B$7*$C31*$B$12 -> 0 | G31: =SUM(D31:F31) -> 0 | H31: =IF(A31=0,$B$17*$B$14*$B$13,H30*$B$13) -> 8178.3227 | I31: =$I$29*B31 -> 5525 | J31: =MAX(IF(A31>=$B$22,J30-$B$24,$B$17),0) -> 54522.151 | K31: =IF(A31>=$B$20,J31*$B$18,0) -> 2180.886 | L31: =IF(A31=$B$28,$B$27,0) -> 0 | M31: =I31-G31-K31+L31 -> 3344.114 | N31: =M31-H31 -> -4834.2087 | O31: =IF(N31<0,N31,0) -> -4834.2087 | P31: =N31-O31 -> 0 | Q31: =$B$25*P31 -> 0 | R31: =M31-Q31 -> 3344.114 | S31: =IFERROR(__xludf.DUMMYFUNCTION("IF(ISBETWEEN(A31,$B$22,$B$22+$B$19-1),$B$24,0)"),0.0) -> 0 | T31: =R31-S31 -> 3344.114 | U31: =T31 -> 3344.114
A32: 1 | B32: =POWER(1-$B$8,A32)*$B$3 -> 64675 | C32: =POWER(1+$B$9,A32) -> 1.03 | D32: =$B$7*C32*$B$10 -> 0 | E32: =$B$7*$C32*$B$11 -> 0 | F32: =$B$7*$C32*$B$12 -> 0 | G32: =SUM(D32:F32) -> 0 | H32: =IF(A32=0,$B$17*$B$14*$B$13,H31*$B$13) -> 2453.4968 | I32: =$I$29*B32 -> 5497.375 | J32: =MAX(IF(A32>=$B$22,J31-$B$24,$B$17),0) -> 54522.151 | K32: =IF(A32>=$B$20,J32*$B$18,0) -> 2180.886 | L32: =IF(A32=$B$28,$B$27,0) -> 16356.645 | M32: =I32-G32-K32+L32 -> 19673.134 | N32: =M32-H32 -> 17219.637 | O32: =IF(N32<0,N32,0) -> 0 | P32: =IF(N32>0,N32+O31,0) -> 12385.429 | Q32: =$B$25*P32 -> 2848.6486 | R32: =M32-Q32 -> 16824.486 | S32: =IFERROR(__xludf.DUMMYFUNCTION("IF(ISBETWEEN(A32,$B$22,$B$22+$B$19-1),$B$24,0)"),0.0) -> 0 | T32: =R32-S32 -> 16824.486 | U32: =T32+U31 -> 20168.6
A33: 2 | B33: =POWER(1-$B$8,A33)*$B$3 -> 64351.625 | C33: =POWER(1+$B$9,A33) -> 1.0609 | D33: =$B$7*C33*$B$10 -> 0 | E33: =$B$7*$C33*$B$11 -> 0 | F33: =$B$7*$C33*$B$12 -> 0 | G33: =SUM(D33:F33) -> 0 | H33: =IF(A33=0,$B$17*$B$14*$B$13,H32*$B$13) -> 736.04904 | I33: =$I$29*B33 -> 5469.8881 | J33: =MAX(IF(A33>=$B$22,J32-$B$24,$B$17),0) -> 54522.151 | K33: =IF(A33>=$B$20,J33*$B$18,0) -> 2180.886 | L33: =IF(A33=$B$28,$B$27,0) -> 0 | M33: =I33-G33-K33+L33 -> 3289.0021 | N33: =M33-H33 -> 2552.953 | O33: =IF(N33<0,N33,0) -> 0 | P33: =IF(N33>0,N33+O32,0) -> 2552.953 | Q33: =$B$25*P33 -> 587.1792 | R33: =M33-Q33 -> 2701.8229 | S33: =IFERROR(__xludf.DUMMYFUNCTION("IF(ISBETWEEN(A33,$B$22,$B$22+$B$19-1),$B$24,0)"),0.0) -> 0 | T33: =R33-S33 -> 2701.8229 | U33: =T33+U32 -> 22870.423
A34: 3 | B34: =POWER(1-$B$8,A34)*$B$3 -> 64029.867 | C34: =POWER(1+$B$9,A34) -> 1.092727 | D34: =$B$7*C34*$B$10 -> 0 | E34: =$B$7*$C34*$B$11 -> 0 | F34: =$B$7*$C34*$B$12 -> 0 | G34: =SUM(D34:F34) -> 0 | H34: =IF(A34=0,$B$17*$B$14*$B$13,H33*$B$13) -> 220.81471 | I34: =$I$29*B34 -> 5442.5387 | J34: =MAX(IF(A34>=$B$22,J33-$B$24,$B$17),0) -> 49069.936 | K34: =IF(A34>=$B$20,J34*$B$18,0) -> 1962.7974 | L34: =IF(A34=$B$28,$B$27,0) -> 0 | M34: =I34-G34-K34+L34 -> 3479.7412 | N34: =M34-H34 -> 3258.9265 | O34: =IF(N34<0,N34,0) -> 0 | P34: =IF(N34>0,N34+O33,0) -> 3258.9265 | Q34: =$B$25*P34 -> 749.5531 | R34: =M34-Q34 -> 2730.1881 | S34: =IFERROR(__xludf.DUMMYFUNCTION("IF(ISBETWEEN(A34,$B$22,$B$22+$B$19-1),$B$24,0)"),5452.215109178511) -> 5452.2151 | T34: =R34-S34 -> -2722.027 | U34: =T34+U33 -> 20148.396
A35: 4 | B35: =POWER(1-$B$8,A35)*$B$3 -> 63709.718 | C35: =POWER(1+$B$9,A35) -> 1.1255088 | D35: =$B$7*C35*$B$10 -> 0 | E35: =$B$7*$C35*$B$11 -> 0 | F35: =$B$7*$C35*$B$12 -> 0 | G35: =SUM(D35:F35) -> 0 | H35: =IF(A35=0,$B$17*$B$14*$B$13,H34*$B$13) -> 66.244414 | I35: =$I$29*B35 -> 5415.326 | J35: =MAX(IF(A35>=$B$22,J34-$B$24,$B$17),0) -> 43617.721 | K35: =IF(A35>=$B$20,J35*$B$18,0) -> 1744.7088 | L35: =IF(A35=$B$28,$B$27,0) -> 0 | M35: =I35-G35-K35+L35 -> 3670.6172 | N35: =M35-H35 -> 3604.3727 | O35: =IF(N35<0,N35,0) -> 0 | P35: =IF(N35>0,N35+O34,0) -> 3604.3727 | Q35: =$B$25*P35 -> 829.00573 | R35: =M35-Q35 -> 2841.6114 | S35: =IFERROR(__xludf.DUMMYFUNCTION("IF(ISBETWEEN(A35,$B$22,$B$22+$B$19-1),$B$24,0)"),5452.215109178511) -> 5452.2151 | T35: =R35-S35 -> -2610.6037 | U35: =T35+U34 -> 17537.792
A36: 5 | B36: =POWER(1-$B$8,A36)*$B$3 -> 63391.169 | C36: =POWER(1+$B$9,A36) -> 1.1592741 | D36: =$B$7*C36*$B$10 -> 0 | E36: =$B$7*$C36*$B$11 -> 0 | F36: =$B$7*$C36*$B$12 -> 0 | G36: =SUM(D36:F36) -> 0 | H36: =IF(A36=0,$B$17*$B$14*$B$13,H35*$B$13) -> 19.873324 | I36: =$I$29*B36 -> 5388.2494 | J36: =MAX(IF(A36>=$B$22,J35-$B$24,$B$17),0) -> 38165.506 | K36: =IF(A36>=$B$20,J36*$B$18,0) -> 1526.6202 | L36: =IF(A36=$B$28,$B$27,0) -> 0 | M36: =I36-G36-K36+L36 -> 3861.6291 | N36: =M36-H36 -> 3841.7558 | O36: =IF(N36<0,N36,0) -> 0 | P36: =IF(N36>0,N36+O35,0) -> 3841.7558 | Q36: =$B$25*P36 -> 883.60384 | R36: =M36-Q36 -> 2978.0253 | S36: =IFERROR(__xludf.DUMMYFUNCTION("IF(ISBETWEEN(A36,$B$22,$B$22+$B$19-1),$B$24,0)"),5452.215109178511) -> 5452.2151 | T36: =R36-S36 -> -2474.1898 | U36: =T36+U35 -> 15063.602
A37: 6 | B37: =POWER(1-$B$8,A37)*$B$3 -> 63074.213 | C37: =POWER(1+$B$9,A37) -> 1.1940523 | D37: =$B$7*C37*$B$10 -> 0 | E37: =$B$7*$C37*$B$11 -> 0 | F37: =$B$7*$C37*$B$12 -> 0 | G37: =SUM(D37:F37) -> 0 | H37: =IF(A37=0,$B$17*$B$14*$B$13,H36*$B$13) -> 5.9619972 | I37: =$I$29*B37 -> 5361.3081 | J37: =MAX(IF(A37>=$B$22,J36-$B$24,$B$17),0) -> 32713.291 | K37: =IF(A37>=$B$20,J37*$B$18,0) -> 1308.5316 | L37: =IF(A37=$B$28,$B$27,0) -> 0 | M37: =I37-G37-K37+L37 -> 4052.7765 | N37: =M37-H37 -> 4046.8145 | O37: =IF(N37<0,N37,0) -> 0 | P37: =IF(N37>0,N37+O36,0) -> 4046.8145 | Q37: =$B$25*P37 -> 930.76733 | R37: =M37-Q37 -> 3122.0092 | S37: =IFERROR(__xludf.DUMMYFUNCTION("IF(ISBETWEEN(A37,$B$22,$B$22+$B$19-1),$B$24,0)"),5452.215109178511) -> 5452.2151 | T37: =R37-S37 -> -2330.206 | U37: =T37+U36 -> 12733.396
A38: 7 | B38: =POWER(1-$B$8,A38)*$B$3 -> 62758.842 | C38: =POWER(1+$B$9,A38) -> 1.2298739 | D38: =$B$7*C38*$B$10 -> 0 | E38: =$B$7*$C38*$B$11 -> 0 | F38: =$B$7*$C38*$B$12 -> 0 | G38: =SUM(D38:F38) -> 0 | H38: =IF(A38=0,$B$17*$B$14*$B$13,H37*$B$13) -> 1.7885992 | I38: =$I$29*B38 -> 5334.5016 | J38: =MAX(IF(A38>=$B$22,J37-$B$24,$B$17),0) -> 27261.076 | K38: =IF(A38>=$B$20,J38*$B$18,0) -> 1090.443 | L38: =IF(A38=$B$28,$B$27,0) -> 0 | M38: =I38-G38-K38+L38 -> 4244.0586 | N38: =M38-H38 -> 4242.27 | O38: =IF(N38<0,N38,0) -> 0 | P38: =IF(N38>0,N38+O37,0) -> 4242.27 | Q38: =$B$25*P38 -> 975.72209 | R38: =M38-Q38 -> 3268.3365 | S38: =IFERROR(__xludf.DUMMYFUNCTION("IF(ISBETWEEN(A38,$B$22,$B$22+$B$19-1),$B$24,0)"),5452.215109178511) -> 5452.2151 | T38: =R38-S38 -> -2183.8786 | U38: =T38+U37 -> 10549.517
A39: 8 | B39: =POWER(1-$B$8,A39)*$B$3 -> 62445.048 | C39: =POWER(1+$B$9,A39) -> 1.2667701 | D39: =$B$7*C39*$B$10 -> 0 | E39: =$B$7*$C39*$B$11 -> 0 | F39: =$B$7*$C39*$B$12 -> 0 | G39: =SUM(D39:F39) -> 0 | H39: =IF(A39=0,$B$17*$B$14*$B$13,H38*$B$13) -> 0.53657975 | I39: =$I$29*B39 -> 5307.8291 | J39: =MAX(IF(A39>=$B$22,J38-$B$24,$B$17),0) -> 21808.86 | K39: =IF(A39>=$B$20,J39*$B$18,0) -> 872.35442 | L39: =IF(A39=$B$28,$B$27,0) -> 0 | M39: =I39-G39-K39+L39 -> 4435.4746 | N39: =M39-H39 -> 4434.9381 | O39: =IF(N39<0,N39,0) -> 0 | P39: =IF(N39>0,N39+O38,0) -> 4434.9381 | Q39: =$B$25*P39 -> 1020.0358 | R39: =M39-Q39 -> 3415.4389 | S39: =IFERROR(__xludf.DUMMYFUNCTION("IF(ISBETWEEN(A39,$B$22,$B$22+$B$19-1),$B$24,0)"),5452.215109178511) -> 5452.2151 | T39: =R39-S39 -> -2036.7762 | U39: =T39+U38 -> 8512.7412
A40: 9 | B40: =POWER(1-$B$8,A40)*$B$3 -> 62132.823 | C40: =POWER(1+$B$9,A40) -> 1.3047732 | D40: =$B$7*C40*$B$10 -> 0 | E40: =$B$7*$C40*$B$11 -> 0 | F40: =$B$7*$C40*$B$12 -> 0 | G40: =SUM(D40:F40) -> 0 | H40: =IF(A40=0,$B$17*$B$14*$B$13,H39*$B$13) -> 0.16097392 | I40: =$I$29*B40 -> 5281.2899 | J40: =MAX(IF(A40>=$B$22,J39-$B$24,$B$17),0) -> 16356.645 | K40: =IF(A40>=$B$20,J40*$B$18,0) -> 654.26581 | L40: =IF(A40=$B$28,$B$27,0) -> 0 | M40: =I40-G40-K40+L40 -> 4627.0241 | N40: =M40-H40 -> 4626.8631 | O40: =IF(N40<0,N40,0) -> 0 | P40: =IF(N40>0,N40+O39,0) -> 4626.8631 | Q40: =$B$25*P40 -> 1064.1785 | R40: =M40-Q40 -> 3562.8456 | S40: =IFERROR(__xludf.DUMMYFUNCTION("IF(ISBETWEEN(A40,$B$22,$B$22+$B$19-1),$B$24,0)"),5452.215109178511) -> 5452.2151 | T40: =R40-S40 -> -1889.3695 | U40: =T40+U39 -> 6623.3717
A41: 10 | B41: =POWER(1-$B$8,A41)*$B$3 -> 61822.158 | C41: =POWER(1+$B$9,A41) -> 1.3439164 | D41: =$B$7*C41*$B$10 -> 0 | E41: =$B$7*$C41*$B$11 -> 0 | F41: =$B$7*$C41*$B$12 -> 0 | G41: =SUM(D41:F41) -> 0 | H41: =IF(A41=0,$B$17*$B$14*$B$13,H40*$B$13) -> 0.048292177 | I41: =$I$29*B41 -> 5254.8835 | J41: =MAX(IF(A41>=$B$22,J40-$B$24,$B$17),0) -> 10904.43 | K41: =IF(A41>=$B$20,J41*$B$18,0) -> 436.17721 | L41: =IF(A41=$B$28,$B$27,0) -> 0 | M41: =I41-G41-K41+L41 -> 4818.7063 | N41: =M41-H41 -> 4818.658 | O41: =IF(N41<0,N41,0) -> 0 | P41: =IF(N41>0,N41+O40,0) -> 4818.658 | Q41: =$B$25*P41 -> 1108.2913 | R41: =M41-Q41 -> 3710.4149 | S41: =IFERROR(__xludf.DUMMYFUNCTION("IF(ISBETWEEN(A41,$B$22,$B$22+$B$19-1),$B$24,0)"),5452.215109178511) -> 5452.2151 | T41: =R41-S41 -> -1741.8002 | U41: =T41+U40 -> 4881.5715
A42: 11 | B42: =POWER(1-$B$8,A42)*$B$3 -> 61513.048 | C42: =POWER(1+$B$9,A42) -> 1.3842339 | D42: =$B$7*C42*$B$10 -> 0 | E42: =$B$7*$C42*$B$11 -> 0 | F42: =$B$7*$C42*$B$12 -> 0 | G42: =SUM(D42:F42) -> 0 | H42: =IF(A42=0,$B$17*$B$14*$B$13,H41*$B$13) -> 0.014487653 | I42: =$I$29*B42 -> 5228.6091 | J42: =MAX(IF(A42>=$B$22,J41-$B$24,$B$17),0) -> 5452.2151 | K42: =IF(A42>=$B$20,J42*$B$18,0) -> 218.0886 | L42: =IF(A42=$B$28,$B$27,0) -> 0 | M42: =I42-G42-K42+L42 -> 5010.5204 | N42: =M42-H42 -> 5010.506 | O42: =IF(N42<0,N42,0) -> 0 | P42: =IF(N42>0,N42+O41,0) -> 5010.506 | Q42: =$B$25*P42 -> 1152.4164 | R42: =M42-Q42 -> 3858.1041 | S42: =IFERROR(__xludf.DUMMYFUNCTION("IF(ISBETWEEN(A42,$B$22,$B$22+$B$19-1),$B$24,0)"),5452.215109178511) -> 5452.2151 | T42: =R42-S42 -> -1594.111 | U42: =T42+U41 -> 3287.4605
A43: 12 | B43: =POWER(1-$B$8,A43)*$B$3 -> 61205.482 | C43: =POWER(1+$B$9,A43) -> 1.4257609 | D43: =$B$7*C43*$B$10 -> 0 | E43: =$B$7*$C43*$B$11 -> 0 | F43: =$B$7*$C43*$B$12 -> 0 | G43: =SUM(D43:F43) -> 0 | H43: =IF(A43=0,$B$17*$B$14*$B$13,H42*$B$13) -> 0.004346296 | I43: =$I$29*B43 -> 5202.466 | J43: =MAX(IF(A43>=$B$22,J42-$B$24,$B$17),0) -> 0 | K43: =IF(A43>=$B$20,J43*$B$18,0) -> 0 | L43: =IF(A43=$B$28,$B$27,0) -> 0 | M43: =I43-G43-K43+L43 -> 5202.466 | N43: =M43-H43 -> 5202.4617 | O43: =IF(N43<0,N43,0) -> 0 | P43: =IF(N43>0,N43+O42,0) -> 5202.4617 | Q43: =$B$25*P43 -> 1196.5662 | R43: =M43-Q43 -> 4005.8998 | S43: =IFERROR(__xludf.DUMMYFUNCTION("IF(ISBETWEEN(A43,$B$22,$B$22+$B$19-1),$B$24,0)"),5452.215109178511) -> 5452.2151 | T43: =R43-S43 -> -1446.3153 | U43: =T43+U42 -> 1841.1452
A44: 13 | B44: =POWER(1-$B$8,A44)*$B$3 -> 60899.455 | C44: =POWER(1+$B$9,A44) -> 1.4685337 | D44: =$B$7*C44*$B$10 -> 0 | E44: =$B$7*$C44*$B$11 -> 0 | F44: =$B$7*$C44*$B$12 -> 0 | G44: =SUM(D44:F44) -> 0 | H44: =IF(A44=0,$B$17*$B$14*$B$13,H43*$B$13) -> 0.0013038888 | I44: =$I$29*B44 -> 5176.4537 | J44: =MAX(IF(A44>=$B$22,J43-$B$24,$B$17),0) -> 0 | K44: =IF(A44>=$B$20,J44*$B$18,0) -> 0 | L44: =IF(A44=$B$28,$B$27,0) -> 0 | M44: =I44-G44-K44+L44 -> 5176.4537 | N44: =M44-H44 -> 5176.4524 | O44: =IF(N44<0,N44,0) -> 0 | P44: =IF(N44>0,N44+O43,0) -> 5176.4524 | Q44: =$B$25*P44 -> 1190.584 | R44: =M44-Q44 -> 3985.8696 | S44: =IFERROR(__xludf.DUMMYFUNCTION("IF(ISBETWEEN(A44,$B$22,$B$22+$B$19-1),$B$24,0)"),0.0) -> 0 | T44: =R44-S44 -> 3985.8696 | U44: =T44+U43 -> 5827.0148
A45: 14 | B45: =POWER(1-$B$8,A45)*$B$3 -> 60594.958 | C45: =POWER(1+$B$9,A45) -> 1.5125897 | D45: =$B$7*C45*$B$10 -> 0 | E45: =$B$7*$C45*$B$11 -> 0 | F45: =$B$7*$C45*$B$12 -> 0 | G45: =SUM(D45:F45) -> 0 | H45: =IF(A45=0,$B$17*$B$14*$B$13,H44*$B$13) -> 0.00039116664 | I45: =$I$29*B45 -> 5150.5714 | J45: =MAX(IF(A45>=$B$22,J44-$B$24,$B$17),0) -> 0 | K45: =IF(A45>=$B$20,J45*$B$18,0) -> 0 | L45: =IF(A45=$B$28,$B$27,0) -> 0 | M45: =I45-G45-K45+L45 -> 5150.5714 | N45: =M45-H45 -> 5150.571 | O45: =IF(N45<0,N45,0) -> 0 | P45: =IF(N45>0,N45+O44,0) -> 5150.571 | Q45: =$B$25*P45 -> 1184.6313 | R45: =M45-Q45 -> 3965.9401 | S45: =IFERROR(__xludf.DUMMYFUNCTION("IF(ISBETWEEN(A45,$B$22,$B$22+$B$19-1),$B$24,0)"),0.0) -> 0 | T45: =R45-S45 -> 3965.9401 | U45: =T45+U44 -> 9792.9549
A46: 15 | B46: =POWER(1-$B$8,A46)*$B$3 -> 60291.983 | C46: =POWER(1+$B$9,A46) -> 1.5579674 | D46: =$B$7*C46*$B$10 -> 0 | E46: =$B$7*$C46*$B$11 -> 0 | F46: =$B$7*$C46*$B$12 -> 0 | G46: =SUM(D46:F46) -> 0 | H46: =IF(A46=0,$B$17*$B$14*$B$13,H45*$B$13) -> 0.00011734999 | I46: =$I$29*B46 -> 5124.8186 | J46: =MAX(IF(A46>=$B$22,J45-$B$24,$B$17),0) -> 0 | K46: =IF(A46>=$B$20,J46*$B$18,0) -> 0 | L46: =IF(A46=$B$28,$B$27,0) -> 0 | M46: =I46-G46-K46+L46 -> 5124.8186 | N46: =M46-H46 -> 5124.8184 | O46: =IF(N46<0,N46,0) -> 0 | P46: =IF(N46>0,N46+O45,0) -> 5124.8184 | Q46: =$B$25*P46 -> 1178.7082 | R46: =M46-Q46 -> 3946.1103 | S46: =IFERROR(__xludf.DUMMYFUNCTION("IF(ISBETWEEN(A46,$B$22,$B$22+$B$19-1),$B$24,0)"),0.0) -> 0 | T46: =R46-S46 -> 3946.1103 | U46: =T46+U45 -> 13739.065
A47: 16 | B47: =POWER(1-$B$8,A47)*$B$3 -> 59990.523 | C47: =POWER(1+$B$9,A47) -> 1.6047064 | D47: =$B$7*C47*$B$10 -> 0 | E47: =$B$7*$C47*$B$11 -> 0 | F47: =$B$7*$C47*$B$12 -> 0 | G47: =SUM(D47:F47) -> 0 | H47: =IF(A47=0,$B$17*$B$14*$B$13,H46*$B$13) -> 3.5204997e-05 | I47: =$I$29*B47 -> 5099.1945 | J47: =MAX(IF(A47>=$B$22,J46-$B$24,$B$17),0) -> 0 | K47: =IF(A47>=$B$20,J47*$B$18,0) -> 0 | L47: =IF(A47=$B$28,$B$27,0) -> 0 | M47: =I47-G47-K47+L47 -> 5099.1945 | N47: =M47-H47 -> 5099.1944 | O47: =IF(N47<0,N47,0) -> 0 | P47: =IF(N47>0,N47+O46,0) -> 5099.1944 | Q47: =$B$25*P47 -> 1172.8147 | R47: =M47-Q47 -> 3926.3797 | S47: =IFERROR(__xludf.DUMMYFUNCTION("IF(ISBETWEEN(A47,$B$22,$B$22+$B$19-1),$B$24,0)"),0.0) -> 0 | T47: =R47-S47 -> 3926.3797 | U47: =T47+U46 -> 17665.445
A48: 17 | B48: =POWER(1-$B$8,A48)*$B$3 -> 59690.57 | C48: =POWER(1+$B$9,A48) -> 1.6528476 | D48: =$B$7*C48*$B$10 -> 0 | E48: =$B$7*$C48*$B$11 -> 0 | F48: =$B$7*$C48*$B$12 -> 0 | G48: =SUM(D48:F48) -> 0 | H48: =IF(A48=0,$B$17*$B$14*$B$13,H47*$B$13) -> 1.0561499e-05 | I48: =$I$29*B48 -> 5073.6985 | J48: =MAX(IF(A48>=$B$22,J47-$B$24,$B$17),0) -> 0 | K48: =IF(A48>=$B$20,J48*$B$18,0) -> 0 | L48: =IF(A48=$B$28,$B$27,0) -> 0 | M48: =I48-G48-K48+L48 -> 5073.6985 | N48: =M48-H48 -> 5073.6985 | O48: =IF(N48<0,N48,0) -> 0 | P48: =IF(N48>0,N48+O47,0) -> 5073.6985 | Q48: =$B$25*P48 -> 1166.9506 | R48: =M48-Q48 -> 3906.7478 | S48: =IFERROR(__xludf.DUMMYFUNCTION("IF(ISBETWEEN(A48,$B$22,$B$22+$B$19-1),$B$24,0)"),0.0) -> 0 | T48: =R48-S48 -> 3906.7478 | U48: =T48+U47 -> 21572.193
A49: 18 | B49: =POWER(1-$B$8,A49)*$B$3 -> 59392.118 | C49: =POWER(1+$B$9,A49) -> 1.7024331 | D49: =$B$7*C49*$B$10 -> 0 | E49: =$B$7*$C49*$B$11 -> 0 | F49: =$B$7*$C49*$B$12 -> 0 | G49: =SUM(D49:F49) -> 0 | H49: =IF(A49=0,$B$17*$B$14*$B$13,H48*$B$13) -> 3.1684498e-06 | I49: =$I$29*B49 -> 5048.33 | J49: =MAX(IF(A49>=$B$22,J48-$B$24,$B$17),0) -> 0 | K49: =IF(A49>=$B$20,J49*$B$18,0) -> 0 | L49: =IF(A49=$B$28,$B$27,0) -> 0 | M49: =I49-G49-K49+L49 -> 5048.33 | N49: =M49-H49 -> 5048.33 | O49: =IF(N49<0,N49,0) -> 0 | P49: =IF(N49>0,N49+O48,0) -> 5048.33 | Q49: =$B$25*P49 -> 1161.1159 | R49: =M49-Q49 -> 3887.2141 | S49: =IFERROR(__xludf.DUMMYFUNCTION("IF(ISBETWEEN(A49,$B$22,$B$22+$B$19-1),$B$24,0)"),0.0) -> 0 | T49: =R49-S49 -> 3887.2141 | U49: =T49+U48 -> 25459.407
A50: 19 | B50: =POWER(1-$B$8,A50)*$B$3 -> 59095.157 | C50: =POWER(1+$B$9,A50) -> 1.7535061 | D50: =$B$7*C50*$B$10 -> 0 | E50: =$B$7*$C50*$B$11 -> 0 | F50: =$B$7*$C50*$B$12 -> 0 | G50: =SUM(D50:F50) -> 0 | H50: =IF(A50=0,$B$17*$B$14*$B$13,H49*$B$13) -> 9.5053493e-07 | I50: =$I$29*B50 -> 5023.0883 | J50: =MAX(IF(A50>=$B$22,J49-$B$24,$B$17),0) -> 0 | K50: =IF(A50>=$B$20,J50*$B$18,0) -> 0 | L50: =IF(A50=$B$28,$B$27,0) -> 0 | M50: =I50-G50-K50+L50 -> 5023.0883 | N50: =M50-H50 -> 5023.0883 | O50: =IF(N50<0,N50,0) -> 0 | P50: =IF(N50>0,N50+O49,0) -> 5023.0883 | Q50: =$B$25*P50 -> 1155.3103 | R50: =M50-Q50 -> 3867.778 | S50: =IFERROR(__xludf.DUMMYFUNCTION("IF(ISBETWEEN(A50,$B$22,$B$22+$B$19-1),$B$24,0)"),0.0) -> 0 | T50: =R50-S50 -> 3867.778 | U50: =T50+U49 -> 29327.185
A51: 20 | B51: =POWER(1-$B$8,A51)*$B$3 -> 58799.681 | C51: =POWER(1+$B$9,A51) -> 1.8061112 | D51: =$B$7*C51*$B$10 -> 0 | E51: =$B$7*$C51*$B$11 -> 0 | F51: =$B$7*$C51*$B$12 -> 0 | G51: =SUM(D51:F51) -> 0 | H51: =IF(A51=0,$B$17*$B$14*$B$13,H50*$B$13) -> 2.8516048e-07 | I51: =$I$29*B51 -> 4997.9729 | J51: =MAX(IF(A51>=$B$22,J50-$B$24,$B$17),0) -> 0 | K51: =IF(A51>=$B$20,J51*$B$18,0) -> 0 | L51: =IF(A51=$B$28,$B$27,0) -> 0 | M51: =I51-G51-K51+L51 -> 4997.9729 | N51: =M51-H51 -> 4997.9729 | O51: =IF(N51<0,N51,0) -> 0 | P51: =IF(N51>0,N51+O50,0) -> 4997.9729 | Q51: =$B$25*P51 -> 1149.5338 | R51: =M51-Q51 -> 3848.4391 | S51: =IFERROR(__xludf.DUMMYFUNCTION("IF(ISBETWEEN(A51,$B$22,$B$22+$B$19-1),$B$24,0)"),0.0) -> 0 | T51: =R51-S51 -> 3848.4391 | U51: =T51+U50 -> 33175.624
A52: 21 | B52: =POWER(1-$B$8,A52)*$B$3 -> 58505.683 | C52: =POWER(1+$B$9,A52) -> 1.8602946 | D52: =$B$7*C52*$B$10 -> 0 | E52: =$B$7*$C52*$B$11 -> 0 | F52: =$B$7*$C52*$B$12 -> 0 | G52: =SUM(D52:F52) -> 0 | H52: =IF(A52=0,$B$17*$B$14*$B$13,H51*$B$13) -> 8.5548144e-08 | I52: =$I$29*B52 -> 4972.983 | J52: =MAX(IF(A52>=$B$22,J51-$B$24,$B$17),0) -> 0 | K52: =IF(A52>=$B$20,J52*$B$18,0) -> 0 | L52: =IF(A52=$B$28,$B$27,0) -> 0 | M52: =I52-G52-K52+L52 -> 4972.983 | N52: =M52-H52 -> 4972.983 | O52: =IF(N52<0,N52,0) -> 0 | P52: =IF(N52>0,N52+O51,0) -> 4972.983 | Q52: =$B$25*P52 -> 1143.7861 | R52: =M52-Q52 -> 3829.1969 | S52: =IFERROR(__xludf.DUMMYFUNCTION("IF(ISBETWEEN(A52,$B$22,$B$22+$B$19-1),$B$24,0)"),0.0) -> 0 | T52: =R52-S52 -> 3829.1969 | U52: =T52+U51 -> 37004.821
A53: 22 | B53: =POWER(1-$B$8,A53)*$B$3 -> 58213.154 | C53: =POWER(1+$B$9,A53) -> 1.9161034 | D53: =$B$7*C53*$B$10 -> 0 | E53: =$B$7*$C53*$B$11 -> 0 | F53: =$B$7*$C53*$B$12 -> 0 | G53: =SUM(D53:F53) -> 0 | H53: =IF(A53=0,$B$17*$B$14*$B$13,H52*$B$13) -> 2.5664443e-08 | I53: =$I$29*B53 -> 4948.1181 | J53: =MAX(IF(A53>=$B$22,J52-$B$24,$B$17),0) -> 0 | K53: =IF(A53>=$B$20,J53*$B$18,0) -> 0 | L53: =IF(A53=$B$28,$B$27,0) -> 0 | M53: =I53-G53-K53+L53 -> 4948.1181 | N53: =M53-H53 -> 4948.1181 | O53: =IF(N53<0,N53,0) -> 0 | P53: =IF(N53>0,N53+O52,0) -> 4948.1181 | Q53: =$B$25*P53 -> 1138.0672 | R53: =M53-Q53 -> 3810.051 | S53: =IFERROR(__xludf.DUMMYFUNCTION("IF(ISBETWEEN(A53,$B$22,$B$22+$B$19-1),$B$24,0)"),0.0) -> 0 | T53: =R53-S53 -> 3810.051 | U53: =T53+U52 -> 40814.872
A54: 23 | B54: =POWER(1-$B$8,A54)*$B$3 -> 57922.089 | C54: =POWER(1+$B$9,A54) -> 1.9735865 | D54: =$B$7*C54*$B$10 -> 0 | E54: =$B$7*$C54*$B$11 -> 0 | F54: =$B$7*$C54*$B$12 -> 0 | G54: =SUM(D54:F54) -> 0 | H54: =IF(A54=0,$B$17*$B$14*$B$13,H53*$B$13) -> 7.6993329e-09 | I54: =$I$29*B54 -> 4923.3775 | J54: =MAX(IF(A54>=$B$22,J53-$B$24,$B$17),0) -> 0 | K54: =IF(A54>=$B$20,J54*$B$18,0) -> 0 | L54: =IF(A54=$B$28,$B$27,0) -> 0 | M54: =I54-G54-K54+L54 -> 4923.3775 | N54: =M54-H54 -> 4923.3775 | O54: =IF(N54<0,N54,0) -> 0 | P54: =IF(N54>0,N54+O53,0) -> 4923.3775 | Q54: =$B$25*P54 -> 1132.3768 | R54: =M54-Q54 -> 3791.0007 | S54: =IFERROR(__xludf.DUMMYFUNCTION("IF(ISBETWEEN(A54,$B$22,$B$22+$B$19-1),$B$24,0)"),0.0) -> 0 | T54: =R54-S54 -> 3791.0007 | U54: =T54+U53 -> 44605.873
A55: 24 | B55: =POWER(1-$B$8,A55)*$B$3 -> 57632.478 | C55: =POWER(1+$B$9,A55) -> 2.0327941 | D55: =$B$7*C55*$B$10 -> 0 | E55: =$B$7*$C55*$B$11 -> 0 | F55: =$B$7*$C55*$B$12 -> 0 | G55: =SUM(D55:F55) -> 0 | H55: =IF(A55=0,$B$17*$B$14*$B$13,H54*$B$13) -> 2.3097999e-09 | I55: =$I$29*B55 -> 4898.7606 | J55: =MAX(IF(A55>=$B$22,J54-$B$24,$B$17),0) -> 0 | K55: =IF(A55>=$B$20,J55*$B$18,0) -> 0 | L55: =IF(A55=$B$28,$B$27,0) -> 0 | M55: =I55-G55-K55+L55 -> 4898.7606 | N55: =M55-H55 -> 4898.7606 | O55: =IF(N55<0,N55,0) -> 0 | P55: =IF(N55>0,N55+O54,0) -> 4898.7606 | Q55: =$B$25*P55 -> 1126.7149 | R55: =M55-Q55 -> 3772.0457 | S55: =IFERROR(__xludf.DUMMYFUNCTION("IF(ISBETWEEN(A55,$B$22,$B$22+$B$19-1),$B$24,0)"),0.0) -> 0 | T55: =R55-S55 -> 3772.0457 | U55: =T55+U54 -> 48377.918
B56: =SUM(B31:B55) -> 1531136.8 | D56: =SUM(D31:D55) -> 0 | E56: =SUM(E31:E55) -> 0 | F56: =SUM(F31:F55) -> 0 | G56: =SUM(G31:G55) -> 0 | H56: =SUM(H31:H55) -> 11683.318 | I56: =SUM(I31:I55) -> 130146.63 | K56: =SUM(K31:K55) -> 16356.645 | L56: =SUM(L31:L55) -> 16356.645 | M56: =SUM(M31:M55) -> 130146.63 | Q56: =SUM(Q31:Q55) -> 27246.562 | R56: =SUM(R31:R55) -> 102900.07 | S56: =SUM(S31:S55) -> 54522.151 | T56: =SUM(T31:T55) -> 48377.918

Sheet 50% Grant, flow through BVGEC
A2: Capacity Factor | B2: 0.17 | D2: Norfolk | E2: 0.33
A3: System Output | B3: 65000 | D3: BVGEC | E3: 0.33
A4: Hours per Year | B4: 8766 | D4: Community | E4: =1-E2-E3 -> 0.34
A5: System Size | B5: =$B$3/$B$4/$B$2 -> 43.617721
A6: Install Cost | B6: 2.5
A7: Capex | B7: =B5*B6*1000 -> 109044.3
A8: Degradation | B8: 0.005
A9: Inflation | B9: 0.03
A10: Admin Rate | B10: =$E$11 -> 0.014 | D10: Combined OPEX Rate | E10: 0.042
A11: Insurance Rate | B11: =$E$11 -> 0.014 | D11: Individual | E11: =E10/3 -> 0.014
A12: Maintenance Rate | B12: =$E$11 -> 0.014
A13: CCA Rate | B13: 0.3
A14: Half Year Rule | B14: 0.5
A15: Grant Rate | B15: 0.5 | L15: Current Bill | M15: ='Bill Comparison'!F28 -> 322479.95
A16: Grant Amount | B16: =B7*B15 -> 54522.151 | L16: New Bill | M16: ='Bill Comparison'!J28 -> 49771.697 | N16: Benefit Dist | O16: Annuity
A17: Net Capex | B17: =B7-B16 -> 54522.151 | L17: Available Savings | M17: ='Bill Comparison'!L28 -> 272708.26 | R17: Bill Saving | S17: =1-(I56+M16)/M15 -> 0.038498498
A18: Debt Rate | B18: 0.04 | L18: Norfolk Bill Savings | M18: =M17-I56 -> 12414.994 | N18: =M18/M19 -> 0.06225837
A19: Debt Term | B19: 10 | L19: Total Benefit | M19: =M18+T56+G56 -> 199410.84 | R19: Effective Savings | S19: =1-(M16+I56-M21)/M15 -> 0.24255948
L20: Norfolk Residual | M20: =M19*0.33-M18 -> 53390.583
L21: Norfolk Total | M21: =M18+M20 -> 65805.577 | N21: =M21/M19 -> 0.33 | O21: =M21/25 -> 2632.2231
A22: Repayment Start | B22: 3 | L22: BVGEC Residual | M22: =M19*0.45-G56 -> -77243.474
L23: BVGEC Total | M23: =M22+G56 -> 89734.878 | N23: =M23/M19 -> 0.45 | O23: =M23/25 -> 3589.3951
A24: Repayment Principal | B24: =B17/B19 -> 5452.2151 | L24: Community | M24: =M19-M21-M23 -> 43870.385 | N24: =M24/M19 -> 0.22 | O24: =M24/25 -> 1754.8154
A25: Tax Rate | B25: 0.23 | N25: =N21+N23+N24 -> 1
A26: ITC Rate | B26: 0.3
A27: ITC Amount | B27: =B26*B17 -> 16356.645 | L27: Utilization | M27: =M19/M17 -> 0.73122406
A28: ITC year | B28: 1
H29: Effective PPA | I29: 0.17
A30: Year | B30: Effective Output | C30: Escalation Factor | D30: Admin Cost | E30: Insurance Cost | F30: Maintenance Cost | G30: OPEX | H30: Capital Cost Allowance | I30: Revenue | J30: Debt Principal | K30: Debt Interest | L30: ITC Credit | M30: Pre Tax Operating Cashflow | N30: Taxable Income Before Carry Forward Loss | O30: Carry Forward Losses | P30: Taxable Income After Carry Forward Loss | Q30: Tax | R30: After Tax Income | S30: Principal Repayent | T30: Cashflow To Equity
A31: 0 | B31: =POWER(1-$B$8,A31)*$B$3 -> 65000 | C31: =POWER(1+$B$9,A31) -> 1 | D31: =$B$7*C31*$B$10 -> 1526.6202 | E31: =$B$7*$C31*$B$11 -> 1526.6202 | F31: =$B$7*$C31*$B$12 -> 1526.6202 | G31: =SUM(D31:F31) -> 4579.8607 | H31: =IF(A31=0,$B$17*$B$14*$B$13,H30*$B$13) -> 8178.3227 | I31: =$I$29*B31 -> 11050 | J31: =MAX(IF(A31>=$B$22,J30-$B$24,$B$17),0) -> 54522.151 | K31: =IF(A31>=$B$20,J31*$B$18,0) -> 2180.886 | L31: =IF(A31=$B$28,$B$27,0) -> 0 | M31: =I31-G31-K31+L31 -> 4289.2533 | N31: =M31-H31 -> -3889.0694 | O31: =IF(N31<0,N31,0) -> -3889.0694 | P31: =N31-O31 -> 0 | Q31: =$B$25*P31 -> 0 | R31: =M31-Q31 -> 4289.2533 | S31: =IFERROR(__xludf.DUMMYFUNCTION("IF(ISBETWEEN(A31,$B$22,$B$22+$B$19-1),$B$24,0)"),0.0) -> 0 | T31: =R31-S31 -> 4289.2533 | U31: =T31 -> 4289.2533
A32: 1 | B32: =POWER(1-$B$8,A32)*$B$3 -> 64675 | C32: =POWER(1+$B$9,A32) -> 1.03 | D32: =$B$7*C32*$B$10 -> 1572.4188 | E32: =$B$7*$C32*$B$11 -> 1572.4188 | F32: =$B$7*$C32*$B$12 -> 1572.4188 | G32: =SUM(D32:F32) -> 4717.2565 | H32: =IF(A32=0,$B$17*$B$14*$B$13,H31*$B$13) -> 2453.4968 | I32: =$I$29*B32 -> 10994.75 | J32: =MAX(IF(A32>=$B$22,J31-$B$24,$B$17),0) -> 54522.151 | K32: =IF(A32>=$B$20,J32*$B$18,0) -> 2180.886 | L32: =IF(A32=$B$28,$B$27,0) -> 16356.645 | M32: =I32-G32-K32+L32 -> 20453.253 | N32: =M32-H32 -> 17999.756 | O32: =IF(N32<0,N32,0) -> 0 | P32: =IF(N32>0,N32+O31,0) -> 14110.687 | Q32: =$B$25*P32 -> 3245.4579 | R32: =M32-Q32 -> 17207.795 | S32: =IFERROR(__xludf.DUMMYFUNCTION("IF(ISBETWEEN(A32,$B$22,$B$22+$B$19-1),$B$24,0)"),0.0) -> 0 | T32: =R32-S32 -> 17207.795 | U32: =T32+U31 -> 21497.048
A33: 2 | B33: =POWER(1-$B$8,A33)*$B$3 -> 64351.625 | C33: =POWER(1+$B$9,A33) -> 1.0609 | D33: =$B$7*C33*$B$10 -> 1619.5914 | E33: =$B$7*$C33*$B$11 -> 1619.5914 | F33: =$B$7*$C33*$B$12 -> 1619.5914 | G33: =SUM(D33:F33) -> 4858.7742 | H33: =IF(A33=0,$B$17*$B$14*$B$13,H32*$B$13) -> 736.04904 | I33: =$I$29*B33 -> 10939.776 | J33: =MAX(IF(A33>=$B$22,J32-$B$24,$B$17),0) -> 54522.151 | K33: =IF(A33>=$B$20,J33*$B$18,0) -> 2180.886 | L33: =IF(A33=$B$28,$B$27,0) -> 0 | M33: =I33-G33-K33+L33 -> 3900.116 | N33: =M33-H33 -> 3164.067 | O33: =IF(N33<0,N33,0) -> 0 | P33: =IF(N33>0,N33+O32,0) -> 3164.067 | Q33: =$B$25*P33 -> 727.7354 | R33: =M33-Q33 -> 3172.3806 | S33: =IFERROR(__xludf.DUMMYFUNCTION("IF(ISBETWEEN(A33,$B$22,$B$22+$B$19-1),$B$24,0)"),0.0) -> 0 | T33: =R33-S33 -> 3172.3806 | U33: =T33+U32 -> 24669.429
A34: 3 | B34: =POWER(1-$B$8,A34)*$B$3 -> 64029.867 | C34: =POWER(1+$B$9,A34) -> 1.092727 | D34: =$B$7*C34*$B$10 -> 1668.1791 | E34: =$B$7*$C34*$B$11 -> 1668.1791 | F34: =$B$7*$C34*$B$12 -> 1668.1791 | G34: =SUM(D34:F34) -> 5004.5374 | H34: =IF(A34=0,$B$17*$B$14*$B$13,H33*$B$13) -> 220.81471 | I34: =$I$29*B34 -> 10885.077 | J34: =MAX(IF(A34>=$B$22,J33-$B$24,$B$17),0) -> 49069.936 | K34: =IF(A34>=$B$20,J34*$B$18,0) -> 1962.7974 | L34: =IF(A34=$B$28,$B$27,0) -> 0 | M34: =I34-G34-K34+L34 -> 3917.7425 | N34: =M34-H34 -> 3696.9278 | O34: =IF(N34<0,N34,0) -> 0 | P34: =IF(N34>0,N34+O33,0) -> 3696.9278 | Q34: =$B$25*P34 -> 850.29339 | R34: =M34-Q34 -> 3067.4491 | S34: =IFERROR(__xludf.DUMMYFUNCTION("IF(ISBETWEEN(A34,$B$22,$B$22+$B$19-1),$B$24,0)"),5452.215109178511) -> 5452.2151 | T34: =R34-S34 -> -2384.766 | U34: =T34+U33 -> 22284.663
A35: 4 | B35: =POWER(1-$B$8,A35)*$B$3 -> 63709.718 | C35: =POWER(1+$B$9,A35) -> 1.1255088 | D35: =$B$7*C35*$B$10 -> 1718.2245 | E35: =$B$7*$C35*$B$11 -> 1718.2245 | F35: =$B$7*$C35*$B$12 -> 1718.2245 | G35: =SUM(D35:F35) -> 5154.6736 | H35: =IF(A35=0,$B$17*$B$14*$B$13,H34*$B$13) -> 66.244414 | I35: =$I$29*B35 -> 10830.652 | J35: =MAX(IF(A35>=$B$22,J34-$B$24,$B$17),0) -> 43617.721 | K35: =IF(A35>=$B$20,J35*$B$18,0) -> 1744.7088 | L35: =IF(A35=$B$28,$B$27,0) -> 0 | M35: =I35-G35-K35+L35 -> 3931.2696 | N35: =M35-H35 -> 3865.0252 | O35: =IF(N35<0,N35,0) -> 0 | P35: =IF(N35>0,N35+O34,0) -> 3865.0252 | Q35: =$B$25*P35 -> 888.95579 | R35: =M35-Q35 -> 3042.3138 | S35: =IFERROR(__xludf.DUMMYFUNCTION("IF(ISBETWEEN(A35,$B$22,$B$22+$B$19-1),$B$24,0)"),5452.215109178511) -> 5452.2151 | T35: =R35-S35 -> -2409.9013 | U35: =T35+U34 -> 19874.761
A36: 5 | B36: =POWER(1-$B$8,A36)*$B$3 -> 63391.169 | C36: =POWER(1+$B$9,A36) -> 1.1592741 | D36: =$B$7*C36*$B$10 -> 1769.7713 | E36: =$B$7*$C36*$B$11 -> 1769.7713 | F36: =$B$7*$C36*$B$12 -> 1769.7713 | G36: =SUM(D36:F36) -> 5309.3138 | H36: =IF(A36=0,$B$17*$B$14*$B$13,H35*$B$13) -> 19.873324 | I36: =$I$29*B36 -> 10776.499 | J36: =MAX(IF(A36>=$B$22,J35-$B$24,$B$17),0) -> 38165.506 | K36: =IF(A36>=$B$20,J36*$B$18,0) -> 1526.6202 | L36: =IF(A36=$B$28,$B$27,0) -> 0 | M36: =I36-G36-K36+L36 -> 3940.5647 | N36: =M36-H36 -> 3920.6914 | O36: =IF(N36<0,N36,0) -> 0 | P36: =IF(N36>0,N36+O35,0) -> 3920.6914 | Q36: =$B$25*P36 -> 901.75902 | R36: =M36-Q36 -> 3038.8057 | S36: =IFERROR(__xludf.DUMMYFUNCTION("IF(ISBETWEEN(A36,$B$22,$B$22+$B$19-1),$B$24,0)"),5452.215109178511) -> 5452.2151 | T36: =R36-S36 -> -2413.4094 | U36: =T36+U35 -> 17461.352
A37: 6 | B37: =POWER(1-$B$8,A37)*$B$3 -> 63074.213 | C37: =POWER(1+$B$9,A37) -> 1.1940523 | D37: =$B$7*C37*$B$10 -> 1822.8644 | E37: =$B$7*$C37*$B$11 -> 1822.8644 | F37: =$B$7*$C37*$B$12 -> 1822.8644 | G37: =SUM(D37:F37) -> 5468.5932 | H37: =IF(A37=0,$B$17*$B$14*$B$13,H36*$B$13) -> 5.9619972 | I37: =$I$29*B37 -> 10722.616 | J37: =MAX(IF(A37>=$B$22,J36-$B$24,$B$17),0) -> 32713.291 | K37: =IF(A37>=$B$20,J37*$B$18,0) -> 1308.5316 | L37: =IF(A37=$B$28,$B$27,0) -> 0 | M37: =I37-G37-K37+L37 -> 3945.4914 | N37: =M37-H37 -> 3939.5294 | O37: =IF(N37<0,N37,0) -> 0 | P37: =IF(N37>0,N37+O36,0) -> 3939.5294 | Q37: =$B$25*P37 -> 906.09177 | R37: =M37-Q37 -> 3039.3997 | S37: =IFERROR(__xludf.DUMMYFUNCTION("IF(ISBETWEEN(A37,$B$22,$B$22+$B$19-1),$B$24,0)"),5452.215109178511) -> 5452.2151 | T37: =R37-S37 -> -2412.8155 | U37: =T37+U36 -> 15048.537
A38: 7 | B38: =POWER(1-$B$8,A38)*$B$3 -> 62758.842 | C38: =POWER(1+$B$9,A38) -> 1.2298739 | D38: =$B$7*C38*$B$10 -> 1877.5503 | E38: =$B$7*$C38*$B$11 -> 1877.5503 | F38: =$B$7*$C38*$B$12 -> 1877.5503 | G38: =SUM(D38:F38) -> 5632.651 | H38: =IF(A38=0,$B$17*$B$14*$B$13,H37*$B$13) -> 1.7885992 | I38: =$I$29*B38 -> 10669.003 | J38: =MAX(IF(A38>=$B$22,J37-$B$24,$B$17),0) -> 27261.076 | K38: =IF(A38>=$B$20,J38*$B$18,0) -> 1090.443 | L38: =IF(A38=$B$28,$B$27,0) -> 0 | M38: =I38-G38-K38+L38 -> 3945.9092 | N38: =M38-H38 -> 3944.1206 | O38: =IF(N38<0,N38,0) -> 0 | P38: =IF(N38>0,N38+O37,0) -> 3944.1206 | Q38: =$B$25*P38 -> 907.14773 | R38: =M38-Q38 -> 3038.7614 | S38: =IFERROR(__xludf.DUMMYFUNCTION("IF(ISBETWEEN(A38,$B$22,$B$22+$B$19-1),$B$24,0)"),5452.215109178511) -> 5452.2151 | T38: =R38-S38 -> -2413.4537 | U38: =T38+U37 -> 12635.083
A39: 8 | B39: =POWER(1-$B$8,A39)*$B$3 -> 62445.048 | C39: =POWER(1+$B$9,A39) -> 1.2667701 | D39: =$B$7*C39*$B$10 -> 1933.8768 | E39: =$B$7*$C39*$B$11 -> 1933.8768 | F39: =$B$7*$C39*$B$12 -> 1933.8768 | G39: =SUM(D39:F39) -> 5801.6305 | H39: =IF(A39=0,$B$17*$B$14*$B$13,H38*$B$13) -> 0.53657975 | I39: =$I$29*B39 -> 10615.658 | J39: =MAX(IF(A39>=$B$22,J38-$B$24,$B$17),0) -> 21808.86 | K39: =IF(A39>=$B$20,J39*$B$18,0) -> 872.35442 | L39: =IF(A39=$B$28,$B$27,0) -> 0 | M39: =I39-G39-K39+L39 -> 3941.6732 | N39: =M39-H39 -> 3941.1366 | O39: =IF(N39<0,N39,0) -> 0 | P39: =IF(N39>0,N39+O38,0) -> 3941.1366 | Q39: =$B$25*P39 -> 906.46143 | R39: =M39-Q39 -> 3035.2118 | S39: =IFERROR(__xludf.DUMMYFUNCTION("IF(ISBETWEEN(A39,$B$22,$B$22+$B$19-1),$B$24,0)"),5452.215109178511) -> 5452.2151 | T39: =R39-S39 -> -2417.0033 | U39: =T39+U38 -> 10218.08
A40: 9 | B40: =POWER(1-$B$8,A40)*$B$3 -> 62132.823 | C40: =POWER(1+$B$9,A40) -> 1.3047732 | D40: =$B$7*C40*$B$10 -> 1991.8931 | E40: =$B$7*$C40*$B$11 -> 1991.8931 | F40: =$B$7*$C40*$B$12 -> 1991.8931 | G40: =SUM(D40:F40) -> 5975.6794 | H40: =IF(A40=0,$B$17*$B$14*$B$13,H39*$B$13) -> 0.16097392 | I40: =$I$29*B40 -> 10562.58 | J40: =MAX(IF(A40>=$B$22,J39-$B$24,$B$17),0) -> 16356.645 | K40: =IF(A40>=$B$20,J40*$B$18,0) -> 654.26581 | L40: =IF(A40=$B$28,$B$27,0) -> 0 | M40: =I40-G40-K40+L40 -> 3932.6346 | N40: =M40-H40 -> 3932.4736 | O40: =IF(N40<0,N40,0) -> 0 | P40: =IF(N40>0,N40+O39,0) -> 3932.4736 | Q40: =$B$25*P40 -> 904.46894 | R40: =M40-Q40 -> 3028.1657 | S40: =IFERROR(__xludf.DUMMYFUNCTION("IF(ISBETWEEN(A40,$B$22,$B$22+$B$19-1),$B$24,0)"),5452.215109178511) -> 5452.2151 | T40: =R40-S40 -> -2424.0494 | U40: =T40+U39 -> 7794.0301
A41: 10 | B41: =POWER(1-$B$8,A41)*$B$3 -> 61822.158 | C41: =POWER(1+$B$9,A41) -> 1.3439164 | D41: =$B$7*C41*$B$10 -> 2051.6499 | E41: =$B$7*$C41*$B$11 -> 2051.6499 | F41: =$B$7*$C41*$B$12 -> 2051.6499 | G41: =SUM(D41:F41) -> 6154.9498 | H41: =IF(A41=0,$B$17*$B$14*$B$13,H40*$B$13) -> 0.048292177 | I41: =$I$29*B41 -> 10509.767 | J41: =MAX(IF(A41>=$B$22,J40-$B$24,$B$17),0) -> 10904.43 | K41: =IF(A41>=$B$20,J41*$B$18,0) -> 436.17721 | L41: =IF(A41=$B$28,$B$27,0) -> 0 | M41: =I41-G41-K41+L41 -> 3918.6399 | N41: =M41-H41 -> 3918.5916 | O41: =IF(N41<0,N41,0) -> 0 | P41: =IF(N41>0,N41+O40,0) -> 3918.5916 | Q41: =$B$25*P41 -> 901.27608 | R41: =M41-Q41 -> 3017.3639 | S41: =IFERROR(__xludf.DUMMYFUNCTION("IF(ISBETWEEN(A41,$B$22,$B$22+$B$19-1),$B$24,0)"),5452.215109178511) -> 5452.2151 | T41: =R41-S41 -> -2434.8513 | U41: =T41+U40 -> 5359.1789
A42: 11 | B42: =POWER(1-$B$8,A42)*$B$3 -> 61513.048 | C42: =POWER(1+$B$9,A42) -> 1.3842339 | D42: =$B$7*C42*$B$10 -> 2113.1994 | E42: =$B$7*$C42*$B$11 -> 2113.1994 | F42: =$B$7*$C42*$B$12 -> 2113.1994 | G42: =SUM(D42:F42) -> 6339.5983 | H42: =IF(A42=0,$B$17*$B$14*$B$13,H41*$B$13) -> 0.014487653 | I42: =$I$29*B42 -> 10457.218 | J42: =MAX(IF(A42>=$B$22,J41-$B$24,$B$17),0) -> 5452.2151 | K42: =IF(A42>=$B$20,J42*$B$18,0) -> 218.0886 | L42: =IF(A42=$B$28,$B$27,0) -> 0 | M42: =I42-G42-K42+L42 -> 3899.5312 | N42: =M42-H42 -> 3899.5167 | O42: =IF(N42<0,N42,0) -> 0 | P42: =IF(N42>0,N42+O41,0) -> 3899.5167 | Q42: =$B$25*P42 -> 896.88885 | R42: =M42-Q42 -> 3002.6424 | S42: =IFERROR(__xludf.DUMMYFUNCTION("IF(ISBETWEEN(A42,$B$22,$B$22+$B$19-1),$B$24,0)"),5452.215109178511) -> 5452.2151 | T42: =R42-S42 -> -2449.5727 | U42: =T42+U41 -> 2909.6061
A43: 12 | B43: =POWER(1-$B$8,A43)*$B$3 -> 61205.482 | C43: =POWER(1+$B$9,A43) -> 1.4257609 | D43: =$B$7*C43*$B$10 -> 2176.5954 | E43: =$B$7*$C43*$B$11 -> 2176.5954 | F43: =$B$7*$C43*$B$12 -> 2176.5954 | G43: =SUM(D43:F43) -> 6529.7862 | H43: =IF(A43=0,$B$17*$B$14*$B$13,H42*$B$13) -> 0.004346296 | I43: =$I$29*B43 -> 10404.932 | J43: =MAX(IF(A43>=$B$22,J42-$B$24,$B$17),0) -> 0 | K43: =IF(A43>=$B$20,J43*$B$18,0) -> 0 | L43: =IF(A43=$B$28,$B$27,0) -> 0 | M43: =I43-G43-K43+L43 -> 3875.1458 | N43: =M43-H43 -> 3875.1414 | O43: =IF(N43<0,N43,0) -> 0 | P43: =IF(N43>0,N43+O42,0) -> 3875.1414 | Q43: =$B$25*P43 -> 891.28253 | R43: =M43-Q43 -> 2983.8632 | S43: =IFERROR(__xludf.DUMMYFUNCTION("IF(ISBETWEEN(A43,$B$22,$B$22+$B$19-1),$B$24,0)"),5452.215109178511) -> 5452.2151 | T43: =R43-S43 -> -2468.3519 | U43: =T43+U42 -> 441.25425
A44: 13 | B44: =POWER(1-$B$8,A44)*$B$3 -> 60899.455 | C44: =POWER(1+$B$9,A44) -> 1.4685337 | D44: =$B$7*C44*$B$10 -> 2241.8933 | E44: =$B$7*$C44*$B$11 -> 2241.8933 | F44: =$B$7*$C44*$B$12 -> 2241.8933 | G44: =SUM(D44:F44) -> 6725.6798 | H44: =IF(A44=0,$B$17*$B$14*$B$13,H43*$B$13) -> 0.0013038888 | I44: =$I$29*B44 -> 10352.907 | J44: =MAX(IF(A44>=$B$22,J43-$B$24,$B$17),0) -> 0 | K44: =IF(A44>=$B$20,J44*$B$18,0) -> 0 | L44: =IF(A44=$B$28,$B$27,0) -> 0 | M44: =I44-G44-K44+L44 -> 3627.2275 | N44: =M44-H44 -> 3627.2262 | O44: =IF(N44<0,N44,0) -> 0 | P44: =IF(N44>0,N44+O43,0) -> 3627.2262 | Q44: =$B$25*P44 -> 834.26203 | R44: =M44-Q44 -> 2792.9655 | S44: =IFERROR(__xludf.DUMMYFUNCTION("IF(ISBETWEEN(A44,$B$22,$B$22+$B$19-1),$B$24,0)"),0.0) -> 0 | T44: =R44-S44 -> 2792.9655 | U44: =T44+U43 -> 3234.2197
A45: 14 | B45: =POWER(1-$B$8,A45)*$B$3 -> 60594.958 | C45: =POWER(1+$B$9,A45) -> 1.5125897 | D45: =$B$7*C45*$B$10 -> 2309.1501 | E45: =$B$7*$C45*$B$11 -> 2309.1501 | F45: =$B$7*$C45*$B$12 -> 2309.1501 | G45: =SUM(D45:F45) -> 6927.4502 | H45: =IF(A45=0,$B$17*$B$14*$B$13,H44*$B$13) -> 0.00039116664 | I45: =$I$29*B45 -> 10301.143 | J45: =MAX(IF(A45>=$B$22,J44-$B$24,$B$17),0) -> 0 | K45: =IF(A45>=$B$20,J45*$B$18,0) -> 0 | L45: =IF(A45=$B$28,$B$27,0) -> 0 | M45: =I45-G45-K45+L45 -> 3373.6926 | N45: =M45-H45 -> 3373.6922 | O45: =IF(N45<0,N45,0) -> 0 | P45: =IF(N45>0,N45+O44,0) -> 3373.6922 | Q45: =$B$25*P45 -> 775.94921 | R45: =M45-Q45 -> 2597.7434 | S45: =IFERROR(__xludf.DUMMYFUNCTION("IF(ISBETWEEN(A45,$B$22,$B$22+$B$19-1),$B$24,0)"),0.0) -> 0 | T45: =R45-S45 -> 2597.7434 | U45: =T45+U44 -> 5831.9631
A46: 15 | B46: =POWER(1-$B$8,A46)*$B$3 -> 60291.983 | C46: =POWER(1+$B$9,A46) -> 1.5579674 | D46: =$B$7*C46*$B$10 -> 2378.4246 | E46: =$B$7*$C46*$B$11 -> 2378.4246 | F46: =$B$7*$C46*$B$12 -> 2378.4246 | G46: =SUM(D46:F46) -> 7135.2737 | H46: =IF(A46=0,$B$17*$B$14*$B$13,H45*$B$13) -> 0.00011734999 | I46: =$I$29*B46 -> 10249.637 | J46: =MAX(IF(A46>=$B$22,J45-$B$24,$B$17),0) -> 0 | K46: =IF(A46>=$B$20,J46*$B$18,0) -> 0 | L46: =IF(A46=$B$28,$B$27,0) -> 0 | M46: =I46-G46-K46+L46 -> 3114.3634 | N46: =M46-H46 -> 3114.3633 | O46: =IF(N46<0,N46,0) -> 0 | P46: =IF(N46>0,N46+O45,0) -> 3114.3633 | Q46: =$B$25*P46 -> 716.30355 | R46: =M46-Q46 -> 2398.0598 | S46: =IFERROR(__xludf.DUMMYFUNCTION("IF(ISBETWEEN(A46,$B$22,$B$22+$B$19-1),$B$24,0)"),0.0) -> 0 | T46: =R46-S46 -> 2398.0598 | U46: =T46+U45 -> 8230.023
A47: 16 | B47: =POWER(1-$B$8,A47)*$B$3 -> 59990.523 | C47: =POWER(1+$B$9,A47) -> 1.6047064 | D47: =$B$7*C47*$B$10 -> 2449.7773 | E47: =$B$7*$C47*$B$11 -> 2449.7773 | F47: =$B$7*$C47*$B$12 -> 2449.7773 | G47: =SUM(D47:F47) -> 7349.3319 | H47: =IF(A47=0,$B$17*$B$14*$B$13,H46*$B$13) -> 3.5204997e-05 | I47: =$I$29*B47 -> 10198.389 | J47: =MAX(IF(A47>=$B$22,J46-$B$24,$B$17),0) -> 0 | K47: =IF(A47>=$B$20,J47*$B$18,0) -> 0 | L47: =IF(A47=$B$28,$B$27,0) -> 0 | M47: =I47-G47-K47+L47 -> 2849.057 | N47: =M47-H47 -> 2849.0569 | O47: =IF(N47<0,N47,0) -> 0 | P47: =IF(N47>0,N47+O46,0) -> 2849.0569 | Q47: =$B$25*P47 -> 655.2831 | R47: =M47-Q47 -> 2193.7739 | S47: =IFERROR(__xludf.DUMMYFUNCTION("IF(ISBETWEEN(A47,$B$22,$B$22+$B$19-1),$B$24,0)"),0.0) -> 0 | T47: =R47-S47 -> 2193.7739 | U47: =T47+U46 -> 10423.797
A48: 17 | B48: =POWER(1-$B$8,A48)*$B$3 -> 59690.57 | C48: =POWER(1+$B$9,A48) -> 1.6528476 | D48: =$B$7*C48*$B$10 -> 2523.2706 | E48: =$B$7*$C48*$B$11 -> 2523.2706 | F48: =$B$7*$C48*$B$12 -> 2523.2706 | G48: =SUM(D48:F48) -> 7569.8119 | H48: =IF(A48=0,$B$17*$B$14*$B$13,H47*$B$13) -> 1.0561499e-05 | I48: =$I$29*B48 -> 10147.397 | J48: =MAX(IF(A48>=$B$22,J47-$B$24,$B$17),0) -> 0 | K48: =IF(A48>=$B$20,J48*$B$18,0) -> 0 | L48: =IF(A48=$B$28,$B$27,0) -> 0 | M48: =I48-G48-K48+L48 -> 2577.5851 | N48: =M48-H48 -> 2577.5851 | O48: =IF(N48<0,N48,0) -> 0 | P48: =IF(N48>0,N48+O47,0) -> 2577.5851 | Q48: =$B$25*P48 -> 592.84456 | R48: =M48-Q48 -> 1984.7405 | S48: =IFERROR(__xludf.DUMMYFUNCTION("IF(ISBETWEEN(A48,$B$22,$B$22+$B$19-1),$B$24,0)"),0.0) -> 0 | T48: =R48-S48 -> 1984.7405 | U48: =T48+U47 -> 12408.537
A49: 18 | B49: =POWER(1-$B$8,A49)*$B$3 -> 59392.118 | C49: =POWER(1+$B$9,A49) -> 1.7024331 | D49: =$B$7*C49*$B$10 -> 2598.9688 | E49: =$B$7*$C49*$B$11 -> 2598.9688 | F49: =$B$7*$C49*$B$12 -> 2598.9688 | G49: =SUM(D49:F49) -> 7796.9063 | H49: =IF(A49=0,$B$17*$B$14*$B$13,H48*$B$13) -> 3.1684498e-06 | I49: =$I$29*B49 -> 10096.66 | J49: =MAX(IF(A49>=$B$22,J48-$B$24,$B$17),0) -> 0 | K49: =IF(A49>=$B$20,J49*$B$18,0) -> 0 | L49: =IF(A49=$B$28,$B$27,0) -> 0 | M49: =I49-G49-K49+L49 -> 2299.7537 | N49: =M49-H49 -> 2299.7537 | O49: =IF(N49<0,N49,0) -> 0 | P49: =IF(N49>0,N49+O48,0) -> 2299.7537 | Q49: =$B$25*P49 -> 528.94336 | R49: =M49-Q49 -> 1770.8104 | S49: =IFERROR(__xludf.DUMMYFUNCTION("IF(ISBETWEEN(A49,$B$22,$B$22+$B$19-1),$B$24,0)"),0.0) -> 0 | T49: =R49-S49 -> 1770.8104 | U49: =T49+U48 -> 14179.348
A50: 19 | B50: =POWER(1-$B$8,A50)*$B$3 -> 59095.157 | C50: =POWER(1+$B$9,A50) -> 1.7535061 | D50: =$B$7*C50*$B$10 -> 2676.9378 | E50: =$B$7*$C50*$B$11 -> 2676.9378 | F50: =$B$7*$C50*$B$12 -> 2676.9378 | G50: =SUM(D50:F50) -> 8030.8134 | H50: =IF(A50=0,$B$17*$B$14*$B$13,H49*$B$13) -> 9.5053493e-07 | I50: =$I$29*B50 -> 10046.177 | J50: =MAX(IF(A50>=$B$22,J49-$B$24,$B$17),0) -> 0 | K50: =IF(A50>=$B$20,J50*$B$18,0) -> 0 | L50: =IF(A50=$B$28,$B$27,0) -> 0 | M50: =I50-G50-K50+L50 -> 2015.3632 | N50: =M50-H50 -> 2015.3632 | O50: =IF(N50<0,N50,0) -> 0 | P50: =IF(N50>0,N50+O49,0) -> 2015.3632 | Q50: =$B$25*P50 -> 463.53355 | R50: =M50-Q50 -> 1551.8297 | S50: =IFERROR(__xludf.DUMMYFUNCTION("IF(ISBETWEEN(A50,$B$22,$B$22+$B$19-1),$B$24,0)"),0.0) -> 0 | T50: =R50-S50 -> 1551.8297 | U50: =T50+U49 -> 15731.177
A51: 20 | B51: =POWER(1-$B$8,A51)*$B$3 -> 58799.681 | C51: =POWER(1+$B$9,A51) -> 1.8061112 | D51: =$B$7*C51*$B$10 -> 2757.2459 | E51: =$B$7*$C51*$B$11 -> 2757.2459 | F51: =$B$7*$C51*$B$12 -> 2757.2459 | G51: =SUM(D51:F51) -> 8271.7378 | H51: =IF(A51=0,$B$17*$B$14*$B$13,H50*$B$13) -> 2.8516048e-07 | I51: =$I$29*B51 -> 9995.9458 | J51: =MAX(IF(A51>=$B$22,J50-$B$24,$B$17),0) -> 0 | K51: =IF(A51>=$B$20,J51*$B$18,0) -> 0 | L51: =IF(A51=$B$28,$B$27,0) -> 0 | M51: =I51-G51-K51+L51 -> 1724.208 | N51: =M51-H51 -> 1724.208 | O51: =IF(N51<0,N51,0) -> 0 | P51: =IF(N51>0,N51+O50,0) -> 1724.208 | Q51: =$B$25*P51 -> 396.56783 | R51: =M51-Q51 -> 1327.6401 | S51: =IFERROR(__xludf.DUMMYFUNCTION("IF(ISBETWEEN(A51,$B$22,$B$22+$B$19-1),$B$24,0)"),0.0) -> 0 | T51: =R51-S51 -> 1327.6401 | U51: =T51+U50 -> 17058.818
A52: 21 | B52: =POWER(1-$B$8,A52)*$B$3 -> 58505.683 | C52: =POWER(1+$B$9,A52) -> 1.8602946 | D52: =$B$7*C52*$B$10 -> 2839.9633 | E52: =$B$7*$C52*$B$11 -> 2839.9633 | F52: =$B$7*$C52*$B$12 -> 2839.9633 | G52: =SUM(D52:F52) -> 8519.89 | H52: =IF(A52=0,$B$17*$B$14*$B$13,H51*$B$13) -> 8.5548144e-08 | I52: =$I$29*B52 -> 9945.9661 | J52: =MAX(IF(A52>=$B$22,J51-$B$24,$B$17),0) -> 0 | K52: =IF(A52>=$B$20,J52*$B$18,0) -> 0 | L52: =IF(A52=$B$28,$B$27,0) -> 0 | M52: =I52-G52-K52+L52 -> 1426.0761 | N52: =M52-H52 -> 1426.0761 | O52: =IF(N52<0,N52,0) -> 0 | P52: =IF(N52>0,N52+O51,0) -> 1426.0761 | Q52: =$B$25*P52 -> 327.9975 | R52: =M52-Q52 -> 1098.0786 | S52: =IFERROR(__xludf.DUMMYFUNCTION("IF(ISBETWEEN(A52,$B$22,$B$22+$B$19-1),$B$24,0)"),0.0) -> 0 | T52: =R52-S52 -> 1098.0786 | U52: =T52+U51 -> 18156.896
A53: 22 | B53: =POWER(1-$B$8,A53)*$B$3 -> 58213.154 | C53: =POWER(1+$B$9,A53) -> 1.9161034 | D53: =$B$7*C53*$B$10 -> 2925.1622 | E53: =$B$7*$C53*$B$11 -> 2925.1622 | F53: =$B$7*$C53*$B$12 -> 2925.1622 | G53: =SUM(D53:F53) -> 8775.4867 | H53: =IF(A53=0,$B$17*$B$14*$B$13,H52*$B$13) -> 2.5664443e-08 | I53: =$I$29*B53 -> 9896.2362 | J53: =MAX(IF(A53>=$B$22,J52-$B$24,$B$17),0) -> 0 | K53: =IF(A53>=$B$20,J53*$B$18,0) -> 0 | L53: =IF(A53=$B$28,$B$27,0) -> 0 | M53: =I53-G53-K53+L53 -> 1120.7496 | N53: =M53-H53 -> 1120.7496 | O53: =IF(N53<0,N53,0) -> 0 | P53: =IF(N53>0,N53+O52,0) -> 1120.7496 | Q53: =$B$25*P53 -> 257.7724 | R53: =M53-Q53 -> 862.97716 | S53: =IFERROR(__xludf.DUMMYFUNCTION("IF(ISBETWEEN(A53,$B$22,$B$22+$B$19-1),$B$24,0)"),0.0) -> 0 | T53: =R53-S53 -> 862.97716 | U53: =T53+U52 -> 19019.873
A54: 23 | B54: =POWER(1-$B$8,A54)*$B$3 -> 57922.089 | C54: =POWER(1+$B$9,A54) -> 1.9735865 | D54: =$B$7*C54*$B$10 -> 3012.9171 | E54: =$B$7*$C54*$B$11 -> 3012.9171 | F54: =$B$7*$C54*$B$12 -> 3012.9171 | G54: =SUM(D54:F54) -> 9038.7513 | H54: =IF(A54=0,$B$17*$B$14*$B$13,H53*$B$13) -> 7.6993329e-09 | I54: =$I$29*B54 -> 9846.7551 | J54: =MAX(IF(A54>=$B$22,J53-$B$24,$B$17),0) -> 0 | K54: =IF(A54>=$B$20,J54*$B$18,0) -> 0 | L54: =IF(A54=$B$28,$B$27,0) -> 0 | M54: =I54-G54-K54+L54 -> 808.00378 | N54: =M54-H54 -> 808.00378 | O54: =IF(N54<0,N54,0) -> 0 | P54: =IF(N54>0,N54+O53,0) -> 808.00378 | Q54: =$B$25*P54 -> 185.84087 | R54: =M54-Q54 -> 622.16291 | S54: =IFERROR(__xludf.DUMMYFUNCTION("IF(ISBETWEEN(A54,$B$22,$B$22+$B$19-1),$B$24,0)"),0.0) -> 0 | T54: =R54-S54 -> 622.16291 | U54: =T54+U53 -> 19642.036
A55: 24 | B55: =POWER(1-$B$8,A55)*$B$3 -> 57632.478 | C55: =POWER(1+$B$9,A55) -> 2.0327941 | D55: =$B$7*C55*$B$10 -> 3103.3046 | E55: =$B$7*$C55*$B$11 -> 3103.3046 | F55: =$B$7*$C55*$B$12 -> 3103.3046 | G55: =SUM(D55:F55) -> 9309.9138 | H55: =IF(A55=0,$B$17*$B$14*$B$13,H54*$B$13) -> 2.3097999e-09 | I55: =$I$29*B55 -> 9797.5213 | J55: =MAX(IF(A55>=$B$22,J54-$B$24,$B$17),0) -> 0 | K55: =IF(A55>=$B$20,J55*$B$18,0) -> 0 | L55: =IF(A55=$B$28,$B$27,0) -> 0 | M55: =I55-G55-K55+L55 -> 487.60747 | N55: =M55-H55 -> 487.60747 | O55: =IF(N55<0,N55,0) -> 0 | P55: =IF(N55>0,N55+O54,0) -> 487.60747 | Q55: =$B$25*P55 -> 112.14972 | R55: =M55-Q55 -> 375.45775 | S55: =IFERROR(__xludf.DUMMYFUNCTION("IF(ISBETWEEN(A55,$B$22,$B$22+$B$19-1),$B$24,0)"),0.0) -> 0 | T55: =R55-S55 -> 375.45775 | U55: =T55+U54 -> 20017.494
B56: =SUM(B31:B55) -> 1531136.8 | D56: =SUM(D31:D55) -> 55659.451 | E56: =SUM(E31:E55) -> 55659.451 | F56: =SUM(F31:F55) -> 55659.451 | G56: =SUM(G31:G55) -> 166978.35 | H56: =SUM(H31:H55) -> 11683.318 | I56: =SUM(I31:I55) -> 260293.26 | K56: =SUM(K31:K55) -> 16356.645 | L56: =SUM(L31:L55) -> 16356.645 | M56: =SUM(M31:M55) -> 93314.912 | Q56: =SUM(Q31:Q55) -> 18775.267 | R56: =SUM(R31:R55) -> 74539.645 | S56: =SUM(S31:S55) -> 54522.151 | T56: =SUM(T31:T55) -> 20017.494

Sheet 50% Grant, BVGEC recoup via OPE
A2: Capacity Factor | B2: 0.17 | D2: Norfolk | E2: 0.33
A3: System Output | B3: 65000 | D3: BVGEC | E3: 0.33
A4: Hours per Year | B4: 8766 | D4: Community | E4: =1-E2-E3 -> 0.34
A5: System Size | B5: =$B$3/$B$4/$B$2 -> 43.617721
A6: Install Cost | B6: 2.5
A7: Capex | B7: =B5*B6*1000 -> 109044.3
A8: Degradation | B8: 0.005
A9: Inflation | B9: 0.03
A10: Admin Rate | B10: =$E$11 -> 0.0075 | D10: Combined OPEX Rate | E10: 0.0225
A11: Insurance Rate | B11: =$E$11 -> 0.0075 | D11: Individual | E11: =E10/3 -> 0.0075
A12: Maintenance Rate | B12: =$E$11 -> 0.0075
A13: CCA Rate | B13: 0.3
A14: Half Year Rule | B14: 0.5
A15: Grant Rate | B15: 0.5 | L15: Current Bill | M15: ='Bill Comparison'!F28 -> 322479.95
A16: Grant Amount | B16: =B7*B15 -> 54522.151 | L16: New Bill | M16: ='Bill Comparison'!J28 -> 49771.697 | N16: Benefit Dist | O16: Annuity
A17: Net Capex | B17: =B7-B16 -> 54522.151 | L17: Available Savings | M17: ='Bill Comparison'!L28 -> 272708.26 | R17: Bill Saving | S17: =1-(I53+M16)/M15 -> 0.2640288
A18: Debt Rate | B18: 0.04 | L18: Norfolk Savings | M18: =M17-I53 -> 85143.994 | N18: =M18/M19 -> 0.41871599 | O18: =M18/25 -> 3405.7597
A19: Debt Term | B19: 10 | L19: Total Benefit | M19: =M18+T53+G53 -> 203345.45
A20: Repayment Start | B20: 3 | L20: BVGEC | M20: =G53 -> 89452.688 | N20: =M20/M19 -> 0.43990503 | O20: =M20/25 -> 3578.1075
A21: Repayment Principal | B21: =B17/B19 -> 5452.2151 | L21: Community | M21: =M19-M18-M20 -> 28748.771 | N21: =M21/M19 -> 0.14137897 | O21: =M21/25 -> 1149.9509
A22: Tax Rate | B22: 0.23 | N22: =N18+N20+N21 -> 1
A23: ITC Rate | B23: 0.3
A24: ITC Amount | B24: =B17*B23 -> 16356.645 | L24: Utilization | M24: =M19/M17 -> 0.74565199
A25: ITC year | B25: 1
H26: Effective PPA | I26: 0.1225
A27: Year | B27: Effective Output | C27: Escalation Factor | D27: Admin Cost | E27: Insurance Cost | F27: Maintenance Cost | G27: OPEX | H27: Capital Cost Allowance | I27: Revenue | J27: Debt Principal | K27: Debt Interest | L27: ITC Credit | M27: Pre Tax Operating Cashflow | N27: Taxable Income Before Carry Forward Loss | O27: Carry Forward Losses | P27: Taxable Income After Carry Forward Loss | Q27: Tax | R27: After Tax Income | S27: Principal Repayent | T27: Cashflow To Equity | U27: Cumulative Equity
A28: 0 | B28: =POWER(1-$B$8,A28)*$B$3 -> 65000 | C28: =POWER(1+$B$9,A28) -> 1 | D28: =$B$7*C28*$B$10 -> 817.83227 | E28: =$B$7*$C28*$B$11 -> 817.83227 | F28: =$B$7*$C28*$B$12 -> 817.83227 | G28: =SUM(D28:F28) -> 2453.4968 | H28: =IF(A28=0,$B$17*$B$14*$B$13,H27*$B$13) -> 8178.3227 | I28: =B28*$I$26 -> 7962.5 | J28: =MAX(IF(A28>=$B$20,J27-$B$21,$B$17),0) -> 54522.151 | K28: =IF(A28>=$B$20,J28*$B$18,0) -> 0 | L28: =IF(A28=$B$25,$B$24,0) -> 0 | M28: =I28-G28-K28+L28 -> 5509.0032 | N28: =M28-H28 -> -2669.3195 | O28: =IF(N28<0,N28,0) -> -2669.3195 | P28: =IF(N28>0,N28+O27,0) -> 0 | Q28: =$B$22*P28 -> 0 | R28: =M28-Q28 -> 5509.0032 | S28: =IFERROR(__xludf.DUMMYFUNCTION("IF(ISBETWEEN(A28,$B$20,$B$20+$B$19-1),$B$21,0)"),0.0) -> 0 | T28: =R28-S28 -> 5509.0032 | U28: =T28 -> 5509.0032
A29: 1 | B29: =POWER(1-$B$8,A29)*$B$3 -> 64675 | C29: =POWER(1+$B$9,A29) -> 1.03 | D29: =$B$7*C29*$B$10 -> 842.36723 | E29: =$B$7*$C29*$B$11 -> 842.36723 | F29: =$B$7*$C29*$B$12 -> 842.36723 | G29: =SUM(D29:F29) -> 2527.1017 | H29: =IF(A29=0,$B$17*$B$14*$B$13,H28*$B$13) -> 2453.4968 | I29: =B29*$I$26 -> 7922.6875 | J29: =MAX(IF(A29>=$B$20,J28-$B$21,$B$17),0) -> 54522.151 | K29: =IF(A29>=$B$20,J29*$B$18,0) -> 0 | L29: =IF(A29=$B$25,$B$24,0) -> 16356.645 | M29: =I29-G29-K29+L29 -> 21752.231 | N29: =M29-H29 -> 19298.734 | O29: =IF(N29<0,N29,0) -> 0 | P29: =IF(N29>0,N29+O28,0) -> 16629.415 | Q29: =$B$22*P29 -> 3824.7654 | R29: =M29-Q29 -> 17927.466 | S29: =IFERROR(__xludf.DUMMYFUNCTION("IF(ISBETWEEN(A29,$B$20,$B$20+$B$19-1),$B$21,0)"),0.0) -> 0 | T29: =R29-S29 -> 17927.466 | U29: =T29+U28 -> 23436.469
A30: 2 | B30: =POWER(1-$B$8,A30)*$B$3 -> 64351.625 | C30: =POWER(1+$B$9,A30) -> 1.0609 | D30: =$B$7*C30*$B$10 -> 867.63825 | E30: =$B$7*$C30*$B$11 -> 867.63825 | F30: =$B$7*$C30*$B$12 -> 867.63825 | G30: =SUM(D30:F30) -> 2602.9148 | H30: =IF(A30=0,$B$17*$B$14*$B$13,H29*$B$13) -> 736.04904 | I30: =B30*$I$26 -> 7883.0741 | J30: =MAX(IF(A30>=$B$20,J29-$B$21,$B$17),0) -> 54522.151 | K30: =IF(A30>=$B$20,J30*$B$18,0) -> 0 | L30: =IF(A30=$B$25,$B$24,0) -> 0 | M30: =I30-G30-K30+L30 -> 5280.1593 | N30: =M30-H30 -> 4544.1103 | O30: =IF(N30<0,N30,0) -> 0 | P30: =IF(N30>0,N30+O29,0) -> 4544.1103 | Q30: =$B$22*P30 -> 1045.1454 | R30: =M30-Q30 -> 4235.0139 | S30: =IFERROR(__xludf.DUMMYFUNCTION("IF(ISBETWEEN(A30,$B$20,$B$20+$B$19-1),$B$21,0)"),0.0) -> 0 | T30: =R30-S30 -> 4235.0139 | U30: =T30+U29 -> 27671.483
A31: 3 | B31: =POWER(1-$B$8,A31)*$B$3 -> 64029.867 | C31: =POWER(1+$B$9,A31) -> 1.092727 | D31: =$B$7*C31*$B$10 -> 893.6674 | E31: =$B$7*$C31*$B$11 -> 893.6674 | F31: =$B$7*$C31*$B$12 -> 893.6674 | G31: =SUM(D31:F31) -> 2681.0022 | H31: =IF(A31=0,$B$17*$B$14*$B$13,H30*$B$13) -> 220.81471 | I31: =B31*$I$26 -> 7843.6587 | J31: =MAX(IF(A31>=$B$20,J30-$B$21,$B$17),0) -> 49069.936 | K31: =IF(A31>=$B$20,J31*$B$18,0) -> 1962.7974 | L31: =IF(A31=$B$25,$B$24,0) -> 0 | M31: =I31-G31-K31+L31 -> 3199.8591 | N31: =M31-H31 -> 2979.0443 | O31: =IF(N31<0,N31,0) -> 0 | P31: =IF(N31>0,N31+O30,0) -> 2979.0443 | Q31: =$B$22*P31 -> 685.1802 | R31: =M31-Q31 -> 2514.6789 | S31: =IFERROR(__xludf.DUMMYFUNCTION("IF(ISBETWEEN(A31,$B$20,$B$20+$B$19-1),$B$21,0)"),5452.215109178511) -> 5452.2151 | T31: =R31-S31 -> -2937.5363 | U31: =T31+U30 -> 24733.947
A32: 4 | B32: =POWER(1-$B$8,A32)*$B$3 -> 63709.718 | C32: =POWER(1+$B$9,A32) -> 1.1255088 | D32: =$B$7*C32*$B$10 -> 920.47742 | E32: =$B$7*$C32*$B$11 -> 920.47742 | F32: =$B$7*$C32*$B$12 -> 920.47742 | G32: =SUM(D32:F32) -> 2761.4323 | H32: =IF(A32=0,$B$17*$B$14*$B$13,H31*$B$13) -> 66.244414 | I32: =B32*$I$26 -> 7804.4404 | J32: =MAX(IF(A32>=$B$20,J31-$B$21,$B$17),0) -> 43617.721 | K32: =IF(A32>=$B$20,J32*$B$18,0) -> 1744.7088 | L32: =IF(A32=$B$25,$B$24,0) -> 0 | M32: =I32-G32-K32+L32 -> 3298.2993 | N32: =M32-H32 -> 3232.0549 | O32: =IF(N32<0,N32,0) -> 0 | P32: =IF(N32>0,N32+O31,0) -> 3232.0549 | Q32: =$B$22*P32 -> 743.37262 | R32: =M32-Q32 -> 2554.9267 | S32: =IFERROR(__xludf.DUMMYFUNCTION("IF(ISBETWEEN(A32,$B$20,$B$20+$B$19-1),$B$21,0)"),5452.215109178511) -> 5452.2151 | T32: =R32-S32 -> -2897.2884 | U32: =T32+U31 -> 21836.658
A33: 5 | B33: =POWER(1-$B$8,A33)*$B$3 -> 63391.169 | C33: =POWER(1+$B$9,A33) -> 1.1592741 | D33: =$B$7*C33*$B$10 -> 948.09174 | E33: =$B$7*$C33*$B$11 -> 948.09174 | F33: =$B$7*$C33*$B$12 -> 948.09174 | G33: =SUM(D33:F33) -> 2844.2752 | H33: =IF(A33=0,$B$17*$B$14*$B$13,H32*$B$13) -> 19.873324 | I33: =B33*$I$26 -> 7765.4182 | J33: =MAX(IF(A33>=$B$20,J32-$B$21,$B$17),0) -> 38165.506 | K33: =IF(A33>=$B$20,J33*$B$18,0) -> 1526.6202 | L33: =IF(A33=$B$25,$B$24,0) -> 0 | M33: =I33-G33-K33+L33 -> 3394.5227 | N33: =M33-H33 -> 3374.6494 | O33: =IF(N33<0,N33,0) -> 0 | P33: =IF(N33>0,N33+O32,0) -> 3374.6494 | Q33: =$B$22*P33 -> 776.16936 | R33: =M33-Q33 -> 2618.3534 | S33: =IFERROR(__xludf.DUMMYFUNCTION("IF(ISBETWEEN(A33,$B$20,$B$20+$B$19-1),$B$21,0)"),5452.215109178511) -> 5452.2151 | T33: =R33-S33 -> -2833.8617 | U33: =T33+U32 -> 19002.796
A34: 6 | B34: =POWER(1-$B$8,A34)*$B$3 -> 63074.213 | C34: =POWER(1+$B$9,A34) -> 1.1940523 | D34: =$B$7*C34*$B$10 -> 976.5345 | E34: =$B$7*$C34*$B$11 -> 976.5345 | F34: =$B$7*$C34*$B$12 -> 976.5345 | G34: =SUM(D34:F34) -> 2929.6035 | H34: =IF(A34=0,$B$17*$B$14*$B$13,H33*$B$13) -> 5.9619972 | I34: =B34*$I$26 -> 7726.5911 | J34: =MAX(IF(A34>=$B$20,J33-$B$21,$B$17),0) -> 32713.291 | K34: =IF(A34>=$B$20,J34*$B$18,0) -> 1308.5316 | L34: =IF(A34=$B$25,$B$24,0) -> 0 | M34: =I34-G34-K34+L34 -> 3488.456 | N34: =M34-H34 -> 3482.494 | O34: =IF(N34<0,N34,0) -> 0 | P34: =IF(N34>0,N34+O33,0) -> 3482.494 | Q34: =$B$22*P34 -> 800.97362 | R34: =M34-Q34 -> 2687.4824 | S34: =IFERROR(__xludf.DUMMYFUNCTION("IF(ISBETWEEN(A34,$B$20,$B$20+$B$19-1),$B$21,0)"),5452.215109178511) -> 5452.2151 | T34: =R34-S34 -> -2764.7327 | U34: =T34+U33 -> 16238.064
A35: 7 | B35: =POWER(1-$B$8,A35)*$B$3 -> 62758.842 | C35: =POWER(1+$B$9,A35) -> 1.2298739 | D35: =$B$7*C35*$B$10 -> 1005.8305 | E35: =$B$7*$C35*$B$11 -> 1005.8305 | F35: =$B$7*$C35*$B$12 -> 1005.8305 | G35: =SUM(D35:F35) -> 3017.4916 | H35: =IF(A35=0,$B$17*$B$14*$B$13,H34*$B$13) -> 1.7885992 | I35: =B35*$I$26 -> 7687.9582 | J35: =MAX(IF(A35>=$B$20,J34-$B$21,$B$17),0) -> 27261.076 | K35: =IF(A35>=$B$20,J35*$B$18,0) -> 1090.443 | L35: =IF(A35=$B$25,$B$24,0) -> 0 | M35: =I35-G35-K35+L35 -> 3580.0235 | N35: =M35-H35 -> 3578.2349 | O35: =IF(N35<0,N35,0) -> 0 | P35: =IF(N35>0,N35+O34,0) -> 3578.2349 | Q35: =$B$22*P35 -> 822.99404 | R35: =M35-Q35 -> 2757.0295 | S35: =IFERROR(__xludf.DUMMYFUNCTION("IF(ISBETWEEN(A35,$B$20,$B$20+$B$19-1),$B$21,0)"),5452.215109178511) -> 5452.2151 | T35: =R35-S35 -> -2695.1856 | U35: =T35+U34 -> 13542.878
A36: 8 | B36: =POWER(1-$B$8,A36)*$B$3 -> 62445.048 | C36: =POWER(1+$B$9,A36) -> 1.2667701 | D36: =$B$7*C36*$B$10 -> 1036.0054 | E36: =$B$7*$C36*$B$11 -> 1036.0054 | F36: =$B$7*$C36*$B$12 -> 1036.0054 | G36: =SUM(D36:F36) -> 3108.0163 | H36: =IF(A36=0,$B$17*$B$14*$B$13,H35*$B$13) -> 0.53657975 | I36: =B36*$I$26 -> 7649.5184 | J36: =MAX(IF(A36>=$B$20,J35-$B$21,$B$17),0) -> 21808.86 | K36: =IF(A36>=$B$20,J36*$B$18,0) -> 872.35442 | L36: =IF(A36=$B$25,$B$24,0) -> 0 | M36: =I36-G36-K36+L36 -> 3669.1476 | N36: =M36-H36 -> 3668.611 | O36: =IF(N36<0,N36,0) -> 0 | P36: =IF(N36>0,N36+O35,0) -> 3668.611 | Q36: =$B$22*P36 -> 843.78054 | R36: =M36-Q36 -> 2825.3671 | S36: =IFERROR(__xludf.DUMMYFUNCTION("IF(ISBETWEEN(A36,$B$20,$B$20+$B$19-1),$B$21,0)"),5452.215109178511) -> 5452.2151 | T36: =R36-S36 -> -2626.848 | U36: =T36+U35 -> 10916.03
A37: 9 | B37: =POWER(1-$B$8,A37)*$B$3 -> 62132.823 | C37: =POWER(1+$B$9,A37) -> 1.3047732 | D37: =$B$7*C37*$B$10 -> 1067.0856 | E37: =$B$7*$C37*$B$11 -> 1067.0856 | F37: =$B$7*$C37*$B$12 -> 1067.0856 | G37: =SUM(D37:F37) -> 3201.2568 | H37: =IF(A37=0,$B$17*$B$14*$B$13,H36*$B$13) -> 0.16097392 | I37: =B37*$I$26 -> 7611.2708 | J37: =MAX(IF(A37>=$B$20,J36-$B$21,$B$17),0) -> 16356.645 | K37: =IF(A37>=$B$20,J37*$B$18,0) -> 654.26581 | L37: =IF(A37=$B$25,$B$24,0) -> 0 | M37: =I37-G37-K37+L37 -> 3755.7481 | N37: =M37-H37 -> 3755.5872 | O37: =IF(N37<0,N37,0) -> 0 | P37: =IF(N37>0,N37+O36,0) -> 3755.5872 | Q37: =$B$22*P37 -> 863.78504 | R37: =M37-Q37 -> 2891.9631 | S37: =IFERROR(__xludf.DUMMYFUNCTION("IF(ISBETWEEN(A37,$B$20,$B$20+$B$19-1),$B$21,0)"),5452.215109178511) -> 5452.2151 | T37: =R37-S37 -> -2560.252 | U37: =T37+U36 -> 8355.778
A38: 10 | B38: =POWER(1-$B$8,A38)*$B$3 -> 61822.158 | C38: =POWER(1+$B$9,A38) -> 1.3439164 | D38: =$B$7*C38*$B$10 -> 1099.0982 | E38: =$B$7*$C38*$B$11 -> 1099.0982 | F38: =$B$7*$C38*$B$12 -> 1099.0982 | G38: =SUM(D38:F38) -> 3297.2945 | H38: =IF(A38=0,$B$17*$B$14*$B$13,H37*$B$13) -> 0.048292177 | I38: =B38*$I$26 -> 7573.2144 | J38: =MAX(IF(A38>=$B$20,J37-$B$21,$B$17),0) -> 10904.43 | K38: =IF(A38>=$B$20,J38*$B$18,0) -> 436.17721 | L38: =IF(A38=$B$25,$B$24,0) -> 0 | M38: =I38-G38-K38+L38 -> 3839.7427 | N38: =M38-H38 -> 3839.6944 | O38: =IF(N38<0,N38,0) -> 0 | P38: =IF(N38>0,N38+O37,0) -> 3839.6944 | Q38: =$B$22*P38 -> 883.12971 | R38: =M38-Q38 -> 2956.613 | S38: =IFERROR(__xludf.DUMMYFUNCTION("IF(ISBETWEEN(A38,$B$20,$B$20+$B$19-1),$B$21,0)"),5452.215109178511) -> 5452.2151 | T38: =R38-S38 -> -2495.6021 | U38: =T38+U37 -> 5860.1759
A39: 11 | B39: =POWER(1-$B$8,A39)*$B$3 -> 61513.048 | C39: =POWER(1+$B$9,A39) -> 1.3842339 | D39: =$B$7*C39*$B$10 -> 1132.0711 | E39: =$B$7*$C39*$B$11 -> 1132.0711 | F39: =$B$7*$C39*$B$12 -> 1132.0711 | G39: =SUM(D39:F39) -> 3396.2134 | H39: =IF(A39=0,$B$17*$B$14*$B$13,H38*$B$13) -> 0.014487653 | I39: =B39*$I$26 -> 7535.3483 | J39: =MAX(IF(A39>=$B$20,J38-$B$21,$B$17),0) -> 5452.2151 | K39: =IF(A39>=$B$20,J39*$B$18,0) -> 218.0886 | L39: =IF(A39=$B$25,$B$24,0) -> 0 | M39: =I39-G39-K39+L39 -> 3921.0464 | N39: =M39-H39 -> 3921.0319 | O39: =IF(N39<0,N39,0) -> 0 | P39: =IF(N39>0,N39+O38,0) -> 3921.0319 | Q39: =$B$22*P39 -> 901.83733 | R39: =M39-Q39 -> 3019.209 | S39: =IFERROR(__xludf.DUMMYFUNCTION("IF(ISBETWEEN(A39,$B$20,$B$20+$B$19-1),$B$21,0)"),5452.215109178511) -> 5452.2151 | T39: =R39-S39 -> -2433.0061 | U39: =T39+U38 -> 3427.1698
A40: 12 | B40: =POWER(1-$B$8,A40)*$B$3 -> 61205.482 | C40: =POWER(1+$B$9,A40) -> 1.4257609 | D40: =$B$7*C40*$B$10 -> 1166.0333 | E40: =$B$7*$C40*$B$11 -> 1166.0333 | F40: =$B$7*$C40*$B$12 -> 1166.0333 | G40: =SUM(D40:F40) -> 3498.0998 | H40: =IF(A40=0,$B$17*$B$14*$B$13,H39*$B$13) -> 0.004346296 | I40: =B40*$I$26 -> 7497.6716 | J40: =MAX(IF(A40>=$B$20,J39-$B$21,$B$17),0) -> 0 | K40: =IF(A40>=$B$20,J40*$B$18,0) -> 0 | L40: =IF(A40=$B$25,$B$24,0) -> 0 | M40: =I40-G40-K40+L40 -> 3999.5718 | N40: =M40-H40 -> 3999.5675 | O40: =IF(N40<0,N40,0) -> 0 | P40: =IF(N40>0,N40+O39,0) -> 3999.5675 | Q40: =$B$22*P40 -> 919.90052 | R40: =M40-Q40 -> 3079.6713 | S40: =IFERROR(__xludf.DUMMYFUNCTION("IF(ISBETWEEN(A40,$B$20,$B$20+$B$19-1),$B$21,0)"),5452.215109178511) -> 5452.2151 | T40: =R40-S40 -> -2372.5438 | U40: =T40+U39 -> 1054.626
A41: 13 | B41: =POWER(1-$B$8,A41)*$B$3 -> 60899.455 | C41: =POWER(1+$B$9,A41) -> 1.4685337 | D41: =$B$7*C41*$B$10 -> 1201.0143 | E41: =$B$7*$C41*$B$11 -> 1201.0143 | F41: =$B$7*$C41*$B$12 -> 1201.0143 | G41: =SUM(D41:F41) -> 3603.0428 | H41: =IF(A41=0,$B$17*$B$14*$B$13,H40*$B$13) -> 0.0013038888 | I41: =B41*$I$26 -> 7460.1832 | J41: =MAX(IF(A41>=$B$20,J40-$B$21,$B$17),0) -> 0 | K41: =IF(A41>=$B$20,J41*$B$18,0) -> 0 | L41: =IF(A41=$B$25,$B$24,0) -> 0 | M41: =I41-G41-K41+L41 -> 3857.1405 | N41: =M41-H41 -> 3857.1392 | O41: =IF(N41<0,N41,0) -> 0 | P41: =IF(N41>0,N41+O40,0) -> 3857.1392 | Q41: =$B$22*P41 -> 887.14201 | R41: =M41-Q41 -> 2969.9985 | S41: =IFERROR(__xludf.DUMMYFUNCTION("IF(ISBETWEEN(A41,$B$20,$B$20+$B$19-1),$B$21,0)"),0.0) -> 0 | T41: =R41-S41 -> 2969.9985 | U41: =T41+U40 -> 4024.6245
A42: 14 | B42: =POWER(1-$B$8,A42)*$B$3 -> 60594.958 | C42: =POWER(1+$B$9,A42) -> 1.5125897 | D42: =$B$7*C42*$B$10 -> 1237.0447 | E42: =$B$7*$C42*$B$11 -> 1237.0447 | F42: =$B$7*$C42*$B$12 -> 1237.0447 | G42: =SUM(D42:F42) -> 3711.134 | H42: =IF(A42=0,$B$17*$B$14*$B$13,H41*$B$13) -> 0.00039116664 | I42: =B42*$I$26 -> 7422.8823 | J42: =MAX(IF(A42>=$B$20,J41-$B$21,$B$17),0) -> 0 | K42: =IF(A42>=$B$20,J42*$B$18,0) -> 0 | L42: =IF(A42=$B$25,$B$24,0) -> 0 | M42: =I42-G42-K42+L42 -> 3711.7483 | N42: =M42-H42 -> 3711.7479 | O42: =IF(N42<0,N42,0) -> 0 | P42: =IF(N42>0,N42+O41,0) -> 3711.7479 | Q42: =$B$22*P42 -> 853.70201 | R42: =M42-Q42 -> 2858.0463 | S42: =IFERROR(__xludf.DUMMYFUNCTION("IF(ISBETWEEN(A42,$B$20,$B$20+$B$19-1),$B$21,0)"),0.0) -> 0 | T42: =R42-S42 -> 2858.0463 | U42: =T42+U41 -> 6882.6707
A43: 15 | B43: =POWER(1-$B$8,A43)*$B$3 -> 60291.983 | C43: =POWER(1+$B$9,A43) -> 1.5579674 | D43: =$B$7*C43*$B$10 -> 1274.156 | E43: =$B$7*$C43*$B$11 -> 1274.156 | F43: =$B$7*$C43*$B$12 -> 1274.156 | G43: =SUM(D43:F43) -> 3822.4681 | H43: =IF(A43=0,$B$17*$B$14*$B$13,H42*$B$13) -> 0.00011734999 | I43: =B43*$I$26 -> 7385.7679 | J43: =MAX(IF(A43>=$B$20,J42-$B$21,$B$17),0) -> 0 | K43: =IF(A43>=$B$20,J43*$B$18,0) -> 0 | L43: =IF(A43=$B$25,$B$24,0) -> 0 | M43: =I43-G43-K43+L43 -> 3563.2998 | N43: =M43-H43 -> 3563.2997 | O43: =IF(N43<0,N43,0) -> 0 | P43: =IF(N43>0,N43+O42,0) -> 3563.2997 | Q43: =$B$22*P43 -> 819.55894 | R43: =M43-Q43 -> 2743.7409 | S43: =IFERROR(__xludf.DUMMYFUNCTION("IF(ISBETWEEN(A43,$B$20,$B$20+$B$19-1),$B$21,0)"),0.0) -> 0 | T43: =R43-S43 -> 2743.7409 | U43: =T43+U42 -> 9626.4116
A44: 16 | B44: =POWER(1-$B$8,A44)*$B$3 -> 59990.523 | C44: =POWER(1+$B$9,A44) -> 1.6047064 | D44: =$B$7*C44*$B$10 -> 1312.3807 | E44: =$B$7*$C44*$B$11 -> 1312.3807 | F44: =$B$7*$C44*$B$12 -> 1312.3807 | G44: =SUM(D44:F44) -> 3937.1421 | H44: =IF(A44=0,$B$17*$B$14*$B$13,H43*$B$13) -> 3.5204997e-05 | I44: =B44*$I$26 -> 7348.8391 | J44: =MAX(IF(A44>=$B$20,J43-$B$21,$B$17),0) -> 0 | K44: =IF(A44>=$B$20,J44*$B$18,0) -> 0 | L44: =IF(A44=$B$25,$B$24,0) -> 0 | M44: =I44-G44-K44+L44 -> 3411.697 | N44: =M44-H44 -> 3411.6969 | O44: =IF(N44<0,N44,0) -> 0 | P44: =IF(N44>0,N44+O43,0) -> 3411.6969 | Q44: =$B$22*P44 -> 784.69029 | R44: =M44-Q44 -> 2627.0067 | S44: =IFERROR(__xludf.DUMMYFUNCTION("IF(ISBETWEEN(A44,$B$20,$B$20+$B$19-1),$B$21,0)"),0.0) -> 0 | T44: =R44-S44 -> 2627.0067 | U44: =T44+U43 -> 12253.418
A45: 17 | B45: =POWER(1-$B$8,A45)*$B$3 -> 59690.57 | C45: =POWER(1+$B$9,A45) -> 1.6528476 | D45: =$B$7*C45*$B$10 -> 1351.7521 | E45: =$B$7*$C45*$B$11 -> 1351.7521 | F45: =$B$7*$C45*$B$12 -> 1351.7521 | G45: =SUM(D45:F45) -> 4055.2564 | H45: =IF(A45=0,$B$17*$B$14*$B$13,H44*$B$13) -> 1.0561499e-05 | I45: =B45*$I$26 -> 7312.0949 | J45: =MAX(IF(A45>=$B$20,J44-$B$21,$B$17),0) -> 0 | K45: =IF(A45>=$B$20,J45*$B$18,0) -> 0 | L45: =IF(A45=$B$25,$B$24,0) -> 0 | M45: =I45-G45-K45+L45 -> 3256.8385 | N45: =M45-H45 -> 3256.8385 | O45: =IF(N45<0,N45,0) -> 0 | P45: =IF(N45>0,N45+O44,0) -> 3256.8385 | Q45: =$B$22*P45 -> 749.07285 | R45: =M45-Q45 -> 2507.7657 | S45: =IFERROR(__xludf.DUMMYFUNCTION("IF(ISBETWEEN(A45,$B$20,$B$20+$B$19-1),$B$21,0)"),0.0) -> 0 | T45: =R45-S45 -> 2507.7657 | U45: =T45+U44 -> 14761.184
A46: 18 | B46: =POWER(1-$B$8,A46)*$B$3 -> 59392.118 | C46: =POWER(1+$B$9,A46) -> 1.7024331 | D46: =$B$7*C46*$B$10 -> 1392.3047 | E46: =$B$7*$C46*$B$11 -> 1392.3047 | F46: =$B$7*$C46*$B$12 -> 1392.3047 | G46: =SUM(D46:F46) -> 4176.9141 | H46: =IF(A46=0,$B$17*$B$14*$B$13,H45*$B$13) -> 3.1684498e-06 | I46: =B46*$I$26 -> 7275.5344 | J46: =MAX(IF(A46>=$B$20,J45-$B$21,$B$17),0) -> 0 | K46: =IF(A46>=$B$20,J46*$B$18,0) -> 0 | L46: =IF(A46=$B$25,$B$24,0) -> 0 | M46: =I46-G46-K46+L46 -> 3098.6203 | N46: =M46-H46 -> 3098.6203 | O46: =IF(N46<0,N46,0) -> 0 | P46: =IF(N46>0,N46+O45,0) -> 3098.6203 | Q46: =$B$22*P46 -> 712.68268 | R46: =M46-Q46 -> 2385.9377 | S46: =IFERROR(__xludf.DUMMYFUNCTION("IF(ISBETWEEN(A46,$B$20,$B$20+$B$19-1),$B$21,0)"),0.0) -> 0 | T46: =R46-S46 -> 2385.9377 | U46: =T46+U45 -> 17147.122
A47: 19 | B47: =POWER(1-$B$8,A47)*$B$3 -> 59095.157 | C47: =POWER(1+$B$9,A47) -> 1.7535061 | D47: =$B$7*C47*$B$10 -> 1434.0738 | E47: =$B$7*$C47*$B$11 -> 1434.0738 | F47: =$B$7*$C47*$B$12 -> 1434.0738 | G47: =SUM(D47:F47) -> 4302.2215 | H47: =IF(A47=0,$B$17*$B$14*$B$13,H46*$B$13) -> 9.5053493e-07 | I47: =B47*$I$26 -> 7239.1567 | J47: =MAX(IF(A47>=$B$20,J46-$B$21,$B$17),0) -> 0 | K47: =IF(A47>=$B$20,J47*$B$18,0) -> 0 | L47: =IF(A47=$B$25,$B$24,0) -> 0 | M47: =I47-G47-K47+L47 -> 2936.9352 | N47: =M47-H47 -> 2936.9352 | O47: =IF(N47<0,N47,0) -> 0 | P47: =IF(N47>0,N47+O46,0) -> 2936.9352 | Q47: =$B$22*P47 -> 675.49511 | R47: =M47-Q47 -> 2261.4401 | S47: =IFERROR(__xludf.DUMMYFUNCTION("IF(ISBETWEEN(A47,$B$20,$B$20+$B$19-1),$B$21,0)"),0.0) -> 0 | T47: =R47-S47 -> 2261.4401 | U47: =T47+U46 -> 19408.562
A48: 20 | B48: =POWER(1-$B$8,A48)*$B$3 -> 58799.681 | C48: =POWER(1+$B$9,A48) -> 1.8061112 | D48: =$B$7*C48*$B$10 -> 1477.096 | E48: =$B$7*$C48*$B$11 -> 1477.096 | F48: =$B$7*$C48*$B$12 -> 1477.096 | G48: =SUM(D48:F48) -> 4431.2881 | H48: =IF(A48=0,$B$17*$B$14*$B$13,H47*$B$13) -> 2.8516048e-07 | I48: =B48*$I$26 -> 7202.9609 | J48: =MAX(IF(A48>=$B$20,J47-$B$21,$B$17),0) -> 0 | K48: =IF(A48>=$B$20,J48*$B$18,0) -> 0 | L48: =IF(A48=$B$25,$B$24,0) -> 0 | M48: =I48-G48-K48+L48 -> 2771.6728 | N48: =M48-H48 -> 2771.6728 | O48: =IF(N48<0,N48,0) -> 0 | P48: =IF(N48>0,N48+O47,0) -> 2771.6728 | Q48: =$B$22*P48 -> 637.48475 | R48: =M48-Q48 -> 2134.1881 | S48: =IFERROR(__xludf.DUMMYFUNCTION("IF(ISBETWEEN(A48,$B$20,$B$20+$B$19-1),$B$21,0)"),0.0) -> 0 | T48: =R48-S48 -> 2134.1881 | U48: =T48+U47 -> 21542.75
A49: 21 | B49: =POWER(1-$B$8,A49)*$B$3 -> 58505.683 | C49: =POWER(1+$B$9,A49) -> 1.8602946 | D49: =$B$7*C49*$B$10 -> 1521.4089 | E49: =$B$7*$C49*$B$11 -> 1521.4089 | F49: =$B$7*$C49*$B$12 -> 1521.4089 | G49: =SUM(D49:F49) -> 4564.2268 | H49: =IF(A49=0,$B$17*$B$14*$B$13,H48*$B$13) -> 8.5548144e-08 | I49: =B49*$I$26 -> 7166.9461 | J49: =MAX(IF(A49>=$B$20,J48-$B$21,$B$17),0) -> 0 | K49: =IF(A49>=$B$20,J49*$B$18,0) -> 0 | L49: =IF(A49=$B$25,$B$24,0) -> 0 | M49: =I49-G49-K49+L49 -> 2602.7194 | N49: =M49-H49 -> 2602.7194 | O49: =IF(N49<0,N49,0) -> 0 | P49: =IF(N49>0,N49+O48,0) -> 2602.7194 | Q49: =$B$22*P49 -> 598.62545 | R49: =M49-Q49 -> 2004.0939 | S49: =IFERROR(__xludf.DUMMYFUNCTION("IF(ISBETWEEN(A49,$B$20,$B$20+$B$19-1),$B$21,0)"),0.0) -> 0 | T49: =R49-S49 -> 2004.0939 | U49: =T49+U48 -> 23546.844
A50: 22 | B50: =POWER(1-$B$8,A50)*$B$3 -> 58213.154 | C50: =POWER(1+$B$9,A50) -> 1.9161034 | D50: =$B$7*C50*$B$10 -> 1567.0512 | E50: =$B$7*$C50*$B$11 -> 1567.0512 | F50: =$B$7*$C50*$B$12 -> 1567.0512 | G50: =SUM(D50:F50) -> 4701.1536 | H50: =IF(A50=0,$B$17*$B$14*$B$13,H49*$B$13) -> 2.5664443e-08 | I50: =B50*$I$26 -> 7131.1114 | J50: =MAX(IF(A50>=$B$20,J49-$B$21,$B$17),0) -> 0 | K50: =IF(A50>=$B$20,J50*$B$18,0) -> 0 | L50: =IF(A50=$B$25,$B$24,0) -> 0 | M50: =I50-G50-K50+L50 -> 2429.9578 | N50: =M50-H50 -> 2429.9578 | O50: =IF(N50<0,N50,0) -> 0 | P50: =IF(N50>0,N50+O49,0) -> 2429.9578 | Q50: =$B$22*P50 -> 558.8903 | R50: =M50-Q50 -> 1871.0675 | S50: =IFERROR(__xludf.DUMMYFUNCTION("IF(ISBETWEEN(A50,$B$20,$B$20+$B$19-1),$B$21,0)"),0.0) -> 0 | T50: =R50-S50 -> 1871.0675 | U50: =T50+U49 -> 25417.911
A51: 23 | B51: =POWER(1-$B$8,A51)*$B$3 -> 57922.089 | C51: =POWER(1+$B$9,A51) -> 1.9735865 | D51: =$B$7*C51*$B$10 -> 1614.0627 | E51: =$B$7*$C51*$B$11 -> 1614.0627 | F51: =$B$7*$C51*$B$12 -> 1614.0627 | G51: =SUM(D51:F51) -> 4842.1882 | H51: =IF(A51=0,$B$17*$B$14*$B$13,H50*$B$13) -> 7.6993329e-09 | I51: =B51*$I$26 -> 7095.4559 | J51: =MAX(IF(A51>=$B$20,J50-$B$21,$B$17),0) -> 0 | K51: =IF(A51>=$B$20,J51*$B$18,0) -> 0 | L51: =IF(A51=$B$25,$B$24,0) -> 0 | M51: =I51-G51-K51+L51 -> 2253.2677 | N51: =M51-H51 -> 2253.2677 | O51: =IF(N51<0,N51,0) -> 0 | P51: =IF(N51>0,N51+O50,0) -> 2253.2677 | Q51: =$B$22*P51 -> 518.25156 | R51: =M51-Q51 -> 1735.0161 | S51: =IFERROR(__xludf.DUMMYFUNCTION("IF(ISBETWEEN(A51,$B$20,$B$20+$B$19-1),$B$21,0)"),0.0) -> 0 | T51: =R51-S51 -> 1735.0161 | U51: =T51+U50 -> 27152.927
A52: 24 | B52: =POWER(1-$B$8,A52)*$B$3 -> 57632.478 | C52: =POWER(1+$B$9,A52) -> 2.0327941 | D52: =$B$7*C52*$B$10 -> 1662.4846 | E52: =$B$7*$C52*$B$11 -> 1662.4846 | F52: =$B$7*$C52*$B$12 -> 1662.4846 | G52: =SUM(D52:F52) -> 4987.4538 | H52: =IF(A52=0,$B$17*$B$14*$B$13,H51*$B$13) -> 2.3097999e-09 | I52: =B52*$I$26 -> 7059.9786 | J52: =MAX(IF(A52>=$B$20,J51-$B$21,$B$17),0) -> 0 | K52: =IF(A52>=$B$20,J52*$B$18,0) -> 0 | L52: =IF(A52=$B$25,$B$24,0) -> 0 | M52: =I52-G52-K52+L52 -> 2072.5247 | N52: =M52-H52 -> 2072.5247 | O52: =IF(N52<0,N52,0) -> 0 | P52: =IF(N52>0,N52+O51,0) -> 2072.5247 | Q52: =$B$22*P52 -> 476.68069 | R52: =M52-Q52 -> 1595.8441 | S52: =IFERROR(__xludf.DUMMYFUNCTION("IF(ISBETWEEN(A52,$B$20,$B$20+$B$19-1),$B$21,0)"),0.0) -> 0 | T52: =R52-S52 -> 1595.8441 | U52: =T52+U51 -> 28748.771
B53: =SUM(B28:B52) -> 1531136.8 | D53: =SUM(D28:D52) -> 29817.563 | E53: =SUM(E28:E52) -> 29817.563 | F53: =SUM(F28:F52) -> 29817.563 | G53: =SUM(G28:G52) -> 89452.688 | H53: =SUM(H28:H52) -> 11683.318 | I53: =SUM(I28:I52) -> 187564.26 | K53: =SUM(K28:K52) -> 9813.9872 | L53: =SUM(L28:L52) -> 16356.645 | M53: =SUM(M28:M52) -> 104654.23 | Q53: =SUM(Q28:Q52) -> 21383.31 | R53: =SUM(R28:R52) -> 83270.923 | S53: =SUM(S28:S52) -> 54522.151 | T53: =SUM(T28:T52) -> 28748.771

Sheet Billing Rate
A1: Consumption | B1: 0.068
A2: Ratchet Demand | B2: 25

Sheet Rate Codes
A1: Code | B1: Type | C1: Component Type | D1: Price
A2: D300 | B2: Distribution | C2: Service Charge | D2: 9.591923
A3: D300 | B3: Distribution | C3: Facilities Charge | D3: 0.065117
A4: D300 | B4: Distribution | C4: Non-Ratcheted Demand Charge | D4: 0.062763
A5: D300 | B5: Transmission | C5: Demand Charge | D5: 0.266159
A6: D300 | B6: Transmission | C6: Variable Charge | D6: 0.009162
A7: D200 | B7: Distribution | C7: Service Charge | D7: 1.725485
A8: D200 | B8: Distribution | C8: Useage Charge | D8: 0.012953
A9: D200 | B9: Transmission | C9: Variable Charge | D9: 0.030251

Sheet Daylight Hours
A1: Month | B1: Daylight Hours (decimal) | C1: Light % | D1: Night Hours | E1: Night % | F1: Days | G1: Load kWh | H1: Average Load (kW) | I1: Generation kWh | J1: Average Power (kW) | K1: Coverage Factor
A2: January | B2: 8.45 | C2: =B2/24 -> 0.35208333 | D2: =24-B2 -> 15.55 | E2: =D2/24 -> 0.64791667 | F2: 31 | G2: 5726 | H2: =G2/24 -> 238.58333 | I2: 1775.3429 | J2: =I2/B2 -> 210.09975 | K2: =J2/H2 -> 0.8806137 | L2: =IF(K2>1,1,K2) -> 0.8806137 | M2: =C2*L2 -> 0.31004941 | N2: =1-M2 -> 0.68995059
A3: February | B3: 9.9167 | C3: =B3/24 -> 0.41319583 | D3: =24-B3 -> 14.0833 | E3: =D3/24 -> 0.58680417 | F3: 28 | G3: 5279 | H3: =G3/24 -> 219.95833 | I3: 3003.4757 | J3: =I3/B3 -> 302.87048 | K3: =J3/H3 -> 1.3769448 | L3: =IF(K3>1,1,K3) -> 1 | M3: =C3*L3 -> 0.41319583 | N3: =1-M3 -> 0.58680417
A4: March | B4: 11.8 | C4: =B4/24 -> 0.49166667 | D4: =24-B4 -> 12.2 | E4: =D4/24 -> 0.50833333 | F4: 31 | G4: 4991 | H4: =G4/24 -> 207.95833 | I4: 5525.5406 | J4: =I4/B4 -> 468.26615 | K4: =J4/H4 -> 2.2517306 | L4: =IF(K4>1,1,K4) -> 1 | M4: =C4*L4 -> 0.49166667 | N4: =1-M4 -> 0.50833333
A5: April | B5: 13.8 | C5: =B5/24 -> 0.575 | D5: =24-B5 -> 10.2 | E5: =D5/24 -> 0.425 | F5: 30 | G5: 4952 | H5: =G5/24 -> 206.33333 | I5: 7070.2564 | J5: =I5/B5 -> 512.33742 | K5: =J5/H5 -> 2.483057 | L5: =IF(K5>1,1,K5) -> 1 | M5: =C5*L5 -> 0.575 | N5: =1-M5 -> 0.425
A6: May | B6: 15.5333 | C6: =B6/24 -> 0.64722083 | D6: =24-B6 -> 8.4667 | E6: =D6/24 -> 0.35277917 | F6: 31 | G6: 5559 | H6: =G6/24 -> 231.625 | I6: 8331.327 | J6: =I6/B6 -> 536.35268 | K6: =J6/H6 -> 2.3156079 | L6: =IF(K6>1,1,K6) -> 1 | M6: =C6*L6 -> 0.64722083 | N6: =1-M6 -> 0.35277917
A7: June | B7: 16.4667 | C7: =B7/24 -> 0.6861125 | D7: =24-B7 -> 7.5333 | E7: =D7/24 -> 0.3138875 | F7: 30 | G7: 4964 | H7: =G7/24 -> 206.83333 | I7: 8156.5953 | J7: =I7/B7 -> 495.33879 | K7: =J7/H7 -> 2.3948693 | L7: =IF(K7>1,1,K7) -> 1 | M7: =C7*L7 -> 0.6861125 | N7: =1-M7 -> 0.3138875
A8: July | B8: 16.05 | C8: =B8/24 -> 0.66875 | D8: =24-B8 -> 7.95 | E8: =D8/24 -> 0.33125 | F8: 31 | G8: 6634 | H8: =G8/24 -> 276.41667 | I8: 9421.7052 | J8: =I8/B8 -> 587.02213 | K8: =J8/H8 -> 2.1236857 | L8: =IF(K8>1,1,K8) -> 1 | M8: =C8*L8 -> 0.66875 | N8: =1-M8 -> 0.33125
A9: August | B9: 14.5167 | C9: =B9/24 -> 0.6048625 | D9: =24-B9 -> 9.4833 | E9: =D9/24 -> 0.3951375 | F9: 31 | G9: 5909 | H9: =G9/24 -> 246.20833 | I9: 8105.1907 | J9: =I9/B9 -> 558.33562 | K9: =J9/H9 -> 2.2677365 | L9: =IF(K9>1,1,K9) -> 1 | M9: =C9*L9 -> 0.6048625 | N9: =1-M9 -> 0.3951375
A10: September | B10: 12.5833 | C10: =B10/24 -> 0.52430417 | D10: =24-B10 -> 11.4167 | E10: =D10/24 -> 0.47569583 | F10: 30 | G10: 5270 | H10: =G10/24 -> 219.58333 | I10: 6386.772 | J10: =I10/B10 -> 507.55939 | K10: =J10/H10 -> 2.3114659 | L10: =IF(K10>1,1,K10) -> 1 | M10: =C10*L10 -> 0.52430417 | N10: =1-M10 -> 0.47569583
A11: October | B11: 10.5833 | C11: =B11/24 -> 0.44097083 | D11: =24-B11 -> 13.4167 | E11: =D11/24 -> 0.55902917 | F11: 31 | G11: 5946 | H11: =G11/24 -> 247.75 | I11: 4446.2885 | J11: =I11/B11 -> 420.12307 | K11: =J11/H11 -> 1.6957541 | L11: =IF(K11>1,1,K11) -> 1 | M11: =C11*L11 -> 0.44097083 | N11: =1-M11 -> 0.55902917
A12: November | B12: 8.85 | C12: =B12/24 -> 0.36875 | D12: =24-B12 -> 15.15 | E12: =D12/24 -> 0.63125 | F12: 30 | G12: 5587 | H12: =G12/24 -> 232.79167 | I12: 1764.1523 | J12: =I12/B12 -> 199.33925 | K12: =J12/H12 -> 0.8562989 | L12: =IF(K12>1,1,K12) -> 0.8562989 | M12: =C12*L12 -> 0.31576022 | N12: =1-M12 -> 0.68423978
A13: December | B13: 7.9667 | C13: =B13/24 -> 0.33194583 | D13: =24-B13 -> 16.0333 | E13: =D13/24 -> 0.66805417 | F13: 31 | G13: 5490 | H13: =G13/24 -> 228.75 | I13: 1013.3534 | J13: =I13/B13 -> 127.19864 | K13: =J13/H13 -> 0.55605965 | L13: =IF(K13>1,1,K13) -> 0.55605965 | M13: =C13*L13 -> 0.18458168 | N13: =1-M13 -> 0.81541832
A14: Average | B14: =AVERAGE(B2:B13) -> 12.209725 | C14: =AVERAGE(C2:C13) -> 0.50873854 | D14: =AVERAGE(D2:D13) -> 11.790275 | E14: =AVERAGE(E2:E13) -> 0.49126146 | L14: =IF(K14>1,1,K14) | M14: =C14*L14 -> 0 | N14: =1-M14 -> 1

Sheet Bill Comparison
B1: Current Bill | G1: Bankable | M1: Solar Club
A2: Year | B2: Transmission | C2: Distribution | D2: Consumption | E2: Tax | F2: Total | G2: Transmission | H2: Distribution | I2: Consumption | J2: Tax | K2: Total | L2: Savings | M2: Consumption | N2: Tax | O2: Total | P2: SC Savings
A3: 0 | B3: ='Current Bill'!$K$15 -> 3084.7796 | C3: ='Current Bill'!$H$15 -> 4691.295 | D3: ='Current Bill'!$M$15 -> 4508.876 | E3: ='Current Bill'!$O$15 -> 614.24753 | F3: ='Current Bill'!$P$15 -> 12899.198 | G3: =IFERROR(__xludf.DUMMYFUNCTION("FILTER('Bankable Bill Annual'!T3:T401,'Bankable Bill Annual'!B3:B401=""Total"")"),438.74535759294247) -> 438.74536 | H3: =IFERROR(__xludf.DUMMYFUNCTION("FILTER('Bankable Bill Annual'!S3:S401,'Bankable Bill Annual'!B3:B401=""Total"")"),1068.5473825929425) -> 1068.5474 | I3: =IFERROR(__xludf.DUMMYFUNCTION("FILTER('Bankable Bill Annual'!U3:U401,'Bankable Bill Annual'!B3:B401=""Total"")"),88.87599995580007) -> 88.876 | J3: =IFERROR(__xludf.DUMMYFUNCTION("FILTER('Bankable Bill Annual'!Y3:Y401,'Bankable Bill Annual'!B3:B401=""Total"")"),1726.0196932726194) -> 1726.0197 | K3: =IFERROR(__xludf.DUMMYFUNCTION("FILTER('Bankable Bill Annual'!Y3:Y401,'Bankable Bill Annual'!B3:B401=""Total"")"),1726.0196932726194) -> 1726.0197 | L3: =F3-K3 -> 11173.178 | M3: =IFERROR(__xludf.DUMMYFUNCTION("FILTER('SC Bill Annual'!N3:N401,'SC Bill Annual'!B3:B401=""Total"")"),-3752.91857061456) -> -3752.9186 | N3: =IFERROR(__xludf.DUMMYFUNCTION("FILTER('SC Bill Annual'!Q3:Q401,'SC Bill Annual'!B3:B401=""Total"")"),129.65938618537092) -> 129.65939 | O3: =IFERROR(__xludf.DUMMYFUNCTION("FILTER('SC Bill Annual'!R3:R401,'SC Bill Annual'!B3:B401=""Total"")"),-2134.220631539711) -> -2134.2206 | P3: =F3-O3 -> 15033.419 | R3: =0.17*'Bankable Bill Annual'!I17 -> 11050 | S3: =R3+J3 -> 12776.02
A4: 1 | B4: ='Current Bill'!$K$15 -> 3084.7796 | C4: ='Current Bill'!$H$15 -> 4691.295 | D4: ='Current Bill'!$M$15 -> 4508.876 | E4: ='Current Bill'!$O$15 -> 614.24753 | F4: ='Current Bill'!$P$15 -> 12899.198 | G4: =IFERROR(__xludf.DUMMYFUNCTION("""COMPUTED_VALUE"""),439.0402228377189) -> 439.04022 | H4: =IFERROR(__xludf.DUMMYFUNCTION("""COMPUTED_VALUE"""),1068.8422478377188) -> 1068.8422 | I4: =IFERROR(__xludf.DUMMYFUNCTION("""COMPUTED_VALUE"""),110.97599995602104) -> 110.976 | J4: =IFERROR(__xludf.DUMMYFUNCTION("""COMPUTED_VALUE"""),1748.9429547062625) -> 1748.943 | K4: =IFERROR(__xludf.DUMMYFUNCTION("""COMPUTED_VALUE"""),1748.9429547062625) -> 1748.943 | L4: =F4-K4 -> 11150.255 | M4: =IFERROR(__xludf.DUMMYFUNCTION("""COMPUTED_VALUE"""),-3661.3379817614878) -> -3661.338 | N4: =IFERROR(__xludf.DUMMYFUNCTION("""COMPUTED_VALUE"""),130.07263566774859) -> 130.07264 | O4: =IFERROR(__xludf.DUMMYFUNCTION("""COMPUTED_VALUE"""),-2038.0967037026167) -> -2038.0967 | P4: =F4-O4 -> 14937.295
A5: 2 | B5: ='Current Bill'!$K$15 -> 3084.7796 | C5: ='Current Bill'!$H$15 -> 4691.295 | D5: ='Current Bill'!$M$15 -> 4508.876 | E5: ='Current Bill'!$O$15 -> 614.24753 | F5: ='Current Bill'!$P$15 -> 12899.198 | G5: =IFERROR(__xludf.DUMMYFUNCTION("""COMPUTED_VALUE"""),439.3336137562714) -> 439.33361 | H5: =IFERROR(__xludf.DUMMYFUNCTION("""COMPUTED_VALUE"""),1069.1356387562714) -> 1069.1356 | I5: =IFERROR(__xludf.DUMMYFUNCTION("""COMPUTED_VALUE"""),132.9654999562411) -> 132.9655 | J5: =IFERROR(__xludf.DUMMYFUNCTION("""COMPUTED_VALUE"""),1771.7515998327378) -> 1771.7516 | K5: =IFERROR(__xludf.DUMMYFUNCTION("""COMPUTED_VALUE"""),1771.7515998327378) -> 1771.7516 | L5: =F5-K5 -> 11127.447 | M5: =IFERROR(__xludf.DUMMYFUNCTION("""COMPUTED_VALUE"""),-3570.215295852679) -> -3570.2153 | N5: =IFERROR(__xludf.DUMMYFUNCTION("""COMPUTED_VALUE"""),130.48381890271435) -> 130.48382 | O5: =IFERROR(__xludf.DUMMYFUNCTION("""COMPUTED_VALUE"""),-1942.453395504709) -> -1942.4534 | P5: =F5-O5 -> 14841.652
A6: 3 | B6: ='Current Bill'!$K$15 -> 3084.7796 | C6: ='Current Bill'!$H$15 -> 4691.295 | D6: ='Current Bill'!$M$15 -> 4508.876 | E6: ='Current Bill'!$O$15 -> 614.24753 | F6: ='Current Bill'!$P$15 -> 12899.198 | G6: =IFERROR(__xludf.DUMMYFUNCTION("""COMPUTED_VALUE"""),439.6255377202312) -> 439.62554 | H6: =IFERROR(__xludf.DUMMYFUNCTION("""COMPUTED_VALUE"""),1069.4275627202312) -> 1069.4276 | I6: =IFERROR(__xludf.DUMMYFUNCTION("""COMPUTED_VALUE"""),154.8450524564597) -> 154.84505 | J6: =IFERROR(__xludf.DUMMYFUNCTION("""COMPUTED_VALUE"""),1794.4462017335804) -> 1794.4462 | K6: =IFERROR(__xludf.DUMMYFUNCTION("""COMPUTED_VALUE"""),1794.4462017335804) -> 1794.4462 | L6: =F6-K6 -> 11104.752 | M6: =IFERROR(__xludf.DUMMYFUNCTION("""COMPUTED_VALUE"""),-3479.5482233734156) -> -3479.5482 | N6: =IFERROR(__xludf.DUMMYFUNCTION("""COMPUTED_VALUE"""),130.89294622150527) -> 130.89295 | O6: =IFERROR(__xludf.DUMMYFUNCTION("""COMPUTED_VALUE"""),-1847.2883038477917) -> -1847.2883 | P6: =F6-O6 -> 14746.486
A7: 4 | B7: ='Current Bill'!$K$15 -> 3084.7796 | C7: ='Current Bill'!$H$15 -> 4691.295 | D7: ='Current Bill'!$M$15 -> 4508.876 | E7: ='Current Bill'!$O$15 -> 614.24753 | F7: ='Current Bill'!$P$15 -> 12899.198 | G7: =IFERROR(__xludf.DUMMYFUNCTION("""COMPUTED_VALUE"""),439.91600206437124) -> 439.916 | H7: =IFERROR(__xludf.DUMMYFUNCTION("""COMPUTED_VALUE"""),1069.718027064371) -> 1069.718 | I7: =IFERROR(__xludf.DUMMYFUNCTION("""COMPUTED_VALUE"""),176.61520719417763) -> 176.61521 | J7: =IFERROR(__xludf.DUMMYFUNCTION("""COMPUTED_VALUE"""),1817.027330624919) -> 1817.0273 | K7: =IFERROR(__xludf.DUMMYFUNCTION("""COMPUTED_VALUE"""),1817.027330624919) -> 1817.0273 | L7: =F7-K7 -> 11082.171 | M7: =IFERROR(__xludf.DUMMYFUNCTION("""COMPUTED_VALUE"""),-3389.334486256549) -> -3389.3345 | N7: =IFERROR(__xludf.DUMMYFUNCTION("""COMPUTED_VALUE"""),131.30002790370224) -> 131.30003 | O7: =IFERROR(__xludf.DUMMYFUNCTION("""COMPUTED_VALUE"""),-1752.599037649157) -> -1752.599 | P7: =F7-O7 -> 14651.797
A8: 5 | B8: ='Current Bill'!$K$15 -> 3084.7796 | C8: ='Current Bill'!$H$15 -> 4691.295 | D8: ='Current Bill'!$M$15 -> 4508.876 | E8: ='Current Bill'!$O$15 -> 614.24753 | F8: ='Current Bill'!$P$15 -> 12899.198 | G8: =IFERROR(__xludf.DUMMYFUNCTION("""COMPUTED_VALUE"""),440.20501408679036) -> 440.20501 | H8: =IFERROR(__xludf.DUMMYFUNCTION("""COMPUTED_VALUE"""),1070.0070390867902) -> 1070.007 | I8: =IFERROR(__xludf.DUMMYFUNCTION("""COMPUTED_VALUE"""),198.2765111582068) -> 198.27651 | J8: =IFERROR(__xludf.DUMMYFUNCTION("""COMPUTED_VALUE"""),1839.4955538718004) -> 1839.4956 | K8: =IFERROR(__xludf.DUMMYFUNCTION("""COMPUTED_VALUE"""),1839.4955538718004) -> 1839.4956 | L8: =F8-K8 -> 11059.703 | M8: =IFERROR(__xludf.DUMMYFUNCTION("""COMPUTED_VALUE"""),-3299.571817825265) -> -3299.5718 | N8: =IFERROR(__xludf.DUMMYFUNCTION("""COMPUTED_VALUE"""),131.70507417748826) -> 131.70507 | O8: =IFERROR(__xludf.DUMMYFUNCTION("""COMPUTED_VALUE"""),-1658.3832177815168) -> -1658.3832 | P8: =F8-O8 -> 14557.581
A9: 6 | B9: ='Current Bill'!$K$15 -> 3084.7796 | C9: ='Current Bill'!$H$15 -> 4691.295 | D9: ='Current Bill'!$M$15 -> 4508.876 | E9: ='Current Bill'!$O$15 -> 614.24753 | F9: ='Current Bill'!$P$15 -> 12899.198 | G9: =IFERROR(__xludf.DUMMYFUNCTION("""COMPUTED_VALUE"""),440.4925810490975) -> 440.49258 | H9: =IFERROR(__xludf.DUMMYFUNCTION("""COMPUTED_VALUE"""),1070.2946060490976) -> 1070.2946 | I9: =IFERROR(__xludf.DUMMYFUNCTION("""COMPUTED_VALUE"""),219.82950860241544) -> 219.82951 | J9: =IFERROR(__xludf.DUMMYFUNCTION("""COMPUTED_VALUE"""),1861.8514360024478) -> 1861.8514 | K9: =IFERROR(__xludf.DUMMYFUNCTION("""COMPUTED_VALUE"""),1861.8514360024478) -> 1861.8514 | L9: =F9-K9 -> 11037.347 | M9: =IFERROR(__xludf.DUMMYFUNCTION("""COMPUTED_VALUE"""),-3210.25796273614) -> -3210.258 | N9: =IFERROR(__xludf.DUMMYFUNCTION("""COMPUTED_VALUE"""),132.10809521990532) -> 132.1081 | O9: =IFERROR(__xludf.DUMMYFUNCTION("""COMPUTED_VALUE"""),-1564.6384770132152) -> -1564.6385 | P9: =F9-O9 -> 14463.837
A10: 7 | B10: ='Current Bill'!$K$15 -> 3084.7796 | C10: ='Current Bill'!$H$15 -> 4691.295 | D10: ='Current Bill'!$M$15 -> 4508.876 | E10: ='Current Bill'!$O$15 -> 614.24753 | F10: ='Current Bill'!$P$15 -> 12899.198 | G10: =IFERROR(__xludf.DUMMYFUNCTION("""COMPUTED_VALUE"""),440.7787101765931) -> 440.77871 | H10: =IFERROR(__xludf.DUMMYFUNCTION("""COMPUTED_VALUE"""),1070.5807351765932) -> 1070.5807 | I10: =IFERROR(__xludf.DUMMYFUNCTION("""COMPUTED_VALUE"""),241.27474105940394) -> 241.27474 | J10: =IFERROR(__xludf.DUMMYFUNCTION("""COMPUTED_VALUE"""),1884.0955387224421) -> 1884.0955 | K10: =IFERROR(__xludf.DUMMYFUNCTION("""COMPUTED_VALUE"""),1884.0955387224421) -> 1884.0955 | L10: =F10-K10 -> 11015.103 | M10: =IFERROR(__xludf.DUMMYFUNCTION("""COMPUTED_VALUE"""),-3121.3906769224577) -> -3121.3907 | N10: =IFERROR(__xludf.DUMMYFUNCTION("""COMPUTED_VALUE"""),132.50910115711034) -> 132.5091 | O10: =IFERROR(__xludf.DUMMYFUNCTION("""COMPUTED_VALUE"""),-1471.3624599487525) -> -1471.3625 | P10: =F10-O10 -> 14370.561
A11: 8 | B11: ='Current Bill'!$K$15 -> 3084.7796 | C11: ='Current Bill'!$H$15 -> 4691.295 | D11: ='Current Bill'!$M$15 -> 4508.876 | E11: ='Current Bill'!$O$15 -> 614.24753 | F11: ='Current Bill'!$P$15 -> 12899.198 | G11: =IFERROR(__xludf.DUMMYFUNCTION("""COMPUTED_VALUE"""),441.0634086584513) -> 441.06341 | H11: =IFERROR(__xludf.DUMMYFUNCTION("""COMPUTED_VALUE"""),1070.8654336584511) -> 1070.8654 | I11: =IFERROR(__xludf.DUMMYFUNCTION("""COMPUTED_VALUE"""),262.6127473541064) -> 262.61275 | J11: =IFERROR(__xludf.DUMMYFUNCTION("""COMPUTED_VALUE"""),1906.2284209288357) -> 1906.2284 | K11: =IFERROR(__xludf.DUMMYFUNCTION("""COMPUTED_VALUE"""),1906.2284209288357) -> 1906.2284 | L11: =F11-K11 -> 10992.97 | M11: =IFERROR(__xludf.DUMMYFUNCTION("""COMPUTED_VALUE"""),-3032.9677275378476) -> -3032.9677 | N11: =IFERROR(__xludf.DUMMYFUNCTION("""COMPUTED_VALUE"""),132.90810206462928) -> 132.9081 | O11: =IFERROR(__xludf.DUMMYFUNCTION("""COMPUTED_VALUE"""),-1378.5528229696156) -> -1378.5528 | P11: =F11-O11 -> 14277.751
A12: 9 | B12: ='Current Bill'!$K$15 -> 3084.7796 | C12: ='Current Bill'!$H$15 -> 4691.295 | D12: ='Current Bill'!$M$15 -> 4508.876 | E12: ='Current Bill'!$O$15 -> 614.24753 | F12: ='Current Bill'!$P$15 -> 12899.198 | G12: =IFERROR(__xludf.DUMMYFUNCTION("""COMPUTED_VALUE"""),441.34668364790014) -> 441.34668 | H12: =IFERROR(__xludf.DUMMYFUNCTION("""COMPUTED_VALUE"""),1071.1487086479) -> 1071.1487 | I12: =IFERROR(__xludf.DUMMYFUNCTION("""COMPUTED_VALUE"""),283.84406361733613) -> 283.84406 | J12: =IFERROR(__xludf.DUMMYFUNCTION("""COMPUTED_VALUE"""),1928.2506387241986) -> 1928.2506 | K12: =IFERROR(__xludf.DUMMYFUNCTION("""COMPUTED_VALUE"""),1928.2506387241986) -> 1928.2506 | L12: =F12-K12 -> 10970.948 | M12: =IFERROR(__xludf.DUMMYFUNCTION("""COMPUTED_VALUE"""),-2944.986892900157) -> -2944.9869 | N12: =IFERROR(__xludf.DUMMYFUNCTION("""COMPUTED_VALUE"""),133.30510796761067) -> 133.30511 | O12: =IFERROR(__xludf.DUMMYFUNCTION("""COMPUTED_VALUE"""),-1286.207234175372) -> -1286.2072 | P12: =F12-O12 -> 14185.405
A13: 10 | B13: ='Current Bill'!$K$15 -> 3084.7796 | C13: ='Current Bill'!$H$15 -> 4691.295 | D13: ='Current Bill'!$M$15 -> 4508.876 | E13: ='Current Bill'!$O$15 -> 614.24753 | F13: ='Current Bill'!$P$15 -> 12899.198 | G13: =IFERROR(__xludf.DUMMYFUNCTION("""COMPUTED_VALUE"""),441.6285422624017) -> 441.62854 | H13: =IFERROR(__xludf.DUMMYFUNCTION("""COMPUTED_VALUE"""),1071.4305672624018) -> 1071.4306 | I13: =IFERROR(__xludf.DUMMYFUNCTION("""COMPUTED_VALUE"""),304.9692232992495) -> 304.96922 | J13: =IFERROR(__xludf.DUMMYFUNCTION("""COMPUTED_VALUE"""),1950.1627454305835) -> 1950.1627 | K13: =IFERROR(__xludf.DUMMYFUNCTION("""COMPUTED_VALUE"""),1950.1627454305835) -> 1950.1627 | L13: =F13-K13 -> 10949.035 | M13: =IFERROR(__xludf.DUMMYFUNCTION("""COMPUTED_VALUE"""),-2857.445962435656) -> -2857.446 | N13: =IFERROR(__xludf.DUMMYFUNCTION("""COMPUTED_VALUE"""),133.70012884107712) -> 133.70013 | O13: =IFERROR(__xludf.DUMMYFUNCTION("""COMPUTED_VALUE"""),-1194.323373325099) -> -1194.3234 | P13: =F13-O13 -> 14093.522
A14: 11 | B14: ='Current Bill'!$K$15 -> 3084.7796 | C14: ='Current Bill'!$H$15 -> 4691.295 | D14: ='Current Bill'!$M$15 -> 4508.876 | E14: ='Current Bill'!$O$15 -> 614.24753 | F14: ='Current Bill'!$P$15 -> 12899.198 | G14: =IFERROR(__xludf.DUMMYFUNCTION("""COMPUTED_VALUE"""),441.90899158383087) -> 441.90899 | H14: =IFERROR(__xludf.DUMMYFUNCTION("""COMPUTED_VALUE"""),1071.7110165838308) -> 1071.711 | I14: =IFERROR(__xludf.DUMMYFUNCTION("""COMPUTED_VALUE"""),325.9887571827535) -> 325.98876 | J14: =IFERROR(__xludf.DUMMYFUNCTION("""COMPUTED_VALUE"""),1971.965291603437) -> 1971.9653 | K14: =IFERROR(__xludf.DUMMYFUNCTION("""COMPUTED_VALUE"""),1971.965291603437) -> 1971.9653 | L14: =F14-K14 -> 10927.233 | M14: =IFERROR(__xludf.DUMMYFUNCTION("""COMPUTED_VALUE"""),-2770.3427366234773) -> -2770.3427 | N14: =IFERROR(__xludf.DUMMYFUNCTION("""COMPUTED_VALUE"""),131.39454135387564) -> 131.39454 | O14: =IFERROR(__xludf.DUMMYFUNCTION("""COMPUTED_VALUE"""),-1159.5702301613917) -> -1159.5702 | P14: =F14-O14 -> 14058.768
A15: 12 | B15: ='Current Bill'!$K$15 -> 3084.7796 | C15: ='Current Bill'!$H$15 -> 4691.295 | D15: ='Current Bill'!$M$15 -> 4508.876 | E15: ='Current Bill'!$O$15 -> 614.24753 | F15: ='Current Bill'!$P$15 -> 12899.198 | G15: =IFERROR(__xludf.DUMMYFUNCTION("""COMPUTED_VALUE"""),442.1880386586528) -> 442.18804 | H15: =IFERROR(__xludf.DUMMYFUNCTION("""COMPUTED_VALUE"""),1071.9900636586528) -> 1071.9901 | I15: =IFERROR(__xludf.DUMMYFUNCTION("""COMPUTED_VALUE"""),346.90319339683964) -> 346.90319 | J15: =IFERROR(__xludf.DUMMYFUNCTION("""COMPUTED_VALUE"""),1993.6588250454263) -> 1993.6588 | K15: =IFERROR(__xludf.DUMMYFUNCTION("""COMPUTED_VALUE"""),1993.6588250454263) -> 1993.6588 | L15: =F15-K15 -> 10905.539 | M15: =IFERROR(__xludf.DUMMYFUNCTION("""COMPUTED_VALUE"""),-2683.6750269403597) -> -2683.675 | N15: =IFERROR(__xludf.DUMMYFUNCTION("""COMPUTED_VALUE"""),134.48425515042987) -> 134.48426 | O15: =IFERROR(__xludf.DUMMYFUNCTION("""COMPUTED_VALUE"""),-1011.9316124407889) -> -1011.9316 | P15: =F15-O15 -> 13911.13
A16: 13 | B16: ='Current Bill'!$K$15 -> 3084.7796 | C16: ='Current Bill'!$H$15 -> 4691.295 | D16: ='Current Bill'!$M$15 -> 4508.876 | E16: ='Current Bill'!$O$15 -> 614.24753 | F16: ='Current Bill'!$P$15 -> 12899.198 | G16: =IFERROR(__xludf.DUMMYFUNCTION("""COMPUTED_VALUE"""),442.4656904981006) -> 442.46569 | H16: =IFERROR(__xludf.DUMMYFUNCTION("""COMPUTED_VALUE"""),1072.2677154981004) -> 1072.2677 | I16: =IFERROR(__xludf.DUMMYFUNCTION("""COMPUTED_VALUE"""),367.71305742985516) -> 367.71306 | J16: =IFERROR(__xludf.DUMMYFUNCTION("""COMPUTED_VALUE"""),2015.2438908202053) -> 2015.2439 | K16: =IFERROR(__xludf.DUMMYFUNCTION("""COMPUTED_VALUE"""),2015.2438908202053) -> 2015.2439 | L16: =F16-K16 -> 10883.954 | M16: =IFERROR(__xludf.DUMMYFUNCTION("""COMPUTED_VALUE"""),-2597.4406558056594) -> -2597.4407 | N16: =IFERROR(__xludf.DUMMYFUNCTION("""COMPUTED_VALUE"""),134.87338028798223) -> 134.87338 | O16: =IFERROR(__xludf.DUMMYFUNCTION("""COMPUTED_VALUE"""),-921.4191296991912) -> -921.41913 | P16: =F16-O16 -> 13820.617
A17: 14 | B17: ='Current Bill'!$K$15 -> 3084.7796 | C17: ='Current Bill'!$H$15 -> 4691.295 | D17: ='Current Bill'!$M$15 -> 4508.876 | E17: ='Current Bill'!$O$15 -> 614.24753 | F17: ='Current Bill'!$P$15 -> 12899.198 | G17: =IFERROR(__xludf.DUMMYFUNCTION("""COMPUTED_VALUE"""),442.7419540783512) -> 442.74195 | H17: =IFERROR(__xludf.DUMMYFUNCTION("""COMPUTED_VALUE"""),1072.5439790783512) -> 1072.544 | I17: =IFERROR(__xludf.DUMMYFUNCTION("""COMPUTED_VALUE"""),388.41887214270605) -> 388.41887 | J17: =IFERROR(__xludf.DUMMYFUNCTION("""COMPUTED_VALUE"""),2036.721031266111) -> 2036.721 | K17: =IFERROR(__xludf.DUMMYFUNCTION("""COMPUTED_VALUE"""),2036.721031266111) -> 2036.721 | L17: =F17-K17 -> 10862.477 | M17: =IFERROR(__xludf.DUMMYFUNCTION("""COMPUTED_VALUE"""),-2511.63745652663) -> -2511.6375 | N17: =IFERROR(__xludf.DUMMYFUNCTION("""COMPUTED_VALUE"""),135.26055979984685) -> 135.26056 | O17: =IFERROR(__xludf.DUMMYFUNCTION("""COMPUTED_VALUE"""),-831.3592093712998) -> -831.35921 | P17: =F17-O17 -> 13730.557
A18: 15 | B18: ='Current Bill'!$K$15 -> 3084.7796 | C18: ='Current Bill'!$H$15 -> 4691.295 | D18: ='Current Bill'!$M$15 -> 4508.876 | E18: ='Current Bill'!$O$15 -> 614.24753 | F18: ='Current Bill'!$P$15 -> 12899.198 | G18: =IFERROR(__xludf.DUMMYFUNCTION("""COMPUTED_VALUE"""),443.01683634070054) -> 443.01684 | H18: =IFERROR(__xludf.DUMMYFUNCTION("""COMPUTED_VALUE"""),1072.8188613407006) -> 1072.8189 | I18: =IFERROR(__xludf.DUMMYFUNCTION("""COMPUTED_VALUE"""),409.0211577819923) -> 409.02116 | J18: =IFERROR(__xludf.DUMMYFUNCTION("""COMPUTED_VALUE"""),2058.0907860097864) -> 2058.0908 | K18: =IFERROR(__xludf.DUMMYFUNCTION("""COMPUTED_VALUE"""),2058.0907860097864) -> 2058.0908 | L18: =F18-K18 -> 10841.107 | M18: =IFERROR(__xludf.DUMMYFUNCTION("""COMPUTED_VALUE"""),-2426.2632732439974) -> -2426.2633 | N18: =IFERROR(__xludf.DUMMYFUNCTION("""COMPUTED_VALUE"""),135.6458034141521) -> 135.6458 | O18: =IFERROR(__xludf.DUMMYFUNCTION("""COMPUTED_VALUE"""),-741.749588645049) -> -741.74959 | P18: =F18-O18 -> 13640.948
A19: 16 | B19: ='Current Bill'!$K$15 -> 3084.7796 | C19: ='Current Bill'!$H$15 -> 4691.295 | D19: ='Current Bill'!$M$15 -> 4508.876 | E19: ='Current Bill'!$O$15 -> 614.24753 | F19: ='Current Bill'!$P$15 -> 12899.198 | G19: =IFERROR(__xludf.DUMMYFUNCTION("""COMPUTED_VALUE"""),443.29034419173814) -> 443.29034 | H19: =IFERROR(__xludf.DUMMYFUNCTION("""COMPUTED_VALUE"""),1073.092369191738) -> 1073.0924 | I19: =IFERROR(__xludf.DUMMYFUNCTION("""COMPUTED_VALUE"""),429.5204319930827) -> 429.52043 | J19: =IFERROR(__xludf.DUMMYFUNCTION("""COMPUTED_VALUE"""),2079.353691979744) -> 2079.3537 | K19: =IFERROR(__xludf.DUMMYFUNCTION("""COMPUTED_VALUE"""),2079.353691979744) -> 2079.3537 | L19: =F19-K19 -> 10819.844 | M19: =IFERROR(__xludf.DUMMYFUNCTION("""COMPUTED_VALUE"""),-2341.315960877776) -> -2341.316 | N19: =IFERROR(__xludf.DUMMYFUNCTION("""COMPUTED_VALUE"""),136.02912081038588) -> 136.02912 | O19: =IFERROR(__xludf.DUMMYFUNCTION("""COMPUTED_VALUE"""),-652.5880160224282) -> -652.58802 | P19: =F19-O19 -> 13551.786
A20: 17 | B20: ='Current Bill'!$K$15 -> 3084.7796 | C20: ='Current Bill'!$H$15 -> 4691.295 | D20: ='Current Bill'!$M$15 -> 4508.876 | E20: ='Current Bill'!$O$15 -> 614.24753 | F20: ='Current Bill'!$P$15 -> 12899.198 | G20: =IFERROR(__xludf.DUMMYFUNCTION("""COMPUTED_VALUE"""),443.5624845035205) -> 443.56248 | H20: =IFERROR(__xludf.DUMMYFUNCTION("""COMPUTED_VALUE"""),1073.3645095035206) -> 1073.3645 | I20: =IFERROR(__xludf.DUMMYFUNCTION("""COMPUTED_VALUE"""),449.91720983311745) -> 449.91721 | J20: =IFERROR(__xludf.DUMMYFUNCTION("""COMPUTED_VALUE"""),2100.5102834198515) -> 2100.5103 | K20: =IFERROR(__xludf.DUMMYFUNCTION("""COMPUTED_VALUE"""),2100.5102834198515) -> 2100.5103 | L20: =F20-K20 -> 10798.688 | M20: =IFERROR(__xludf.DUMMYFUNCTION("""COMPUTED_VALUE"""),-2256.793385073386) -> -2256.7934 | N20: =IFERROR(__xludf.DUMMYFUNCTION("""COMPUTED_VALUE"""),136.41052161963844) -> 136.41052 | O20: =IFERROR(__xludf.DUMMYFUNCTION("""COMPUTED_VALUE"""),-563.8722512629205) -> -563.87225 | P20: =F20-O20 -> 13463.07
A21: 18 | B21: ='Current Bill'!$K$15 -> 3084.7796 | C21: ='Current Bill'!$H$15 -> 4691.295 | D21: ='Current Bill'!$M$15 -> 4508.876 | E21: ='Current Bill'!$O$15 -> 614.24753 | F21: ='Current Bill'!$P$15 -> 12899.198 | G21: =IFERROR(__xludf.DUMMYFUNCTION("""COMPUTED_VALUE"""),443.8332641137441) -> 443.83326 | H21: =IFERROR(__xludf.DUMMYFUNCTION("""COMPUTED_VALUE"""),1073.635289113744) -> 1073.6353 | I21: =IFERROR(__xludf.DUMMYFUNCTION("""COMPUTED_VALUE"""),470.2120037839518) -> 470.212 | J21: =IFERROR(__xludf.DUMMYFUNCTION("""COMPUTED_VALUE"""),2121.5610919027586) -> 2121.5611 | K21: =IFERROR(__xludf.DUMMYFUNCTION("""COMPUTED_VALUE"""),2121.5610919027586) -> 2121.5611 | L21: =F21-K21 -> 10777.637 | M21: =IFERROR(__xludf.DUMMYFUNCTION("""COMPUTED_VALUE"""),-2172.6934221480205) -> -2172.6934 | N21: =IFERROR(__xludf.DUMMYFUNCTION("""COMPUTED_VALUE"""),136.79001542484474) -> 136.79002 | O21: =IFERROR(__xludf.DUMMYFUNCTION("""COMPUTED_VALUE"""),-475.6000653272116) -> -475.60007 | P21: =F21-O21 -> 13374.798
A22: 19 | B22: ='Current Bill'!$K$15 -> 3084.7796 | C22: ='Current Bill'!$H$15 -> 4691.295 | D22: ='Current Bill'!$M$15 -> 4508.876 | E22: ='Current Bill'!$O$15 -> 614.24753 | F22: ='Current Bill'!$P$15 -> 12899.198 | G22: =IFERROR(__xludf.DUMMYFUNCTION("""COMPUTED_VALUE"""),444.10268982591657) -> 444.10269 | H22: =IFERROR(__xludf.DUMMYFUNCTION("""COMPUTED_VALUE"""),1073.9047148259165) -> 1073.9047 | I22: =IFERROR(__xludf.DUMMYFUNCTION("""COMPUTED_VALUE"""),490.40532376503194) -> 490.40532 | J22: =IFERROR(__xludf.DUMMYFUNCTION("""COMPUTED_VALUE"""),2142.5066463432513) -> 2142.5066 | K22: =IFERROR(__xludf.DUMMYFUNCTION("""COMPUTED_VALUE"""),2142.5066463432513) -> 2142.5066 | L22: =F22-K22 -> 10756.692 | M22: =IFERROR(__xludf.DUMMYFUNCTION("""COMPUTED_VALUE"""),-2089.013959037281) -> -2089.014 | N22: =IFERROR(__xludf.DUMMYFUNCTION("""COMPUTED_VALUE"""),137.16761176102506) -> 137.16761 | O22: =IFERROR(__xludf.DUMMYFUNCTION("""COMPUTED_VALUE"""),-387.7692403211816) -> -387.76924 | P22: =F22-O22 -> 13286.967
A23: 20 | B23: ='Current Bill'!$K$15 -> 3084.7796 | C23: ='Current Bill'!$H$15 -> 4691.295 | D23: ='Current Bill'!$M$15 -> 4508.876 | E23: ='Current Bill'!$O$15 -> 614.24753 | F23: ='Current Bill'!$P$15 -> 12899.198 | G23: =IFERROR(__xludf.DUMMYFUNCTION("""COMPUTED_VALUE"""),444.37076840952795) -> 444.37077 | H23: =IFERROR(__xludf.DUMMYFUNCTION("""COMPUTED_VALUE"""),1074.172793409528) -> 1074.1728 | I23: =IFERROR(__xludf.DUMMYFUNCTION("""COMPUTED_VALUE"""),510.4976771462065) -> 510.49768 | J23: =IFERROR(__xludf.DUMMYFUNCTION("""COMPUTED_VALUE"""),2163.347473011541) -> 2163.3475 | K23: =IFERROR(__xludf.DUMMYFUNCTION("""COMPUTED_VALUE"""),2163.347473011541) -> 2163.3475 | L23: =F23-K23 -> 10735.851 | M23: =IFERROR(__xludf.DUMMYFUNCTION("""COMPUTED_VALUE"""),-2005.7528932420953) -> -2005.7529 | N23: =IFERROR(__xludf.DUMMYFUNCTION("""COMPUTED_VALUE"""),137.54332011552444) -> 137.54332 | O23: =IFERROR(__xludf.DUMMYFUNCTION("""COMPUTED_VALUE"""),-300.37756944018116) -> -300.37757 | P23: =F23-O23 -> 13199.576
A24: 21 | B24: ='Current Bill'!$K$15 -> 3084.7796 | C24: ='Current Bill'!$H$15 -> 4691.295 | D24: ='Current Bill'!$M$15 -> 4508.876 | E24: ='Current Bill'!$O$15 -> 614.24753 | F24: ='Current Bill'!$P$15 -> 12899.198 | G24: =IFERROR(__xludf.DUMMYFUNCTION("""COMPUTED_VALUE"""),444.6375066002214) -> 444.63751 | H24: =IFERROR(__xludf.DUMMYFUNCTION("""COMPUTED_VALUE"""),1074.4395316002215) -> 1074.4395 | I24: =IFERROR(__xludf.DUMMYFUNCTION("""COMPUTED_VALUE"""),530.4895687604757) -> 530.48957 | J24: =IFERROR(__xludf.DUMMYFUNCTION("""COMPUTED_VALUE"""),2184.143698953072) -> 2184.1437 | K24: =IFERROR(__xludf.DUMMYFUNCTION("""COMPUTED_VALUE"""),2184.143698953072) -> 2184.1437 | L24: =F24-K24 -> 10715.054 | M24: =IFERROR(__xludf.DUMMYFUNCTION("""COMPUTED_VALUE"""),-1922.9081327758834) -> -1922.9081 | N24: =IFERROR(__xludf.DUMMYFUNCTION("""COMPUTED_VALUE"""),138.20640175431285) -> 138.2064 | O24: =IFERROR(__xludf.DUMMYFUNCTION("""COMPUTED_VALUE"""),-213.1336050875231) -> -213.13361 | P24: =F24-O24 -> 13112.332
A25: 22 | B25: ='Current Bill'!$K$15 -> 3084.7796 | C25: ='Current Bill'!$H$15 -> 4691.295 | D25: ='Current Bill'!$M$15 -> 4508.876 | E25: ='Current Bill'!$O$15 -> 614.24753 | F25: ='Current Bill'!$P$15 -> 12899.198 | G25: =IFERROR(__xludf.DUMMYFUNCTION("""COMPUTED_VALUE"""),444.90291109996144) -> 444.90291 | H25: =IFERROR(__xludf.DUMMYFUNCTION("""COMPUTED_VALUE"""),1074.7049360999615) -> 1074.7049 | I25: =IFERROR(__xludf.DUMMYFUNCTION("""COMPUTED_VALUE"""),550.3815009166734) -> 550.3815 | J25: =IFERROR(__xludf.DUMMYFUNCTION("""COMPUTED_VALUE"""),2204.861187358313) -> 2204.8612 | K25: =IFERROR(__xludf.DUMMYFUNCTION("""COMPUTED_VALUE"""),2204.861187358313) -> 2204.8612 | L25: =F25-K25 -> 10694.337 | M25: =IFERROR(__xludf.DUMMYFUNCTION("""COMPUTED_VALUE"""),-1840.477596112004) -> -1840.4776 | N25: =IFERROR(__xludf.DUMMYFUNCTION("""COMPUTED_VALUE"""),138.98867365884578) -> 138.98867 | O25: =IFERROR(__xludf.DUMMYFUNCTION("""COMPUTED_VALUE"""),-126.20335488269075) -> -126.20335 | P25: =F25-O25 -> 13025.402
A26: 23 | B26: ='Current Bill'!$K$15 -> 3084.7796 | C26: ='Current Bill'!$H$15 -> 4691.295 | D26: ='Current Bill'!$M$15 -> 4508.876 | E26: ='Current Bill'!$O$15 -> 614.24753 | F26: ='Current Bill'!$P$15 -> 12899.198 | G26: =IFERROR(__xludf.DUMMYFUNCTION("""COMPUTED_VALUE"""),445.16698857720274) -> 445.16699 | H26: =IFERROR(__xludf.DUMMYFUNCTION("""COMPUTED_VALUE"""),1074.9690135772028) -> 1074.969 | I26: =IFERROR(__xludf.DUMMYFUNCTION("""COMPUTED_VALUE"""),570.1739734120899) -> 570.17397 | J26: =IFERROR(__xludf.DUMMYFUNCTION("""COMPUTED_VALUE"""),2225.475088321528) -> 2225.4751 | K26: =IFERROR(__xludf.DUMMYFUNCTION("""COMPUTED_VALUE"""),2225.475088321528) -> 2225.4751 | L26: =F26-K26 -> 10673.723 | M26: =IFERROR(__xludf.DUMMYFUNCTION("""COMPUTED_VALUE"""),-1758.459212131444) -> -1758.4592 | N26: =IFERROR(__xludf.DUMMYFUNCTION("""COMPUTED_VALUE"""),139.76703420385607) -> 139.76703 | O26: =IFERROR(__xludf.DUMMYFUNCTION("""COMPUTED_VALUE"""),-39.707755928882364) -> -39.707756 | P26: =F26-O26 -> 12938.906
A27: 24 | B27: ='Current Bill'!$K$15 -> 3084.7796 | C27: ='Current Bill'!$H$15 -> 4691.295 | D27: ='Current Bill'!$M$15 -> 4508.876 | E27: ='Current Bill'!$O$15 -> 614.24753 | F27: ='Current Bill'!$P$15 -> 12899.198 | G27: =IFERROR(__xludf.DUMMYFUNCTION("""COMPUTED_VALUE"""),445.4297456670578) -> 445.42975 | H27: =IFERROR(__xludf.DUMMYFUNCTION("""COMPUTED_VALUE"""),1075.2317706670578) -> 1075.2318 | I27: =IFERROR(__xludf.DUMMYFUNCTION("""COMPUTED_VALUE"""),589.8674835450295) -> 589.86748 | J27: =IFERROR(__xludf.DUMMYFUNCTION("""COMPUTED_VALUE"""),2245.9859197799265) -> 2245.9859 | K27: =IFERROR(__xludf.DUMMYFUNCTION("""COMPUTED_VALUE"""),2245.9859197799265) -> 2245.9859 | L27: =F27-K27 -> 10653.212 | M27: =IFERROR(__xludf.DUMMYFUNCTION("""COMPUTED_VALUE"""),-1676.8509200707877) -> -1676.8509 | N27: =IFERROR(__xludf.DUMMYFUNCTION("""COMPUTED_VALUE"""),140.5415029461413) -> 140.5415 | O27: =IFERROR(__xludf.DUMMYFUNCTION("""COMPUTED_VALUE"""),46.35536503015612) -> 46.355365 | P27: =F27-O27 -> 12852.843
A28: Total | B28: =SUM(B3:B27) -> 77119.491 | C28: =SUM(C3:C27) -> 117282.37 | D28: =SUM(D3:D27) -> 112721.9 | E28: =SUM(E3:E27) -> 15356.188 | F28: =SUM(F3:F27) -> 322479.95 | G28: =SUM(G3:G27) -> 11053.794 | H28: =SUM(H3:H27) -> 26798.845 | I28: =SUM(I3:I27) -> 8604.5948 | ... P28: =SUM(P3:P27) -> 348127.01
M29: * T&D are the same as Bankable

Sheet Current Bill
E1: Distribution | I1: Transmission
A2: Month | B2: Days | C2: Demand kVA | D2: Load kWh | E2: Service Charge | F2: Facilities Charge | G2: Demand Charge | H2: Total | I2: Demand Charge | J2: Variable Charge | K2: Total | L2: T&D Total | M2: Consumption | N2: Charges Total | O2: Tax (5%) | P2: Total
A3: Jan | B3: 31 | C3: 25.5 | D3: 5726 | E3: =B3*'Rate Codes'!$D$2 -> 297.34961 | F3: =B3*'Rate Codes'!$D$3*C3 -> 51.474989 | G3: =B3*'Rate Codes'!$D$4*C3 -> 49.614151 | H3: =SUM(E3:G3) -> 398.43875 | I3: =B3*'Rate Codes'!$D$5*C3 -> 210.39869 | J3: =D3*'Rate Codes'!$D$6 -> 52.461612 | K3: =SUM(I3:J3) -> 262.8603 | L3: =H3+K3 -> 661.29905 | M3: =D3*'Billing Rate'!$B$1 -> 389.368 | N3: =H3+K3+M3 -> 1050.6671 | O3: =N3*0.05 -> 52.533353 | P3: =N3+O3 -> 1103.2004
A4: Feb | B4: 28 | C4: 25.5 | D4: 5279 | E4: =B4*'Rate Codes'!$D$2 -> 268.57384 | F4: =B4*'Rate Codes'!$D$3*C4 -> 46.493538 | G4: =B4*'Rate Codes'!$D$4*C4 -> 44.812782 | H4: =SUM(E4:G4) -> 359.88016 | I4: =B4*'Rate Codes'!$D$5*C4 -> 190.03753 | J4: =D4*'Rate Codes'!$D$6 -> 48.366198 | K4: =SUM(I4:J4) -> 238.40372 | L4: =H4+K4 -> 598.28389 | M4: =D4*'Billing Rate'!$B$1 -> 358.972 | N4: =H4+K4+M4 -> 957.25589 | O4: =N4*0.05 -> 47.862794 | P4: =N4+O4 -> 1005.1187
A5: Mar | B5: 31 | C5: 25.5 | D5: 4991 | E5: =B5*'Rate Codes'!$D$2 -> 297.34961 | F5: =B5*'Rate Codes'!$D$3*C5 -> 51.474989 | G5: =B5*'Rate Codes'!$D$4*C5 -> 49.614151 | H5: =SUM(E5:G5) -> 398.43875 | I5: =B5*'Rate Codes'!$D$5*C5 -> 210.39869 | J5: =D5*'Rate Codes'!$D$6 -> 45.727542 | K5: =SUM(I5:J5) -> 256.12623 | L5: =H5+K5 -> 654.56498 | M5: =D5*'Billing Rate'!$B$1 -> 339.388 | N5: =H5+K5+M5 -> 993.95298 | O5: =N5*0.05 -> 49.697649 | P5: =N5+O5 -> 1043.6506
A6: Apr | B6: 30 | C6: 25.5 | D6: 4952 | E6: =B6*'Rate Codes'!$D$2 -> 287.75769 | F6: =B6*'Rate Codes'!$D$3*C6 -> 49.814505 | G6: =B6*'Rate Codes'!$D$4*C6 -> 48.013695 | H6: =SUM(E6:G6) -> 385.58589 | I6: =B6*'Rate Codes'!$D$5*C6 -> 203.61164 | J6: =D6*'Rate Codes'!$D$6 -> 45.370224 | K6: =SUM(I6:J6) -> 248.98186 | L6: =H6+K6 -> 634.56775 | M6: =D6*'Billing Rate'!$B$1 -> 336.736 | N6: =H6+K6+M6 -> 971.30375 | O6: =N6*0.05 -> 48.565187 | P6: =N6+O6 -> 1019.8689
A7: May | B7: 31 | C7: 25.5 | D7: 5559 | E7: =B7*'Rate Codes'!$D$2 -> 297.34961 | F7: =B7*'Rate Codes'!$D$3*C7 -> 51.474989 | G7: =B7*'Rate Codes'!$D$4*C7 -> 49.614151 | H7: =SUM(E7:G7) -> 398.43875 | I7: =B7*'Rate Codes'!$D$5*C7 -> 210.39869 | J7: =D7*'Rate Codes'!$D$6 -> 50.931558 | K7: =SUM(I7:J7) -> 261.33025 | L7: =H7+K7 -> 659.769 | M7: =D7*'Billing Rate'!$B$1 -> 378.012 | N7: =H7+K7+M7 -> 1037.781 | O7: =N7*0.05 -> 51.88905 | P7: =N7+O7 -> 1089.6701
A8: Jun | B8: 30 | C8: 25.5 | D8: 4964 | E8: =B8*'Rate Codes'!$D$2 -> 287.75769 | F8: =B8*'Rate Codes'!$D$3*C8 -> 49.814505 | G8: =B8*'Rate Codes'!$D$4*C8 -> 48.013695 | H8: =SUM(E8:G8) -> 385.58589 | I8: =B8*'Rate Codes'!$D$5*C8 -> 203.61164 | J8: =D8*'Rate Codes'!$D$6 -> 45.480168 | K8: =SUM(I8:J8) -> 249.0918 | L8: =H8+K8 -> 634.67769 | M8: =D8*'Billing Rate'!$B$1 -> 337.552 | N8: =H8+K8+M8 -> 972.22969 | O8: =N8*0.05 -> 48.611485 | P8: =N8+O8 -> 1020.8412
A9: Jul | B9: 31 | C9: 25.5 | D9: 6634 | E9: =B9*'Rate Codes'!$D$2 -> 297.34961 | F9: =B9*'Rate Codes'!$D$3*C9 -> 51.474989 | G9: =B9*'Rate Codes'!$D$4*C9 -> 49.614151 | H9: =SUM(E9:G9) -> 398.43875 | I9: =B9*'Rate Codes'!$D$5*C9 -> 210.39869 | J9: =D9*'Rate Codes'!$D$6 -> 60.780708 | K9: =SUM(I9:J9) -> 271.1794 | L9: =H9+K9 -> 669.61815 | M9: =D9*'Billing Rate'!$B$1 -> 451.112 | N9: =H9+K9+M9 -> 1120.7302 | O9: =N9*0.05 -> 56.036508 | P9: =N9+O9 -> 1176.7667
A10: Aug | B10: 31 | C10: 25.5 | D10: 5909 | E10: =B10*'Rate Codes'!$D$2 -> 297.34961 | F10: =B10*'Rate Codes'!$D$3*C10 -> 51.474989 | G10: =B10*'Rate Codes'!$D$4*C10 -> 49.614151 | H10: =SUM(E10:G10) -> 398.43875 | I10: =B10*'Rate Codes'!$D$5*C10 -> 210.39869 | J10: =D10*'Rate Codes'!$D$6 -> 54.138258 | K10: =SUM(I10:J10) -> 264.53695 | L10: =H10+K10 -> 662.9757 | M10: =D10*'Billing Rate'!$B$1 -> 401.812 | N10: =H10+K10+M10 -> 1064.7877 | O10: =N10*0.05 -> 53.239385 | P10: =N10+O10 -> 1118.0271
A11: Sep | B11: 30 | C11: 25.5 | D11: 5270 | E11: =B11*'Rate Codes'!$D$2 -> 287.75769 | F11: =B11*'Rate Codes'!$D$3*C11 -> 49.814505 | G11: =B11*'Rate Codes'!$D$4*C11 -> 48.013695 | H11: =SUM(E11:G11) -> 385.58589 | I11: =B11*'Rate Codes'!$D$5*C11 -> 203.61164 | J11: =D11*'Rate Codes'!$D$6 -> 48.28374 | K11: =SUM(I11:J11) -> 251.89538 | L11: =H11+K11 -> 637.48127 | M11: =D11*'Billing Rate'!$B$1 -> 358.36 | N11: =H11+K11+M11 -> 995.84127 | O11: =N11*0.05 -> 49.792063 | P11: =N11+O11 -> 1045.6333
A12: Oct | B12: 31 | C12: 25.5 | D12: 5946 | E12: =B12*'Rate Codes'!$D$2 -> 297.34961 | F12: =B12*'Rate Codes'!$D$3*C12 -> 51.474989 | G12: =B12*'Rate Codes'!$D$4*C12 -> 49.614151 | H12: =SUM(E12:G12) -> 398.43875 | I12: =B12*'Rate Codes'!$D$5*C12 -> 210.39869 | J12: =D12*'Rate Codes'!$D$6 -> 54.477252 | K12: =SUM(I12:J12) -> 264.87594 | L12: =H12+K12 -> 663.31469 | M12: =D12*'Billing Rate'!$B$1 -> 404.328 | N12: =H12+K12+M12 -> 1067.6427 | O12: =N12*0.05 -> 53.382135 | P12: =N12+O12 -> 1121.0248
A13: Nov | B13: 30 | C13: 25.5 | D13: 5587 | E13: =B13*'Rate Codes'!$D$2 -> 287.75769 | F13: =B13*'Rate Codes'!$D$3*C13 -> 49.814505 | G13: =B13*'Rate Codes'!$D$4*C13 -> 48.013695 | H13: =SUM(E13:G13) -> 385.58589 | I13: =B13*'Rate Codes'!$D$5*C13 -> 203.61164 | J13: =D13*'Rate Codes'!$D$6 -> 51.188094 | K13: =SUM(I13:J13) -> 254.79973 | L13: =H13+K13 -> 640.38562 | M13: =D13*'Billing Rate'!$B$1 -> 379.916 | N13: =H13+K13+M13 -> 1020.3016 | O13: =N13*0.05 -> 51.015081 | P13: =N13+O13 -> 1071.3167
A14: Dec | B14: 31 | C14: 25.5 | D14: 5490 | E14: =B14*'Rate Codes'!$D$2 -> 297.34961 | F14: =B14*'Rate Codes'!$D$3*C14 -> 51.474989 | G14: =B14*'Rate Codes'!$D$4*C14 -> 49.614151 | H14: =SUM(E14:G14) -> 398.43875 | I14: =B14*'Rate Codes'!$D$5*C14 -> 210.39869 | J14: =D14*'Rate Codes'!$D$6 -> 50.29938 | K14: =SUM(I14:J14) -> 260.69807 | L14: =H14+K14 -> 659.13682 | M14: =D14*'Billing Rate'!$B$1 -> 373.32 | N14: =H14+K14+M14 -> 1032.4568 | O14: =N14*0.05 -> 51.622841 | P14: =N14+O14 -> 1084.0797
A15: Total | C15: =SUM(C3:C14) -> 306 | D15: =SUM(D3:D14) -> 66307 | E15: =SUM(E3:E14) -> 3501.0519 | F15: =SUM(F3:F14) -> 606.07648 | G15: =SUM(G3:G14) -> 584.16662 | H15: =SUM(H3:H14) -> 4691.295 | I15: =SUM(I3:I14) -> 2477.2749 | J15: =SUM(J3:J14) -> 607.50473 | K15: =SUM(I15:J15) -> 3084.7796 | L15: =H15+K15 -> 7776.0746 | M15: =SUM(M3:M14) -> 4508.876 | N15: =SUM(N3:N14) -> 12284.951 | O15: =SUM(O3:O14) -> 614.24753 | P15: =SUM(P3:P14) -> 12899.198

Sheet Bankable Bill Annual
A1: Year | B1: Annual Generation | H1: 65000 | K1: Degradation rate | O1: 0.005 | Q1: 0.3 | V1: *Consumption (Load kWh) + Net exports = generation
V2: * Even when net exporting, we have T&D costs related to our consuming periods.
A3: 0 | B3: Annual Generation | H3: =$H$1* POWER((1 -$O$1),A3) -> 65000 | I3: Percent of Load | K3: =H3/K17 -> 0.98028866 | O3: Uncovered Load | P3: =1-K3 -> 0.019711343 | Q3: Distribution | T3: Transmission
B4: Month | C4: Days | D4: Daylight Hours (decimal) | E4: Light % | F4: Night Hours | G4: Night % | H4: Generation % | I4: Generation | J4: Average Power (kW) | K4: Load kWh | L4: Average Load (kW) | M4: Import Coverage | N4: Import Factor | O4: Net kWh | P4: Import | Q4: Facilities Charge | R4: Useage Charge | S4: Total | T4: Variable Charge | U4: Consumption | V4: T&D Total | W4: Charges Total | X4: Tax | Y4: Total
B5: Jan | C5: 31 | D5: 8.45 | E5: =D5/24 -> 0.35208333 | F5: =24-D5 -> 15.55 | G5: =F5/24 -> 0.64791667 | H5: 0.027312968 | I5: =H$3*H5 -> 1775.3429 | J5: =I5/C5/D5 -> 6.7774113 | K5: 5726 | L5: =K5/C5/24 -> 7.6962366 | M5: =IF((J5/L5)>1,1,J5/L5) -> 0.8806137 | N5: =1-E5*M5 -> 0.68995059 | O5: =K5-I5 -> 3950.6571 | P5: =K5*N5 -> 3950.6571 | Q5: =C5*'Rate Codes'!$D$7 -> 53.490035 | R5: =P5*'Rate Codes'!$D$8 -> 51.172861 | S5: =SUM(Q5:R5) -> 104.6629 | T5: =P5*'Rate Codes'!$D$8 -> 51.172861 | U5: =(O5)*'Billing Rate'!$B$1 -> 268.64468 | V5: =S5+T5 -> 155.83576 | W5: =U5+S5+T5 -> 424.48044 | X5: =(IF(U5>0,U5,0)+V5)*0.05 -> 21.224022 | Y5: =W5+X5 -> 445.70446
B6: Feb | C6: 28 | D6: 9.9167 | E6: =D6/24 -> 0.41319583 | F6: =24-D6 -> 14.0833 | G6: =F6/24 -> 0.58680417 | H6: 0.046207319 | I6: =H$3*H6 -> 3003.4757 | J6: =I6/C6/D6 -> 10.816803 | K6: 5279 | L6: =K6/C6/24 -> 7.8556548 | M6: =IF((J6/L6)>1,1,J6/L6) -> 1 | N6: =1-E6*M6 -> 0.58680417 | O6: =K6-I6 -> 2275.5243 | P6: =K6*N6 -> 3097.7392 | Q6: =C6*'Rate Codes'!$D$7 -> 48.31358 | R6: =P6*'Rate Codes'!$D$8 -> 40.125016 | S6: =SUM(Q6:R6) -> 88.438596 | T6: =P6*'Rate Codes'!$D$8 -> 40.125016 | U6: =(O6)*'Billing Rate'!$B$1 -> 154.73565 | V6: =S6+T6 -> 128.56361 | W6: =U6+S6+T6 -> 283.29926 | X6: =(IF(U6>0,U6,0)+V6)*0.05 -> 14.164963 | Y6: =W6+X6 -> 297.46423
B7: Mar | C7: 31 | D7: 11.8 | E7: =D7/24 -> 0.49166667 | F7: =24-D7 -> 12.2 | G7: =F7/24 -> 0.50833333 | H7: 0.085008316 | I7: =H$3*H7 -> 5525.5406 | J7: =I7/C7/D7 -> 15.10536 | K7: 4991 | L7: =K7/C7/24 -> 6.7083333 | M7: =IF((J7/L7)>1,1,J7/L7) -> 1 | N7: =1-E7*M7 -> 0.50833333 | O7: =K7-I7 -> -534.54056 | P7: =K7*N7 -> 2537.0917 | Q7: =C7*'Rate Codes'!$D$7 -> 53.490035 | R7: =P7*'Rate Codes'!$D$8 -> 32.862948 | S7: =SUM(Q7:R7) -> 86.352983 | T7: =P7*'Rate Codes'!$D$8 -> 32.862948 | U7: =(O7)*'Billing Rate'!$B$1 -> -36.348758 | V7: =S7+T7 -> 119.21593 | W7: =U7+S7+T7 -> 82.867174 | X7: =(IF(U7>0,U7,0)+V7)*0.05 -> 5.9607966 | Y7: =W7+X7 -> 88.827971
B8: Apr | C8: 30 | D8: 13.8 | E8: =D8/24 -> 0.575 | F8: =24-D8 -> 10.2 | G8: =F8/24 -> 0.425 | H8: 0.10877317 | I8: =H$3*H8 -> 7070.2564 | J8: =I8/C8/D8 -> 17.077914 | K8: 4952 | L8: =K8/C8/24 -> 6.8777778 | M8: =IF((J8/L8)>1,1,J8/L8) -> 1 | N8: =1-E8*M8 -> 0.425 | O8: =K8-I8 -> -2118.2564 | P8: =K8*N8 -> 2104.6 | Q8: =C8*'Rate Codes'!$D$7 -> 51.76455 | R8: =P8*'Rate Codes'!$D$8 -> 27.260884 | S8: =SUM(Q8:R8) -> 79.025434 | T8: =P8*'Rate Codes'!$D$8 -> 27.260884 | U8: =(O8)*'Billing Rate'!$B$1 -> -144.04143 | V8: =S8+T8 -> 106.28632 | W8: =U8+S8+T8 -> -37.755116 | X8: =(IF(U8>0,U8,0)+V8)*0.05 -> 5.3143159 | Y8: =W8+X8 -> -32.4408
B9: May | C9: 31 | D9: 15.5333 | E9: =D9/24 -> 0.64722083 | F9: =24-D9 -> 8.4667 | G9: =F9/24 -> 0.35277917 | H9: 0.12817426 | I9: =H$3*H9 -> 8331.327 | J9: =I9/C9/D9 -> 17.301699 | K9: 5559 | L9: =K9/C9/24 -> 7.4717742 | M9: =IF((J9/L9)>1,1,J9/L9) -> 1 | N9: =1-E9*M9 -> 0.35277917 | O9: =K9-I9 -> -2772.327 | P9: =K9*N9 -> 1961.0994 | Q9: =C9*'Rate Codes'!$D$7 -> 53.490035 | R9: =P9*'Rate Codes'!$D$8 -> 25.40212 | S9: =SUM(Q9:R9) -> 78.892155 | T9: =P9*'Rate Codes'!$D$8 -> 25.40212 | U9: =(O9)*'Billing Rate'!$B$1 -> -188.51824 | V9: =S9+T9 -> 104.29428 | W9: =U9+S9+T9 -> -84.223961 | X9: =(IF(U9>0,U9,0)+V9)*0.05 -> 5.2147138 | Y9: =W9+X9 -> -79.009247
B10: Jun | C10: 30 | D10: 16.4667 | E10: =D10/24 -> 0.6861125 | F10: =24-D10 -> 7.5333 | G10: =F10/24 -> 0.3138875 | H10: 0.12548608 | I10: =H$3*H10 -> 8156.5953 | J10: =I10/C10/D10 -> 16.511293 | K10: 4964 | L10: =K10/C10/24 -> 6.8944444 | M10: =IF((J10/L10)>1,1,J10/L10) -> 1 | N10: =1-E10*M10 -> 0.3138875 | O10: =K10-I10 -> -3192.5953 | P10: =K10*N10 -> 1558.1375 | Q10: =C10*'Rate Codes'!$D$7 -> 51.76455 | R10: =P10*'Rate Codes'!$D$8 -> 20.182556 | S10: =SUM(Q10:R10) -> 71.947106 | T10: =P10*'Rate Codes'!$D$8 -> 20.182556 | U10: =(O10)*'Billing Rate'!$B$1 -> -217.09648 | V10: =S10+T10 -> 92.129661 | W10: =U10+S10+T10 -> -124.96682 | X10: =(IF(U10>0,U10,0)+V10)*0.05 -> 4.6064831 | Y10: =W10+X10 -> -120.36033
B11: Jul | C11: 31 | D11: 16.05 | E11: =D11/24 -> 0.66875 | F11: =24-D11 -> 7.95 | G11: =F11/24 -> 0.33125 | H11: 0.14494931 | I11: =H$3*H11 -> 9421.7052 | J11: =I11/C11/D11 -> 18.936198 | K11: 6634 | L11: =K11/C11/24 -> 8.9166667 | M11: =IF((J11/L11)>1,1,J11/L11) -> 1 | N11: =1-E11*M11 -> 0.33125 | O11: =K11-I11 -> -2787.7052 | P11: =K11*N11 -> 2197.5125 | Q11: =C11*'Rate Codes'!$D$7 -> 53.490035 | R11: =P11*'Rate Codes'!$D$8 -> 28.464379 | S11: =SUM(Q11:R11) -> 81.954414 | T11: =P11*'Rate Codes'!$D$8 -> 28.464379 | U11: =(O11)*'Billing Rate'!$B$1 -> -189.56396 | V11: =S11+T11 -> 110.41879 | W11: =U11+S11+T11 -> -79.145162 | X11: =(IF(U11>0,U11,0)+V11)*0.05 -> 5.5209397 | Y11: =W11+X11 -> -73.624222
B12: Aug | C12: 31 | D12: 14.5167 | E12: =D12/24 -> 0.6048625 | F12: =24-D12 -> 9.4833 | G12: =F12/24 -> 0.3951375 | H12: 0.12469524 | I12: =H$3*H12 -> 8105.1907 | J12: =I12/C12/D12 -> 18.010826 | K12: 5909 | L12: =K12/C12/24 -> 7.9422043 | M12: =IF((J12/L12)>1,1,J12/L12) -> 1 | N12: =1-E12*M12 -> 0.3951375 | O12: =K12-I12 -> -2196.1907 | P12: =K12*N12 -> 2334.8675 | Q12: =C12*'Rate Codes'!$D$7 -> 53.490035 | R12: =P12*'Rate Codes'!$D$8 -> 30.243539 | S12: =SUM(Q12:R12) -> 83.733574 | T12: =P12*'Rate Codes'!$D$8 -> 30.243539 | U12: =(O12)*'Billing Rate'!$B$1 -> -149.34096 | V12: =S12+T12 -> 113.97711 | W12: =U12+S12+T12 -> -35.363853 | X12: =(IF(U12>0,U12,0)+V12)*0.05 -> 5.6988556 | Y12: =W12+X12 -> -29.664997
B13: Sep | C13: 30 | D13: 12.5833 | E13: =D13/24 -> 0.52430417 | F13: =24-D13 -> 11.4167 | G13: =F13/24 -> 0.47569583 | H13: 0.098258031 | I13: =H$3*H13 -> 6386.772 | J13: =I13/C13/D13 -> 16.918646 | K13: 5270 | L13: =K13/C13/24 -> 7.3194444 | M13: =IF((J13/L13)>1,1,J13/L13) -> 1 | N13: =1-E13*M13 -> 0.47569583 | O13: =K13-I13 -> -1116.772 | P13: =K13*N13 -> 2506.917 | Q13: =C13*'Rate Codes'!$D$7 -> 51.76455 | R13: =P13*'Rate Codes'!$D$8 -> 32.472096 | S13: =SUM(Q13:R13) -> 84.236646 | T13: =P13*'Rate Codes'!$D$8 -> 32.472096 | U13: =(O13)*'Billing Rate'!$B$1 -> -75.940497 | V13: =S13+T13 -> 116.70874 | W13: =U13+S13+T13 -> 40.768246 | X13: =(IF(U13>0,U13,0)+V13)*0.05 -> 5.8354371 | Y13: =W13+X13 -> 46.603683
B14: Oct | C14: 31 | D14: 10.5833 | E14: =D14/24 -> 0.44097083 | F14: =24-D14 -> 13.4167 | G14: =F14/24 -> 0.55902917 | H14: 0.068404439 | I14: =H$3*H14 -> 4446.2885 | J14: =I14/C14/D14 -> 13.552357 | K14: 5946 | L14: =K14/C14/24 -> 7.9919355 | M14: =IF((J14/L14)>1,1,J14/L14) -> 1 | N14: =1-E14*M14 -> 0.55902917 | O14: =K14-I14 -> 1499.7115 | P14: =K14*N14 -> 3323.9874 | Q14: =C14*'Rate Codes'!$D$7 -> 53.490035 | R14: =P14*'Rate Codes'!$D$8 -> 43.055609 | S14: =SUM(Q14:R14) -> 96.545644 | T14: =P14*'Rate Codes'!$D$8 -> 43.055609 | U14: =(O14)*'Billing Rate'!$B$1 -> 101.98038 | V14: =S14+T14 -> 139.60125 | W14: =U14+S14+T14 -> 241.58163 | X14: =(IF(U14>0,U14,0)+V14)*0.05 -> 12.079082 | Y14: =W14+X14 -> 253.66072
B15: Nov | C15: 30 | D15: 8.85 | E15: =D15/24 -> 0.36875 | F15: =24-D15 -> 15.15 | G15: =F15/24 -> 0.63125 | H15: 0.027140805 | I15: =H$3*H15 -> 1764.1523 | J15: =I15/C15/D15 -> 6.6446416 | K15: 5587 | L15: =K15/C15/24 -> 7.7597222 | M15: =IF((J15/L15)>1,1,J15/L15) -> 0.8562989 | N15: =1-E15*M15 -> 0.68423978 | O15: =K15-I15 -> 3822.8477 | P15: =K15*N15 -> 3822.8477 | Q15: =C15*'Rate Codes'!$D$7 -> 51.76455 | R15: =P15*'Rate Codes'!$D$8 -> 49.517346 | S15: =SUM(Q15:R15) -> 101.2819 | T15: =P15*'Rate Codes'!$D$8 -> 49.517346 | U15: =(O15)*'Billing Rate'!$B$1 -> 259.95364 | V15: =S15+T15 -> 150.79924 | W15: =U15+S15+T15 -> 410.75288 | X15: =(IF(U15>0,U15,0)+V15)*0.05 -> 20.537644 | Y15: =W15+X15 -> 431.29053
B16: Dec | C16: 31 | D16: 7.9667 | E16: =D16/24 -> 0.33194583 | F16: =24-D16 -> 16.0333 | G16: =F16/24 -> 0.66805417 | H16: 0.015590053 | I16: =H$3*H16 -> 1013.3534 | J16: =I16/C16/D16 -> 4.1031821 | K16: 5490 | L16: =K16/C16/24 -> 7.3790323 | M16: =IF((J16/L16)>1,1,J16/L16) -> 0.55605965 | N16: =1-E16*M16 -> 0.81541832 | O16: =K16-I16 -> 4476.6466 | P16: =K16*N16 -> 4476.6466 | Q16: =C16*'Rate Codes'!$D$7 -> 53.490035 | R16: =P16*'Rate Codes'!$D$8 -> 57.986003 | S16: =SUM(Q16:R16) -> 111.47604 | T16: =P16*'Rate Codes'!$D$8 -> 57.986003 | U16: =(O16)*'Billing Rate'!$B$1 -> 304.41197 | V16: =S16+T16 -> 169.46204 | W16: =U16+S16+T16 -> 473.87401 | X16: =(IF(U16>0,U16,0)+V16)*0.05 -> 23.6937 | Y16: =W16+X16 -> 497.56771
B17: Total | H17: =SUM(H5:H16) -> 1 | I17: =SUM(I5:I16) -> 65000 | K17: =SUM(K5:K16) -> 66307 | N17: =G17*M17 -> 0 | O17: =SUM(O5:O16) -> 1307 | P17: =SUM(P5:P16) -> 33872.104 | Q17: =SUM(Q5:Q16) -> 629.80202 | R17: =SUM(R5:R16) -> 438.74536 | S17: =SUM(S5:S16) -> 1068.5474 | T17: =SUM(T5:T16) -> 438.74536 | U17: =SUM(U5:U16) -> 88.876 | V17: =S17+T17 -> 1507.2927 | W17: =SUM(W5:W16) -> 1596.1687 | X17: =SUM(X5:X16) -> 129.85095 | Y17: =SUM(Y5:Y16) -> 1726.0197
A19: 1 | B19: Annual Generation | H19: =$H$1* POWER((1 -$O$1),A19) -> 64675 | I19: Percent of Load | K19: =H19/K33 -> 0.97538721 | O19: Uncovered Load | P19: =1-K19 -> 0.024612786 | Q19: Distribution | T19: Transmission
B20: Month | C20: Days | D20: Daylight Hours (decimal) | E20: Light % | F20: Night Hours | G20: Night % | H20: Generation % | I20: Generation | J20: Average Power (kW) | K20: Load kWh | L20: Average Load (kW) | M20: Import Coverage | N20: Import Factor | O20: Net kWh | P20: Import | Q20: Facilities Charge | R20: Useage Charge | S20: Total | T20: Variable Charge | U20: Consumption | V20: T&D Total | W20: Charges Total | X20: Tax | Y20: Total
B21: Jan | C21: 31 | D21: 8.45 | E21: =D21/24 -> 0.35208333 | F21: =24-D21 -> 15.55 | G21: =F21/24 -> 0.64791667 | H21: 0.027312968 | I21: =H$19*H21 -> 1766.4662 | J21: =I21/C21/D21 -> 6.7435243 | K21: 5726 | L21: =K21/C21/24 -> 7.6962366 | M21: =IF((J21/L21)>1,1,J21/L21) -> 0.87621063 | N21: =1-E21*M21 -> 0.69150084 | O21: =K21-I21 -> 3959.5338 | P21: =K21*N21 -> 3959.5338 | Q21: =C21*'Rate Codes'!$D$7 -> 53.490035 | R21: =P21*'Rate Codes'!$D$8 -> 51.287841 | S21: =SUM(Q21:R21) -> 104.77788 | T21: =P21*'Rate Codes'!$D$8 -> 51.287841 | U21: =(O21)*'Billing Rate'!$B$1 -> 269.2483 | V21: =S21+T21 -> 156.06572 | W21: =U21+S21+T21 -> 425.31402 | X21: =(IF(U21>0,U21,0)+V21)*0.05 -> 21.265701 | Y21: =W21+X21 -> 446.57972
B22: Feb | C22: 28 | D22: 9.9167 | E22: =D22/24 -> 0.41319583 | F22: =24-D22 -> 14.0833 | G22: =F22/24 -> 0.58680417 | H22: 0.046207319 | I22: =H$19*H22 -> 2988.4583 | J22: =I22/C22/D22 -> 10.762719 | K22: 5279 | L22: =K22/C22/24 -> 7.8556548 | M22: =IF((J22/L22)>1,1,J22/L22) -> 1 | N22: =1-E22*M22 -> 0.58680417 | O22: =K22-I22 -> 2290.5417 | P22: =K22*N22 -> 3097.7392 | Q22: =C22*'Rate Codes'!$D$7 -> 48.31358 | R22: =P22*'Rate Codes'!$D$8 -> 40.125016 | S22: =SUM(Q22:R22) -> 88.438596 | T22: =P22*'Rate Codes'!$D$8 -> 40.125016 | U22: =(O22)*'Billing Rate'!$B$1 -> 155.75683 | V22: =S22+T22 -> 128.56361 | W22: =U22+S22+T22 -> 284.32044 | X22: =(IF(U22>0,U22,0)+V22)*0.05 -> 14.216022 | Y22: =W22+X22 -> 298.53647
B23: Mar | C23: 31 | D23: 11.8 | E23: =D23/24 -> 0.49166667 | F23: =24-D23 -> 12.2 | G23: =F23/24 -> 0.50833333 | H23: 0.085008316 | I23: =H$19*H23 -> 5497.9129 | J23: =I23/C23/D23 -> 15.029833 | K23: 4991 | L23: =K23/C23/24 -> 6.7083333 | M23: =IF((J23/L23)>1,1,J23/L23) -> 1 | N23: =1-E23*M23 -> 0.50833333 | O23: =K23-I23 -> -506.91285 | P23: =K23*N23 -> 2537.0917 | Q23: =C23*'Rate Codes'!$D$7 -> 53.490035 | R23: =P23*'Rate Codes'!$D$8 -> 32.862948 | S23: =SUM(Q23:R23) -> 86.352983 | T23: =P23*'Rate Codes'!$D$8 -> 32.862948 | U23: =(O23)*'Billing Rate'!$B$1 -> -34.470074 | V23: =S23+T23 -> 119.21593 | W23: =U23+S23+T23 -> 84.745858 | X23: =(IF(U23>0,U23,0)+V23)*0.05 -> 5.9607966 | Y23: =W23+X23 -> 90.706654
B24: Apr | C24: 30 | D24: 13.8 | E24: =D24/24 -> 0.575 | F24: =24-D24 -> 10.2 | G24: =F24/24 -> 0.425 | H24: 0.10877317 | I24: =H$19*H24 -> 7034.9051 | J24: =I24/C24/D24 -> 16.992524 | K24: 4952 | L24: =K24/C24/24 -> 6.8777778 | M24: =IF((J24/L24)>1,1,J24/L24) -> 1 | N24: =1-E24*M24 -> 0.425 | O24: =K24-I24 -> -2082.9051 | P24: =K24*N24 -> 2104.6 | Q24: =C24*'Rate Codes'!$D$7 -> 51.76455 | R24: =P24*'Rate Codes'!$D$8 -> 27.260884 | S24: =SUM(Q24:R24) -> 79.025434 | T24: =P24*'Rate Codes'!$D$8 -> 27.260884 | U24: =(O24)*'Billing Rate'!$B$1 -> -141.63755 | V24: =S24+T24 -> 106.28632 | W24: =U24+S24+T24 -> -35.351229 | X24: =(IF(U24>0,U24,0)+V24)*0.05 -> 5.3143159 | Y24: =W24+X24 -> -30.036913
B25: May | C25: 31 | D25: 15.5333 | E25: =D25/24 -> 0.64722083 | F25: =24-D25 -> 8.4667 | G25: =F25/24 -> 0.35277917 | H25: 0.12817426 | I25: =H$19*H25 -> 8289.6704 | J25: =I25/C25/D25 -> 17.215191 | K25: 5559 | L25: =K25/C25/24 -> 7.4717742 | M25: =IF((J25/L25)>1,1,J25/L25) -> 1 | N25: =1-E25*M25 -> 0.35277917 | O25: =K25-I25 -> -2730.6704 | P25: =K25*N25 -> 1961.0994 | Q25: =C25*'Rate Codes'!$D$7 -> 53.490035 | R25: =P25*'Rate Codes'!$D$8 -> 25.40212 | S25: =SUM(Q25:R25) -> 78.892155 | T25: =P25*'Rate Codes'!$D$8 -> 25.40212 | U25: =(O25)*'Billing Rate'!$B$1 -> -185.68559 | V25: =S25+T25 -> 104.29428 | W25: =U25+S25+T25 -> -81.39131 | X25: =(IF(U25>0,U25,0)+V25)*0.05 -> 5.2147138 | Y25: =W25+X25 -> -76.176596
B26: Jun | C26: 30 | D26: 16.4667 | E26: =D26/24 -> 0.6861125 | F26: =24-D26 -> 7.5333 | G26: =F26/24 -> 0.3138875 | H26: 0.12548608 | I26: =H$19*H26 -> 8115.8123 | J26: =I26/C26/D26 -> 16.428737 | K26: 4964 | L26: =K26/C26/24 -> 6.8944444 | M26: =IF((J26/L26)>1,1,J26/L26) -> 1 | N26: =1-E26*M26 -> 0.3138875 | O26: =K26-I26 -> -3151.8123 | P26: =K26*N26 -> 1558.1375 | Q26: =C26*'Rate Codes'!$D$7 -> 51.76455 | R26: =P26*'Rate Codes'!$D$8 -> 20.182556 | S26: =SUM(Q26:R26) -> 71.947106 | T26: =P26*'Rate Codes'!$D$8 -> 20.182556 | U26: =(O26)*'Billing Rate'!$B$1 -> -214.32323 | V26: =S26+T26 -> 92.129661 | W26: =U26+S26+T26 -> -122.19357 | X26: =(IF(U26>0,U26,0)+V26)*0.05 -> 4.6064831 | Y26: =W26+X26 -> -117.58709
B27: Jul | C27: 31 | D27: 16.05 | E27: =D27/24 -> 0.66875 | F27: =24-D27 -> 7.95 | G27: =F27/24 -> 0.33125 | H27: 0.14494931 | I27: =H$19*H27 -> 9374.5967 | J27: =I27/C27/D27 -> 18.841517 | K27: 6634 | L27: =K27/C27/24 -> 8.9166667 | M27: =IF((J27/L27)>1,1,J27/L27) -> 1 | N27: =1-E27*M27 -> 0.33125 | O27: =K27-I27 -> -2740.5967 | P27: =K27*N27 -> 2197.5125 | Q27: =C27*'Rate Codes'!$D$7 -> 53.490035 | R27: =P27*'Rate Codes'!$D$8 -> 28.464379 | S27: =SUM(Q27:R27) -> 81.954414 | T27: =P27*'Rate Codes'!$D$8 -> 28.464379 | U27: =(O27)*'Billing Rate'!$B$1 -> -186.36058 | V27: =S27+T27 -> 110.41879 | W27: =U27+S27+T27 -> -75.941782 | X27: =(IF(U27>0,U27,0)+V27)*0.05 -> 5.5209397 | Y27: =W27+X27 -> -70.420842
B28: Aug | C28: 31 | D28: 14.5167 | E28: =D28/24 -> 0.6048625 | F28: =24-D28 -> 9.4833 | G28: =F28/24 -> 0.3951375 | H28: 0.12469524 | I28: =H$19*H28 -> 8064.6647 | J28: =I28/C28/D28 -> 17.920772 | K28: 5909 | L28: =K28/C28/24 -> 7.9422043 | M28: =IF((J28/L28)>1,1,J28/L28) -> 1 | N28: =1-E28*M28 -> 0.3951375 | O28: =K28-I28 -> -2155.6647 | P28: =K28*N28 -> 2334.8675 | Q28: =C28*'Rate Codes'!$D$7 -> 53.490035 | R28: =P28*'Rate Codes'!$D$8 -> 30.243539 | S28: =SUM(Q28:R28) -> 83.733574 | T28: =P28*'Rate Codes'!$D$8 -> 30.243539 | U28: =(O28)*'Billing Rate'!$B$1 -> -146.5852 | V28: =S28+T28 -> 113.97711 | W28: =U28+S28+T28 -> -32.608088 | X28: =(IF(U28>0,U28,0)+V28)*0.05 -> 5.6988556 | Y28: =W28+X28 -> -26.909232
B29: Sep | C29: 30 | D29: 12.5833 | E29: =D29/24 -> 0.52430417 | F29: =24-D29 -> 11.4167 | G29: =F29/24 -> 0.47569583 | H29: 0.098258031 | I29: =H$19*H29 -> 6354.8382 | J29: =I29/C29/D29 -> 16.834053 | K29: 5270 | L29: =K29/C29/24 -> 7.3194444 | M29: =IF((J29/L29)>1,1,J29/L29) -> 1 | N29: =1-E29*M29 -> 0.47569583 | O29: =K29-I29 -> -1084.8382 | P29: =K29*N29 -> 2506.917 | Q29: =C29*'Rate Codes'!$D$7 -> 51.76455 | R29: =P29*'Rate Codes'!$D$8 -> 32.472096 | S29: =SUM(Q29:R29) -> 84.236646 | T29: =P29*'Rate Codes'!$D$8 -> 32.472096 | U29: =(O29)*'Billing Rate'!$B$1 -> -73.768995 | V29: =S29+T29 -> 116.70874 | W29: =U29+S29+T29 -> 42.939748 | X29: =(IF(U29>0,U29,0)+V29)*0.05 -> 5.8354371 | Y29: =W29+X29 -> 48.775185
B30: Oct | C30: 31 | D30: 10.5833 | E30: =D30/24 -> 0.44097083 | F30: =24-D30 -> 13.4167 | G30: =F30/24 -> 0.55902917 | H30: 0.068404439 | I30: =H$19*H30 -> 4424.0571 | J30: =I30/C30/D30 -> 13.484595 | K30: 5946 | L30: =K30/C30/24 -> 7.9919355 | M30: =IF((J30/L30)>1,1,J30/L30) -> 1 | N30: =1-E30*M30 -> 0.55902917 | O30: =K30-I30 -> 1521.9429 | P30: =K30*N30 -> 3323.9874 | Q30: =C30*'Rate Codes'!$D$7 -> 53.490035 | R30: =P30*'Rate Codes'!$D$8 -> 43.055609 | S30: =SUM(Q30:R30) -> 96.545644 | T30: =P30*'Rate Codes'!$D$8 -> 43.055609 | U30: =(O30)*'Billing Rate'!$B$1 -> 103.49212 | V30: =S30+T30 -> 139.60125 | W30: =U30+S30+T30 -> 243.09337 | X30: =(IF(U30>0,U30,0)+V30)*0.05 -> 12.154669 | Y30: =W30+X30 -> 255.24804
B31: Nov | C31: 30 | D31: 8.85 | E31: =D31/24 -> 0.36875 | F31: =24-D31 -> 15.15 | G31: =F31/24 -> 0.63125 | H31: 0.027140805 | I31: =H$19*H31 -> 1755.3316 | J31: =I31/C31/D31 -> 6.6114184 | K31: 5587 | L31: =K31/C31/24 -> 7.7597222 | M31: =IF((J31/L31)>1,1,J31/L31) -> 0.8520174 | N31: =1-E31*M31 -> 0.68581858 | O31: =K31-I31 -> 3831.6684 | P31: =K31*N31 -> 3831.6684 | Q31: =C31*'Rate Codes'!$D$7 -> 51.76455 | R31: =P31*'Rate Codes'!$D$8 -> 49.631601 | S31: =SUM(Q31:R31) -> 101.39615 | T31: =P31*'Rate Codes'!$D$8 -> 49.631601 | U31: =(O31)*'Billing Rate'!$B$1 -> 260.55345 | V31: =S31+T31 -> 151.02775 | W31: =U31+S31+T31 -> 411.58121 | X31: =(IF(U31>0,U31,0)+V31)*0.05 -> 20.57906 | Y31: =W31+X31 -> 432.16027
B32: Dec | C32: 31 | D32: 7.9667 | E32: =D32/24 -> 0.33194583 | F32: =24-D32 -> 16.0333 | G32: =F32/24 -> 0.66805417 | H32: 0.015590053 | I32: =H$19*H32 -> 1008.2867 | J32: =I32/C32/D32 -> 4.0826662 | K32: 5490 | L32: =K32/C32/24 -> 7.3790323 | M32: =IF((J32/L32)>1,1,J32/L32) -> 0.55327935 | N32: =1-E32*M32 -> 0.81634123 | O32: =K32-I32 -> 4481.7133 | P32: =K32*N32 -> 4481.7133 | Q32: =C32*'Rate Codes'!$D$7 -> 53.490035 | R32: =P32*'Rate Codes'!$D$8 -> 58.051633 | S32: =SUM(Q32:R32) -> 111.54167 | T32: =P32*'Rate Codes'!$D$8 -> 58.051633 | U32: =(O32)*'Billing Rate'!$B$1 -> 304.75651 | V32: =S32+T32 -> 169.5933 | W32: =U32+S32+T32 -> 474.34981 | X32: =(IF(U32>0,U32,0)+V32)*0.05 -> 23.71749 | Y32: =W32+X32 -> 498.0673
B33: Total | H33: =SUM(H21:H32) -> 1 | I33: =SUM(I21:I32) -> 64675 | K33: =SUM(K21:K32) -> 66307 | O33: =SUM(O21:O32) -> 1632 | P33: =SUM(P21:P32) -> 33894.868 | Q33: =SUM(Q21:Q32) -> 629.80202 | R33: =SUM(R21:R32) -> 439.04022 | S33: =SUM(S21:S32) -> 1068.8422 | T33: =SUM(T21:T32) -> 439.04022 | U33: =SUM(U21:U32) -> 110.976 | V33: =S33+T33 -> 1507.8825 | W33: =SUM(W21:W32) -> 1618.8585 | X33: =SUM(X21:X32) -> 130.08448 | Y33: =SUM(Y21:Y32) -> 1748.943
A35: 2 | B35: Annual Generation | H35: =$H$1* POWER((1 -$O$1),A35) -> 64351.625 | I35: Percent of Load | K35: =H35/K49 -> 0.97051028 | O35: Uncovered Load | P35: =1-K35 -> 0.029489722 | Q35: Distribution | T35: Transmission
B36: Month | C36: Days | D36: Daylight Hours (decimal) | E36: Light % | F36: Night Hours | G36: Night % | H36: Generation % | I36: Generation | J36: Average Power (kW) | K36: Load kWh | L36: Average Load (kW) | M36: Import Coverage | N36: Import Factor | O36: Net kWh | P36: Import | Q36: Facilities Charge | R36: Useage Charge | S36: Total | T36: Variable Charge | U36: Consumption | V36: T&D Total | W36: Charges Total | X36: Tax | Y36: Total
B37: Jan | C37: 31 | D37: 8.45 | E37: =D37/24 -> 0.35208333 | F37: =24-D37 -> 15.55 | G37: =F37/24 -> 0.64791667 | H37: 0.027312968 | I37: =H$35*H37 -> 1757.6339 | J37: =I37/C37/D37 -> 6.7098067 | K37: 5726 | L37: =K37/C37/24 -> 7.6962366 | M37: =IF((J37/L37)>1,1,J37/L37) -> 0.87182958 | N37: =1-E37*M37 -> 0.69304334 | O37: =K37-I37 -> 3968.3661 | P37: =K37*N37 -> 3968.3661 | Q37: =C37*'Rate Codes'!$D$7 -> 53.490035 | R37: =P37*'Rate Codes'!$D$8 -> 51.402247 | S37: =SUM(Q37:R37) -> 104.89228 | T37: =P37*'Rate Codes'!$D$8 -> 51.402247 | U37: =(O37)*'Billing Rate'!$B$1 -> 269.8489 | V37: =S37+T37 -> 156.29453 | W37: =U37+S37+T37 -> 426.14343 | X37: =(IF(U37>0,U37,0)+V37)*0.05 -> 21.307171 | Y37: =W37+X37 -> 447.4506
B38: Feb | C38: 28 | D38: 9.9167 | E38: =D38/24 -> 0.41319583 | F38: =24-D38 -> 14.0833 | G38: =F38/24 -> 0.58680417 | H38: 0.046207319 | I38: =H$35*H38 -> 2973.516 | J38: =I38/C38/D38 -> 10.708905 | K38: 5279 | L38: =K38/C38/24 -> 7.8556548 | M38: =IF((J38/L38)>1,1,J38/L38) -> 1 | N38: =1-E38*M38 -> 0.58680417 | O38: =K38-I38 -> 2305.484 | P38: =K38*N38 -> 3097.7392 | Q38: =C38*'Rate Codes'!$D$7 -> 48.31358 | R38: =P38*'Rate Codes'!$D$8 -> 40.125016 | S38: =SUM(Q38:R38) -> 88.438596 | T38: =P38*'Rate Codes'!$D$8 -> 40.125016 | U38: =(O38)*'Billing Rate'!$B$1 -> 156.77291 | V38: =S38+T38 -> 128.56361 | W38: =U38+S38+T38 -> 285.33652 | X38: =(IF(U38>0,U38,0)+V38)*0.05 -> 14.266826 | Y38: =W38+X38 -> 299.60335
B39: Mar | C39: 31 | D39: 11.8 | E39: =D39/24 -> 0.49166667 | F39: =24-D39 -> 12.2 | G39: =F39/24 -> 0.50833333 | H39: 0.085008316 | I39: =H$35*H39 -> 5470.4233 | J39: =I39/C39/D39 -> 14.954684 | K39: 4991 | L39: =K39/C39/24 -> 6.7083333 | M39: =IF((J39/L39)>1,1,J39/L39) -> 1 | N39: =1-E39*M39 -> 0.50833333 | O39: =K39-I39 -> -479.42329 | P39: =K39*N39 -> 2537.0917 | Q39: =C39*'Rate Codes'!$D$7 -> 53.490035 | R39: =P39*'Rate Codes'!$D$8 -> 32.862948 | S39: =SUM(Q39:R39) -> 86.352983 | T39: =P39*'Rate Codes'!$D$8 -> 32.862948 | U39: =(O39)*'Billing Rate'!$B$1 -> -32.600784 | V39: =S39+T39 -> 119.21593 | W39: =U39+S39+T39 -> 86.615148 | X39: =(IF(U39>0,U39,0)+V39)*0.05 -> 5.9607966 | Y39: =W39+X39 -> 92.575945
B40: Apr | C40: 30 | D40: 13.8 | E40: =D40/24 -> 0.575 | F40: =24-D40 -> 10.2 | G40: =F40/24 -> 0.425 | H40: 0.10877317 | I40: =H$35*H40 -> 6999.7306 | J40: =I40/C40/D40 -> 16.907562 | K40: 4952 | L40: =K40/C40/24 -> 6.8777778 | M40: =IF((J40/L40)>1,1,J40/L40) -> 1 | N40: =1-E40*M40 -> 0.425 | O40: =K40-I40 -> -2047.7306 | P40: =K40*N40 -> 2104.6 | Q40: =C40*'Rate Codes'!$D$7 -> 51.76455 | R40: =P40*'Rate Codes'!$D$8 -> 27.260884 | S40: =SUM(Q40:R40) -> 79.025434 | T40: =P40*'Rate Codes'!$D$8 -> 27.260884 | U40: =(O40)*'Billing Rate'!$B$1 -> -139.24568 | V40: =S40+T40 -> 106.28632 | W40: =U40+S40+T40 -> -32.959361 | X40: =(IF(U40>0,U40,0)+V40)*0.05 -> 5.3143159 | Y40: =W40+X40 -> -27.645045
B41: May | C41: 31 | D41: 15.5333 | E41: =D41/24 -> 0.64722083 | F41: =24-D41 -> 8.4667 | G41: =F41/24 -> 0.35277917 | H41: 0.12817426 | I41: =H$35*H41 -> 8248.222 | J41: =I41/C41/D41 -> 17.129115 | K41: 5559 | L41: =K41/C41/24 -> 7.4717742 | M41: =IF((J41/L41)>1,1,J41/L41) -> 1 | N41: =1-E41*M41 -> 0.35277917 | O41: =K41-I41 -> -2689.222 | P41: =K41*N41 -> 1961.0994 | Q41: =C41*'Rate Codes'!$D$7 -> 53.490035 | R41: =P41*'Rate Codes'!$D$8 -> 25.40212 | S41: =SUM(Q41:R41) -> 78.892155 | T41: =P41*'Rate Codes'!$D$8 -> 25.40212 | U41: =(O41)*'Billing Rate'!$B$1 -> -182.8671 | V41: =S41+T41 -> 104.29428 | W41: =U41+S41+T41 -> -78.572822 | X41: =(IF(U41>0,U41,0)+V41)*0.05 -> 5.2147138 | Y41: =W41+X41 -> -73.358108
B42: Jun | C42: 30 | D42: 16.4667 | E42: =D42/24 -> 0.6861125 | F42: =24-D42 -> 7.5333 | G42: =F42/24 -> 0.3138875 | H42: 0.12548608 | I42: =H$35*H42 -> 8075.2332 | J42: =I42/C42/D42 -> 16.346593 | K42: 4964 | L42: =K42/C42/24 -> 6.8944444 | M42: =IF((J42/L42)>1,1,J42/L42) -> 1 | N42: =1-E42*M42 -> 0.3138875 | O42: =K42-I42 -> -3111.2332 | P42: =K42*N42 -> 1558.1375 | Q42: =C42*'Rate Codes'!$D$7 -> 51.76455 | R42: =P42*'Rate Codes'!$D$8 -> 20.182556 | S42: =SUM(Q42:R42) -> 71.947106 | T42: =P42*'Rate Codes'!$D$8 -> 20.182556 | U42: =(O42)*'Billing Rate'!$B$1 -> -211.56386 | V42: =S42+T42 -> 92.129661 | W42: =U42+S42+T42 -> -119.4342 | X42: =(IF(U42>0,U42,0)+V42)*0.05 -> 4.6064831 | Y42: =W42+X42 -> -114.82771
B43: Jul | C43: 31 | D43: 16.05 | E43: =D43/24 -> 0.66875 | F43: =24-D43 -> 7.95 | G43: =F43/24 -> 0.33125 | H43: 0.14494931 | I43: =H$35*H43 -> 9327.7237 | J43: =I43/C43/D43 -> 18.747309 | K43: 6634 | L43: =K43/C43/24 -> 8.9166667 | M43: =IF((J43/L43)>1,1,J43/L43) -> 1 | N43: =1-E43*M43 -> 0.33125 | O43: =K43-I43 -> -2693.7237 | P43: =K43*N43 -> 2197.5125 | Q43: =C43*'Rate Codes'!$D$7 -> 53.490035 | R43: =P43*'Rate Codes'!$D$8 -> 28.464379 | S43: =SUM(Q43:R43) -> 81.954414 | T43: =P43*'Rate Codes'!$D$8 -> 28.464379 | U43: =(O43)*'Billing Rate'!$B$1 -> -183.17321 | V43: =S43+T43 -> 110.41879 | W43: =U43+S43+T43 -> -72.754419 | X43: =(IF(U43>0,U43,0)+V43)*0.05 -> 5.5209397 | Y43: =W43+X43 -> -67.233479
B44: Aug | C44: 31 | D44: 14.5167 | E44: =D44/24 -> 0.6048625 | F44: =24-D44 -> 9.4833 | G44: =F44/24 -> 0.3951375 | H44: 0.12469524 | I44: =H$35*H44 -> 8024.3414 | J44: =I44/C44/D44 -> 17.831168 | K44: 5909 | L44: =K44/C44/24 -> 7.9422043 | M44: =IF((J44/L44)>1,1,J44/L44) -> 1 | N44: =1-E44*M44 -> 0.3951375 | O44: =K44-I44 -> -2115.3414 | P44: =K44*N44 -> 2334.8675 | Q44: =C44*'Rate Codes'!$D$7 -> 53.490035 | R44: =P44*'Rate Codes'!$D$8 -> 30.243539 | S44: =SUM(Q44:R44) -> 83.733574 | T44: =P44*'Rate Codes'!$D$8 -> 30.243539 | U44: =(O44)*'Billing Rate'!$B$1 -> -143.84321 | V44: =S44+T44 -> 113.97711 | W44: =U44+S44+T44 -> -29.866102 | X44: =(IF(U44>0,U44,0)+V44)*0.05 -> 5.6988556 | Y44: =W44+X44 -> -24.167246
B45: Sep | C45: 30 | D45: 12.5833 | E45: =D45/24 -> 0.52430417 | F45: =24-D45 -> 11.4167 | G45: =F45/24 -> 0.47569583 | H45: 0.098258031 | I45: =H$35*H45 -> 6323.064 | J45: =I45/C45/D45 -> 16.749883 | K45: 5270 | L45: =K45/C45/24 -> 7.3194444 | M45: =IF((J45/L45)>1,1,J45/L45) -> 1 | N45: =1-E45*M45 -> 0.47569583 | O45: =K45-I45 -> -1053.064 | P45: =K45*N45 -> 2506.917 | Q45: =C45*'Rate Codes'!$D$7 -> 51.76455 | R45: =P45*'Rate Codes'!$D$8 -> 32.472096 | S45: =SUM(Q45:R45) -> 84.236646 | T45: =P45*'Rate Codes'!$D$8 -> 32.472096 | U45: =(O45)*'Billing Rate'!$B$1 -> -71.60835 | V45: =S45+T45 -> 116.70874 | W45: =U45+S45+T45 -> 45.100393 | X45: =(IF(U45>0,U45,0)+V45)*0.05 -> 5.8354371 | Y45: =W45+X45 -> 50.93583
B46: Oct | C46: 31 | D46: 10.5833 | E46: =D46/24 -> 0.44097083 | F46: =24-D46 -> 13.4167 | G46: =F46/24 -> 0.55902917 | H46: 0.068404439 | I46: =H$35*H46 -> 4401.9368 | J46: =I46/C46/D46 -> 13.417172 | K46: 5946 | L46: =K46/C46/24 -> 7.9919355 | M46: =IF((J46/L46)>1,1,J46/L46) -> 1 | N46: =1-E46*M46 -> 0.55902917 | O46: =K46-I46 -> 1544.0632 | P46: =K46*N46 -> 3323.9874 | Q46: =C46*'Rate Codes'!$D$7 -> 53.490035 | R46: =P46*'Rate Codes'!$D$8 -> 43.055609 | S46: =SUM(Q46:R46) -> 96.545644 | T46: =P46*'Rate Codes'!$D$8 -> 43.055609 | U46: =(O46)*'Billing Rate'!$B$1 -> 104.9963 | V46: =S46+T46 -> 139.60125 | W46: =U46+S46+T46 -> 244.59755 | X46: =(IF(U46>0,U46,0)+V46)*0.05 -> 12.229878 | Y46: =W46+X46 -> 256.82743
B47: Nov | C47: 30 | D47: 8.85 | E47: =D47/24 -> 0.36875 | F47: =24-D47 -> 15.15 | G47: =F47/24 -> 0.63125 | H47: 0.027140805 | I47: =H$35*H47 -> 1746.5549 | J47: =I47/C47/D47 -> 6.5783613 | K47: 5587 | L47: =K47/C47/24 -> 7.7597222 | M47: =IF((J47/L47)>1,1,J47/L47) -> 0.84775731 | N47: =1-E47*M47 -> 0.68738949 | O47: =K47-I47 -> 3840.4451 | P47: =K47*N47 -> 3840.4451 | Q47: =C47*'Rate Codes'!$D$7 -> 51.76455 | R47: =P47*'Rate Codes'!$D$8 -> 49.745285 | S47: =SUM(Q47:R47) -> 101.50984 | T47: =P47*'Rate Codes'!$D$8 -> 49.745285 | U47: =(O47)*'Billing Rate'!$B$1 -> 261.15027 | V47: =S47+T47 -> 151.25512 | W47: =U47+S47+T47 -> 412.40539 | X47: =(IF(U47>0,U47,0)+V47)*0.05 -> 20.620269 | Y47: =W47+X47 -> 433.02566
B48: Dec | C48: 31 | D48: 7.9667 | E48: =D48/24 -> 0.33194583 | F48: =24-D48 -> 16.0333 | G48: =F48/24 -> 0.66805417 | H48: 0.015590053 | I48: =H$35*H48 -> 1003.2452 | J48: =I48/C48/D48 -> 4.0622528 | K48: 5490 | L48: =K48/C48/24 -> 7.3790323 | M48: =IF((J48/L48)>1,1,J48/L48) -> 0.55051295 | N48: =1-E48*M48 -> 0.81725952 | O48: =K48-I48 -> 4486.7548 | P48: =K48*N48 -> 4486.7548 | Q48: =C48*'Rate Codes'!$D$7 -> 53.490035 | R48: =P48*'Rate Codes'!$D$8 -> 58.116934 | S48: =SUM(Q48:R48) -> 111.60697 | T48: =P48*'Rate Codes'!$D$8 -> 58.116934 | U48: =(O48)*'Billing Rate'!$B$1 -> 305.09932 | V48: =S48+T48 -> 169.7239 | W48: =U48+S48+T48 -> 474.82323 | X48: =(IF(U48>0,U48,0)+V48)*0.05 -> 23.741161 | Y48: =W48+X48 -> 498.56439
B49: Total | H49: =SUM(H37:H48) -> 1 | I49: =SUM(I37:I48) -> 64351.625 | K49: =SUM(K37:K48) -> 66307 | O49: =SUM(O37:O48) -> 1955.375 | P49: =SUM(P37:P48) -> 33917.518 | Q49: =SUM(Q37:Q48) -> 629.80202 | R49: =SUM(R37:R48) -> 439.33361 | S49: =SUM(S37:S48) -> 1069.1356 | T49: =SUM(T37:T48) -> 439.33361 | U49: =SUM(U37:U48) -> 132.9655 | V49: =S49+T49 -> 1508.4693 | W49: =SUM(W37:W48) -> 1641.4348 | X49: =SUM(X37:X48) -> 130.31685 | Y49: =SUM(Y37:Y48) -> 1771.7516
A51: 3 | B51: Annual Generation | H51: =$H$1* POWER((1 -$O$1),A51) -> 64029.867 | I51: Percent of Load | K51: =H51/K65 -> 0.96565773 | O51: Uncovered Load | P51: =1-K51 -> 0.034342273 | Q51: Distribution | T51: Transmission
B52: Month | C52: Days | D52: Daylight Hours (decimal) | E52: Light % | F52: Night Hours | G52: Night % | H52: Generation % | I52: Generation | J52: Average Power (kW) | K52: Load kWh | L52: Average Load (kW) | M52: Import Coverage | N52: Import Factor | O52: Net kWh | P52: Import | Q52: Facilities Charge | R52: Useage Charge | S52: Total | T52: Variable Charge | U52: Consumption | V52: T&D Total | W52: Charges Total | X52: Tax | Y52: Total
B53: Jan | C53: 31 | D53: 8.45 | E53: =D53/24 -> 0.35208333 | F53: =24-D53 -> 15.55 | G53: =F53/24 -> 0.64791667 | H53: 0.027312968 | I53: =H$51*H53 -> 1748.8457 | J53: =I53/C53/D53 -> 6.6762576 | K53: 5726 | L53: =K53/C53/24 -> 7.6962366 | M53: =IF((J53/L53)>1,1,J53/L53) -> 0.86747043 | N53: =1-E53*M53 -> 0.69457812 | O53: =K53-I53 -> 3977.1543 | P53: =K53*N53 -> 3977.1543 | Q53: =C53*'Rate Codes'!$D$7 -> 53.490035 | R53: =P53*'Rate Codes'!$D$8 -> 51.51608 | S53: =SUM(Q53:R53) -> 105.00611 | T53: =P53*'Rate Codes'!$D$8 -> 51.51608 | U53: =(O53)*'Billing Rate'!$B$1 -> 270.44649 | V53: =S53+T53 -> 156.52219 | W53: =U53+S53+T53 -> 426.96869 | X53: =(IF(U53>0,U53,0)+V53)*0.05 -> 21.348434 | Y53: =W53+X53 -> 448.31712
B54: Feb | C54: 28 | D54: 9.9167 | E54: =D54/24 -> 0.41319583 | F54: =24-D54 -> 14.0833 | G54: =F54/24 -> 0.58680417 | H54: 0.046207319 | I54: =H$51*H54 -> 2958.6485 | J54: =I54/C54/D54 -> 10.655361 | K54: 5279 | L54: =K54/C54/24 -> 7.8556548 | M54: =IF((J54/L54)>1,1,J54/L54) -> 1 | N54: =1-E54*M54 -> 0.58680417 | O54: =K54-I54 -> 2320.3515 | P54: =K54*N54 -> 3097.7392 | Q54: =C54*'Rate Codes'!$D$7 -> 48.31358 | R54: =P54*'Rate Codes'!$D$8 -> 40.125016 | S54: =SUM(Q54:R54) -> 88.438596 | T54: =P54*'Rate Codes'!$D$8 -> 40.125016 | U54: =(O54)*'Billing Rate'!$B$1 -> 157.7839 | V54: =S54+T54 -> 128.56361 | W54: =U54+S54+T54 -> 286.34752 | X54: =(IF(U54>0,U54,0)+V54)*0.05 -> 14.317376 | Y54: =W54+X54 -> 300.66489
B55: Mar | C55: 31 | D55: 11.8 | E55: =D55/24 -> 0.49166667 | F55: =24-D55 -> 12.2 | G55: =F55/24 -> 0.50833333 | H55: 0.085008316 | I55: =H$51*H55 -> 5443.0712 | J55: =I55/C55/D55 -> 14.87991 | K55: 4991 | L55: =K55/C55/24 -> 6.7083333 | M55: =IF((J55/L55)>1,1,J55/L55) -> 1 | N55: =1-E55*M55 -> 0.50833333 | O55: =K55-I55 -> -452.07117 | P55: =K55*N55 -> 2537.0917 | Q55: =C55*'Rate Codes'!$D$7 -> 53.490035 | R55: =P55*'Rate Codes'!$D$8 -> 32.862948 | S55: =SUM(Q55:R55) -> 86.352983 | T55: =P55*'Rate Codes'!$D$8 -> 32.862948 | U55: =(O55)*'Billing Rate'!$B$1 -> -30.74084 | V55: =S55+T55 -> 119.21593 | W55: =U55+S55+T55 -> 88.475092 | X55: =(IF(U55>0,U55,0)+V55)*0.05 -> 5.9607966 | Y55: =W55+X55 -> 94.435889
B56: Apr | C56: 30 | D56: 13.8 | E56: =D56/24 -> 0.575 | F56: =24-D56 -> 10.2 | G56: =F56/24 -> 0.425 | H56: 0.10877317 | I56: =H$51*H56 -> 6964.7319 | J56: =I56/C56/D56 -> 16.823024 | K56: 4952 | L56: =K56/C56/24 -> 6.8777778 | M56: =IF((J56/L56)>1,1,J56/L56) -> 1 | N56: =1-E56*M56 -> 0.425 | O56: =K56-I56 -> -2012.7319 | P56: =K56*N56 -> 2104.6 | Q56: =C56*'Rate Codes'!$D$7 -> 51.76455 | R56: =P56*'Rate Codes'!$D$8 -> 27.260884 | S56: =SUM(Q56:R56) -> 79.025434 | T56: =P56*'Rate Codes'!$D$8 -> 27.260884 | U56: =(O56)*'Billing Rate'!$B$1 -> -136.86577 | V56: =S56+T56 -> 106.28632 | W56: =U56+S56+T56 -> -30.579453 | X56: =(IF(U56>0,U56,0)+V56)*0.05 -> 5.3143159 | Y56: =W56+X56 -> -25.265137
B57: May | C57: 31 | D57: 15.5333 | E57: =D57/24 -> 0.64722083 | F57: =24-D57 -> 8.4667 | G57: =F57/24 -> 0.35277917 | H57: 0.12817426 | I57: =H$51*H57 -> 8206.9809 | J57: =I57/C57/D57 -> 17.043469 | K57: 5559 | L57: =K57/C57/24 -> 7.4717742 | M57: =IF((J57/L57)>1,1,J57/L57) -> 1 | N57: =1-E57*M57 -> 0.35277917 | O57: =K57-I57 -> -2647.9809 | P57: =K57*N57 -> 1961.0994 | Q57: =C57*'Rate Codes'!$D$7 -> 53.490035 | R57: =P57*'Rate Codes'!$D$8 -> 25.40212 | S57: =SUM(Q57:R57) -> 78.892155 | T57: =P57*'Rate Codes'!$D$8 -> 25.40212 | U57: =(O57)*'Billing Rate'!$B$1 -> -180.0627 | V57: =S57+T57 -> 104.29428 | W57: =U57+S57+T57 -> -75.768426 | X57: =(IF(U57>0,U57,0)+V57)*0.05 -> 5.2147138 | Y57: =W57+X57 -> -70.553713
B58: Jun | C58: 30 | D58: 16.4667 | E58: =D58/24 -> 0.6861125 | F58: =24-D58 -> 7.5333 | G58: =F58/24 -> 0.3138875 | H58: 0.12548608 | I58: =H$51*H58 -> 8034.857 | J58: =I58/C58/D58 -> 16.26486 | K58: 4964 | L58: =K58/C58/24 -> 6.8944444 | M58: =IF((J58/L58)>1,1,J58/L58) -> 1 | N58: =1-E58*M58 -> 0.3138875 | O58: =K58-I58 -> -3070.857 | P58: =K58*N58 -> 1558.1375 | Q58: =C58*'Rate Codes'!$D$7 -> 51.76455 | R58: =P58*'Rate Codes'!$D$8 -> 20.182556 | S58: =SUM(Q58:R58) -> 71.947106 | T58: =P58*'Rate Codes'!$D$8 -> 20.182556 | U58: =(O58)*'Billing Rate'!$B$1 -> -208.81828 | V58: =S58+T58 -> 92.129661 | W58: =U58+S58+T58 -> -116.68862 | X58: =(IF(U58>0,U58,0)+V58)*0.05 -> 4.6064831 | Y58: =W58+X58 -> -112.08213
B59: Jul | C59: 31 | D59: 16.05 | E59: =D59/24 -> 0.66875 | F59: =24-D59 -> 7.95 | G59: =F59/24 -> 0.33125 | H59: 0.14494931 | I59: =H$51*H59 -> 9281.0851 | J59: =I59/C59/D59 -> 18.653573 | K59: 6634 | L59: =K59/C59/24 -> 8.9166667 | M59: =IF((J59/L59)>1,1,J59/L59) -> 1 | N59: =1-E59*M59 -> 0.33125 | O59: =K59-I59 -> -2647.0851 | P59: =K59*N59 -> 2197.5125 | Q59: =C59*'Rate Codes'!$D$7 -> 53.490035 | R59: =P59*'Rate Codes'!$D$8 -> 28.464379 | S59: =SUM(Q59:R59) -> 81.954414 | T59: =P59*'Rate Codes'!$D$8 -> 28.464379 | U59: =(O59)*'Billing Rate'!$B$1 -> -180.00179 | V59: =S59+T59 -> 110.41879 | W59: =U59+S59+T59 -> -69.582993 | X59: =(IF(U59>0,U59,0)+V59)*0.05 -> 5.5209397 | Y59: =W59+X59 -> -64.062053
B60: Aug | C60: 31 | D60: 14.5167 | E60: =D60/24 -> 0.6048625 | F60: =24-D60 -> 9.4833 | G60: =F60/24 -> 0.3951375 | H60: 0.12469524 | I60: =H$51*H60 -> 7984.2197 | J60: =I60/C60/D60 -> 17.742013 | K60: 5909 | L60: =K60/C60/24 -> 7.9422043 | M60: =IF((J60/L60)>1,1,J60/L60) -> 1 | N60: =1-E60*M60 -> 0.3951375 | O60: =K60-I60 -> -2075.2197 | P60: =K60*N60 -> 2334.8675 | Q60: =C60*'Rate Codes'!$D$7 -> 53.490035 | R60: =P60*'Rate Codes'!$D$8 -> 30.243539 | S60: =SUM(Q60:R60) -> 83.733574 | T60: =P60*'Rate Codes'!$D$8 -> 30.243539 | U60: =(O60)*'Billing Rate'!$B$1 -> -141.11494 | V60: =S60+T60 -> 113.97711 | W60: =U60+S60+T60 -> -27.137826 | X60: =(IF(U60>0,U60,0)+V60)*0.05 -> 5.6988556 | Y60: =W60+X60 -> -21.43897
B61: Sep | C61: 30 | D61: 12.5833 | E61: =D61/24 -> 0.52430417 | F61: =24-D61 -> 11.4167 | G61: =F61/24 -> 0.47569583 | H61: 0.098258031 | I61: =H$51*H61 -> 6291.4486 | J61: =I61/C61/D61 -> 16.666133 | K61: 5270 | L61: =K61/C61/24 -> 7.3194444 | M61: =IF((J61/L61)>1,1,J61/L61) -> 1 | N61: =1-E61*M61 -> 0.47569583 | O61: =K61-I61 -> -1021.4486 | P61: =K61*N61 -> 2506.917 | Q61: =C61*'Rate Codes'!$D$7 -> 51.76455 | R61: =P61*'Rate Codes'!$D$8 -> 32.472096 | S61: =SUM(Q61:R61) -> 84.236646 | T61: =P61*'Rate Codes'!$D$8 -> 32.472096 | U61: =(O61)*'Billing Rate'!$B$1 -> -69.458508 | V61: =S61+T61 -> 116.70874 | W61: =U61+S61+T61 -> 47.250235 | X61: =(IF(U61>0,U61,0)+V61)*0.05 -> 5.8354371 | Y61: =W61+X61 -> 53.085672
B62: Oct | C62: 31 | D62: 10.5833 | E62: =D62/24 -> 0.44097083 | F62: =24-D62 -> 13.4167 | G62: =F62/24 -> 0.55902917 | H62: 0.068404439 | I62: =H$51*H62 -> 4379.9271 | J62: =I62/C62/D62 -> 13.350087 | K62: 5946 | L62: =K62/C62/24 -> 7.9919355 | M62: =IF((J62/L62)>1,1,J62/L62) -> 1 | N62: =1-E62*M62 -> 0.55902917 | O62: =K62-I62 -> 1566.0729 | P62: =K62*N62 -> 3323.9874 | Q62: =C62*'Rate Codes'!$D$7 -> 53.490035 | R62: =P62*'Rate Codes'!$D$8 -> 43.055609 | S62: =SUM(Q62:R62) -> 96.545644 | T62: =P62*'Rate Codes'!$D$8 -> 43.055609 | U62: =(O62)*'Billing Rate'!$B$1 -> 106.49296 | V62: =S62+T62 -> 139.60125 | W62: =U62+S62+T62 -> 246.09421 | X62: =(IF(U62>0,U62,0)+V62)*0.05 -> 12.304711 | Y62: =W62+X62 -> 258.39892
B63: Nov | C63: 30 | D63: 8.85 | E63: =D63/24 -> 0.36875 | F63: =24-D63 -> 15.15 | G63: =F63/24 -> 0.63125 | H63: 0.027140805 | I63: =H$51*H63 -> 1737.8221 | J63: =I63/C63/D63 -> 6.5454695 | K63: 5587 | L63: =K63/C63/24 -> 7.7597222 | M63: =IF((J63/L63)>1,1,J63/L63) -> 0.84351853 | N63: =1-E63*M63 -> 0.68895254 | O63: =K63-I63 -> 3849.1779 | P63: =K63*N63 -> 3849.1779 | Q63: =C63*'Rate Codes'!$D$7 -> 51.76455 | R63: =P63*'Rate Codes'!$D$8 -> 49.858401 | S63: =SUM(Q63:R63) -> 101.62295 | T63: =P63*'Rate Codes'!$D$8 -> 49.858401 | U63: =(O63)*'Billing Rate'!$B$1 -> 261.74409 | V63: =S63+T63 -> 151.48135 | W63: =U63+S63+T63 -> 413.22545 | X63: =(IF(U63>0,U63,0)+V63)*0.05 -> 20.661272 | Y63: =W63+X63 -> 433.88672
B64: Dec | C64: 31 | D64: 7.9667 | E64: =D64/24 -> 0.33194583 | F64: =24-D64 -> 16.0333 | G64: =F64/24 -> 0.66805417 | H64: 0.015590053 | I64: =H$51*H64 -> 998.22901 | J64: =I64/C64/D64 -> 4.0419416 | K64: 5490 | L64: =K64/C64/24 -> 7.3790323 | M64: =IF((J64/L64)>1,1,J64/L64) -> 0.54776039 | N64: =1-E64*M64 -> 0.81817322 | O64: =K64-I64 -> 4491.771 | P64: =K64*N64 -> 4491.771 | Q64: =C64*'Rate Codes'!$D$7 -> 53.490035 | R64: =P64*'Rate Codes'!$D$8 -> 58.18191 | S64: =SUM(Q64:R64) -> 111.67194 | T64: =P64*'Rate Codes'!$D$8 -> 58.18191 | U64: =(O64)*'Billing Rate'!$B$1 -> 305.44043 | V64: =S64+T64 -> 169.85385 | W64: =U64+S64+T64 -> 475.29428 | X64: =(IF(U64>0,U64,0)+V64)*0.05 -> 23.764714 | Y64: =W64+X64 -> 499.059
B65: Total | H65: =SUM(H53:H64) -> 1 | I65: =SUM(I53:I64) -> 64029.867 | K65: =SUM(K53:K64) -> 66307 | O65: =SUM(O53:O64) -> 2277.1331 | P65: =SUM(P53:P64) -> 33940.055 | Q65: =SUM(Q53:Q64) -> 629.80202 | R65: =SUM(R53:R64) -> 439.62554 | S65: =SUM(S53:S64) -> 1069.4276 | T65: =SUM(T53:T64) -> 439.62554 | U65: =SUM(U53:U64) -> 154.84505 | V65: =S65+T65 -> 1509.0531 | W65: =SUM(W53:W64) -> 1663.8982 | X65: =SUM(X53:X64) -> 130.54805 | Y65: =SUM(Y53:Y64) -> 1794.4462
A67: 4 | B67: Annual Generation | H67: =$H$1* POWER((1 -$O$1),A67) -> 63709.718 | I67: Percent of Load | K67: =H67/K81 -> 0.96082944 | O67: Uncovered Load | P67: =1-K67 -> 0.039170562 | Q67: Distribution | T67: Transmission
B68: Month | C68: Days | D68: Daylight Hours (decimal) | E68: Light % | F68: Night Hours | G68: Night % | H68: Generation % | I68: Generation | J68: Average Power (kW) | K68: Load kWh | L68: Average Load (kW) | M68: Import Coverage | N68: Import Factor | O68: Net kWh | P68: Import | Q68: Facilities Charge | R68: Useage Charge | S68: Total | T68: Variable Charge | U68: Consumption | V68: T&D Total | W68: Charges Total | X68: Tax | Y68: Total
B69: Jan | C69: 31 | D69: 8.45 | E69: =D69/24 -> 0.35208333 | F69: =24-D69 -> 15.55 | G69: =F69/24 -> 0.64791667 | H69: 0.027312968 | I69: =H$67*H69 -> 1740.1015 | J69: =I69/C69/D69 -> 6.6428763 | K69: 5726 | L69: =K69/C69/24 -> 7.6962366 | M69: =IF((J69/L69)>1,1,J69/L69) -> 0.86313308 | N69: =1-E69*M69 -> 0.69610523 | O69: =K69-I69 -> 3985.8985 | P69: =K69*N69 -> 3985.8985 | Q69: =C69*'Rate Codes'!$D$7 -> 53.490035 | R69: =P69*'Rate Codes'!$D$8 -> 51.629344 | S69: =SUM(Q69:R69) -> 105.11938 | T69: =P69*'Rate Codes'!$D$8 -> 51.629344 | U69: =(O69)*'Billing Rate'!$B$1 -> 271.0411 | V69: =S69+T69 -> 156.74872 | W69: =U69+S69+T69 -> 427.78982 | X69: =(IF(U69>0,U69,0)+V69)*0.05 -> 21.389491 | Y69: =W69+X69 -> 449.17931
B70: Feb | C70: 28 | D70: 9.9167 | E70: =D70/24 -> 0.41319583 | F70: =24-D70 -> 14.0833 | G70: =F70/24 -> 0.58680417 | H70: 0.046207319 | I70: =H$67*H70 -> 2943.8552 | J70: =I70/C70/D70 -> 10.602084 | K70: 5279 | L70: =K70/C70/24 -> 7.8556548 | M70: =IF((J70/L70)>1,1,J70/L70) -> 1 | N70: =1-E70*M70 -> 0.58680417 | O70: =K70-I70 -> 2335.1448 | P70: =K70*N70 -> 3097.7392 | Q70: =C70*'Rate Codes'!$D$7 -> 48.31358 | R70: =P70*'Rate Codes'!$D$8 -> 40.125016 | S70: =SUM(Q70:R70) -> 88.438596 | T70: =P70*'Rate Codes'!$D$8 -> 40.125016 | U70: =(O70)*'Billing Rate'!$B$1 -> 158.78985 | V70: =S70+T70 -> 128.56361 | W70: =U70+S70+T70 -> 287.35346 | X70: =(IF(U70>0,U70,0)+V70)*0.05 -> 14.367673 | Y70: =W70+X70 -> 301.72113
B71: Mar | C71: 31 | D71: 11.8 | E71: =D71/24 -> 0.49166667 | F71: =24-D71 -> 12.2 | G71: =F71/24 -> 0.50833333 | H71: 0.085008316 | I71: =H$67*H71 -> 5415.8558 | J71: =I71/C71/D71 -> 14.805511 | K71: 4991 | L71: =K71/C71/24 -> 6.7083333 | M71: =IF((J71/L71)>1,1,J71/L71) -> 1 | N71: =1-E71*M71 -> 0.50833333 | O71: =K71-I71 -> -424.85582 | P71: =K71*N71 -> 2537.0917 | Q71: =C71*'Rate Codes'!$D$7 -> 53.490035 | R71: =P71*'Rate Codes'!$D$8 -> 32.862948 | S71: =SUM(Q71:R71) -> 86.352983 | T71: =P71*'Rate Codes'!$D$8 -> 32.862948 | U71: =(O71)*'Billing Rate'!$B$1 -> -28.890196 | V71: =S71+T71 -> 119.21593 | W71: =U71+S71+T71 -> 90.325736 | X71: =(IF(U71>0,U71,0)+V71)*0.05 -> 5.9607966 | Y71: =W71+X71 -> 96.286533
B72: Apr | C72: 30 | D72: 13.8 | E72: =D72/24 -> 0.575 | F72: =24-D72 -> 10.2 | G72: =F72/24 -> 0.425 | H72: 0.10877317 | I72: =H$67*H72 -> 6929.9083 | J72: =I72/C72/D72 -> 16.738909 | K72: 4952 | L72: =K72/C72/24 -> 6.8777778 | M72: =IF((J72/L72)>1,1,J72/L72) -> 1 | N72: =1-E72*M72 -> 0.425 | O72: =K72-I72 -> -1977.9083 | P72: =K72*N72 -> 2104.6 | Q72: =C72*'Rate Codes'!$D$7 -> 51.76455 | R72: =P72*'Rate Codes'!$D$8 -> 27.260884 | S72: =SUM(Q72:R72) -> 79.025434 | T72: =P72*'Rate Codes'!$D$8 -> 27.260884 | U72: =(O72)*'Billing Rate'!$B$1 -> -134.49776 | V72: =S72+T72 -> 106.28632 | W72: =U72+S72+T72 -> -28.211444 | X72: =(IF(U72>0,U72,0)+V72)*0.05 -> 5.3143159 | Y72: =W72+X72 -> -22.897128
B73: May | C73: 31 | D73: 15.5333 | E73: =D73/24 -> 0.64722083 | F73: =24-D73 -> 8.4667 | G73: =F73/24 -> 0.35277917 | H73: 0.12817426 | I73: =H$67*H73 -> 8165.946 | J73: =I73/C73/D73 -> 16.958252 | K73: 5559 | L73: =K73/C73/24 -> 7.4717742 | M73: =IF((J73/L73)>1,1,J73/L73) -> 1 | N73: =1-E73*M73 -> 0.35277917 | O73: =K73-I73 -> -2606.946 | P73: =K73*N73 -> 1961.0994 | Q73: =C73*'Rate Codes'!$D$7 -> 53.490035 | R73: =P73*'Rate Codes'!$D$8 -> 25.40212 | S73: =SUM(Q73:R73) -> 78.892155 | T73: =P73*'Rate Codes'!$D$8 -> 25.40212 | U73: =(O73)*'Billing Rate'!$B$1 -> -177.27233 | V73: =S73+T73 -> 104.29428 | W73: =U73+S73+T73 -> -72.978053 | X73: =(IF(U73>0,U73,0)+V73)*0.05 -> 5.2147138 | Y73: =W73+X73 -> -67.763339
B74: Jun | C74: 30 | D74: 16.4667 | E74: =D74/24 -> 0.6861125 | F74: =24-D74 -> 7.5333 | G74: =F74/24 -> 0.3138875 | H74: 0.12548608 | I74: =H$67*H74 -> 7994.6828 | J74: =I74/C74/D74 -> 16.183536 | K74: 4964 | L74: =K74/C74/24 -> 6.8944444 | M74: =IF((J74/L74)>1,1,J74/L74) -> 1 | N74: =1-E74*M74 -> 0.3138875 | O74: =K74-I74 -> -3030.6828 | P74: =K74*N74 -> 1558.1375 | Q74: =C74*'Rate Codes'!$D$7 -> 51.76455 | R74: =P74*'Rate Codes'!$D$8 -> 20.182556 | S74: =SUM(Q74:R74) -> 71.947106 | T74: =P74*'Rate Codes'!$D$8 -> 20.182556 | U74: =(O74)*'Billing Rate'!$B$1 -> -206.08643 | V74: =S74+T74 -> 92.129661 | W74: =U74+S74+T74 -> -113.95677 | X74: =(IF(U74>0,U74,0)+V74)*0.05 -> 4.6064831 | Y74: =W74+X74 -> -109.35028
B75: Jul | C75: 31 | D75: 16.05 | E75: =D75/24 -> 0.66875 | F75: =24-D75 -> 7.95 | G75: =F75/24 -> 0.33125 | H75: 0.14494931 | I75: =H$67*H75 -> 9234.6797 | J75: =I75/C75/D75 -> 18.560305 | K75: 6634 | L75: =K75/C75/24 -> 8.9166667 | M75: =IF((J75/L75)>1,1,J75/L75) -> 1 | N75: =1-E75*M75 -> 0.33125 | O75: =K75-I75 -> -2600.6797 | P75: =K75*N75 -> 2197.5125 | Q75: =C75*'Rate Codes'!$D$7 -> 53.490035 | R75: =P75*'Rate Codes'!$D$8 -> 28.464379 | S75: =SUM(Q75:R75) -> 81.954414 | T75: =P75*'Rate Codes'!$D$8 -> 28.464379 | U75: =(O75)*'Billing Rate'!$B$1 -> -176.84622 | V75: =S75+T75 -> 110.41879 | W75: =U75+S75+T75 -> -66.427424 | X75: =(IF(U75>0,U75,0)+V75)*0.05 -> 5.5209397 | Y75: =W75+X75 -> -60.906484
B76: Aug | C76: 31 | D76: 14.5167 | E76: =D76/24 -> 0.6048625 | F76: =24-D76 -> 9.4833 | G76: =F76/24 -> 0.3951375 | H76: 0.12469524 | I76: =H$67*H76 -> 7944.2986 | J76: =I76/C76/D76 -> 17.653302 | K76: 5909 | L76: =K76/C76/24 -> 7.9422043 | M76: =IF((J76/L76)>1,1,J76/L76) -> 1 | N76: =1-E76*M76 -> 0.3951375 | O76: =K76-I76 -> -2035.2986 | P76: =K76*N76 -> 2334.8675 | Q76: =C76*'Rate Codes'!$D$7 -> 53.490035 | R76: =P76*'Rate Codes'!$D$8 -> 30.243539 | S76: =SUM(Q76:R76) -> 83.733574 | T76: =P76*'Rate Codes'!$D$8 -> 30.243539 | U76: =(O76)*'Billing Rate'!$B$1 -> -138.4003 | V76: =S76+T76 -> 113.97711 | W76: =U76+S76+T76 -> -24.423191 | X76: =(IF(U76>0,U76,0)+V76)*0.05 -> 5.6988556 | Y76: =W76+X76 -> -18.724335
B77: Sep | C77: 30 | D77: 12.5833 | E77: =D77/24 -> 0.52430417 | F77: =24-D77 -> 11.4167 | G77: =F77/24 -> 0.47569583 | H77: 0.098258031 | I77: =H$67*H77 -> 6259.9914 | J77: =I77/C77/D77 -> 16.582803 | K77: 5270 | L77: =K77/C77/24 -> 7.3194444 | M77: =IF((J77/L77)>1,1,J77/L77) -> 1 | N77: =1-E77*M77 -> 0.47569583 | O77: =K77-I77 -> -989.9914 | P77: =K77*N77 -> 2506.917 | Q77: =C77*'Rate Codes'!$D$7 -> 51.76455 | R77: =P77*'Rate Codes'!$D$8 -> 32.472096 | S77: =SUM(Q77:R77) -> 84.236646 | T77: =P77*'Rate Codes'!$D$8 -> 32.472096 | U77: =(O77)*'Billing Rate'!$B$1 -> -67.319415 | V77: =S77+T77 -> 116.70874 | W77: =U77+S77+T77 -> 49.389328 | X77: =(IF(U77>0,U77,0)+V77)*0.05 -> 5.8354371 | Y77: =W77+X77 -> 55.224765
B78: Oct | C78: 31 | D78: 10.5833 | E78: =D78/24 -> 0.44097083 | F78: =24-D78 -> 13.4167 | G78: =F78/24 -> 0.55902917 | H78: 0.068404439 | I78: =H$67*H78 -> 4358.0275 | J78: =I78/C78/D78 -> 13.283336 | K78: 5946 | L78: =K78/C78/24 -> 7.9919355 | M78: =IF((J78/L78)>1,1,J78/L78) -> 1 | N78: =1-E78*M78 -> 0.55902917 | O78: =K78-I78 -> 1587.9725 | P78: =K78*N78 -> 3323.9874 | Q78: =C78*'Rate Codes'!$D$7 -> 53.490035 | R78: =P78*'Rate Codes'!$D$8 -> 43.055609 | S78: =SUM(Q78:R78) -> 96.545644 | T78: =P78*'Rate Codes'!$D$8 -> 43.055609 | U78: =(O78)*'Billing Rate'!$B$1 -> 107.98213 | V78: =S78+T78 -> 139.60125 | W78: =U78+S78+T78 -> 247.58339 | X78: =(IF(U78>0,U78,0)+V78)*0.05 -> 12.379169 | Y78: =W78+X78 -> 259.96255
